Workbook

Sheet All Critical Part
A1: Item Number | B1: Item Description | C1: Mesin | D1: Min Qty | E1: Max Qty | F1: =IFERROR(__xludf.DUMMYFUNCTION("ArrayFormula(IF(LEN(A:A),if(ROW(A:A)=1,""Stok"",if(isna(vlookup(A:A,importrange(""https://docs.google.com/spreadsheets/d/1xC-uAlt1jPkVMJk3mS5BBJv2KXQQM32TIOguKnEzvGo/edit?gid=2055262123#gid=2055262123"",""Inventory Tarikan Oracle!A:D""),4,0)),0,VLOOKUP(A:"&"A,importrange(""https://docs.google.com/spreadsheets/d/1xC-uAlt1jPkVMJk3mS5BBJv2KXQQM32TIOguKnEzvGo/edit?gid=2055262123#gid=2055262123"",""Inventory Tarikan Oracle!A:D""),4,0))),))"),"Stok") -> Stok | G1: {=IF(LEN(A:A),if(ROW(A:A)=1,"Status",if(F:F<D:D,"Kurang",if(F:F=D:D,"Sama","Lebih"))),)} -> Status | H1: Aktif/Tidak | I1: Notes 1 | J1: Notes 2 | K1: {=IF(LEN(A:A),if(ROW(A:A)=1,"Rekomendasi Min Stok",if(P:P="AKTIF",Roundup((L:L/12*1)+(0.25*(L:L/12)),0),0)),)} -> Rekomendasi Min Stok | L1: {=IF(LEN(A:A),if(ROW(A:A)=1,"Rekomendasi Max Stok",if(P:P="AKTIF",Roundup(U:U,0),0)),)} -> Rekomendasi Max Stok | M1: =IFERROR(__xludf.DUMMYFUNCTION("MAP(A1:A883, B1:B883, C1:C883, LAMBDA(item, desc, mesin, IF(ROW(item)=1, ""Kategori Barang"", IF(ISBLANK(item), """", LET( text_desc, LOWER(desc), IF(REGEXMATCH(text_desc, ""inverter|valve|valv|plc|motor|pump|pompa|transducer|transmitter|sensor|contro"&"l unit|cylinder|silinder|controller|servo|driver|breaker|mcb|contactor|module|hepa|fan|blower|transformer|encoder|gearbox|thermostat|solenoid|vfd|chiller|flowmeter|pressure gauge""), ""Critical Sparepart"", IF(REGEXMATCH(text_desc, ""o-ring|oring|o ring"&"|seal|gasket|bearing|baut|nut|screw|fitting|pipe|pipa|selang|hose|cleaner|filter|lamp|lampu|fuse|belt|v-belt|cable|kabel|tape|isolasi|grease|oli|oil|elbow|tee|socket|plug|clamp|ribbon|jarum|needle|cam follow""), ""Fast Moving / Consumable"", ""General S"&"parepart"")) )))))"),"Kategori Barang") -> Kategori Barang | N1: {=MAP(M1:M883, LAMBDA(kat, IF(ROW(kat)=1, "Threshold Usia (Bulan)", IF(OR(ISBLANK(kat), kat=""), "", IF(kat="Critical Sparepart", 36, IF(kat="Fast Moving / Consumable", 18, 24)) ))))} -> Threshold Usia (Bulan) | O1: {=MAP(A1:A883, LAMBDA(item, IF(ROW(item)=1, "Tanggal Transaksi Terakhir", IF(ISBLANK(item), "", LET( tgl_pr, IFERROR(MAXIFS('Data PR'!R:R, 'Data PR'!D:D, item), DATE(2000,1,1)), tgl_spr, IFERROR(MAXIFS('Data SPR'!L:L, 'Data SPR'!C:C, item), DATE(2000,1,1)), MAX(tgl_pr, tgl_spr) )))))} -> Tanggal Transaksi Terakhir | P1: {=MAP(A1:A883, N1:N883, O1:O883, LAMBDA(item, threshold, tgl, IF(ROW(item)=1, "Status Aktif/Dead Stok", IF(ISBLANK(item), "", IF(OR(ISBLANK(tgl), tgl=DATE(2000,1,1)), "TIDAK AKTIF", IF(DATEDIF(tgl, TODAY(), "M") <= threshold, "AKTIF", "TIDAK AKTIF"))))))} -> Status Aktif/Dead Stok | Q1: {=MAP(A1:A883, LAMBDA(item, IF(ROW(item)=1, "Rate PR Setahun", IF(ISBLANK(item), "", LET( total_qty, SUMIF('Data PR'!D:D, item, 'Data PR'!F:F), tgl_raw, IFERROR(MINIFS('Data PR'!R:R, 'Data PR'!D:D, item), TODAY()), tgl_pertama, IF(tgl_raw=0, TODAY(), tgl_raw), durasi_bulan, MAX(1, IFERROR(DATEDIF(tgl_pertama, TODAY(), "M"), 1)), IF(total_qty = 0, 0, ROUND((total_qty / durasi_bulan) * 12, 0)) )))))} -> Rate PR Setahun | R1: {=MAP(A1:A883, LAMBDA(item, IF(ROW(item)=1, "Rate SPR Setahun", IF(ISBLANK(item), "", LET( total_qty, SUMIF('Data SPR'!C:C, item, 'Data SPR'!E:E), tgl_raw, IFERROR(MINIFS('Data SPR'!M:M, 'Data SPR'!C:C, item), DATE(2023,1,1)), tgl_pertama, MAX(DATE(2023,1,1), tgl_raw), durasi_bulan, MAX(1, IFERROR(DATEDIF(tgl_pertama, TODAY(), "M"), 1)), IF(total_qty = 0, 0, (total_qty / durasi_bulan) * 12) )))))} -> Rate SPR Setahun | S1: {=MAP(A1:A883, LAMBDA(item, IF(ROW(item)=1, "Total Beli 1 Tahun Terakhir", IF(ISBLANK(item), "", SUMIFS('Data PR'!F:F, 'Data PR'!D:D, item, 'Data PR'!R:R, ">="&(TODAY()-365)) ))))} -> Total Beli 1 Tahun Terakhir | T1: {=IF(LEN(A:A),if(ROW(A:A)=1,"Rata-rata Tertimbang (Bobot PR 70% + SPR 30%)",IF(R:R>0, (Q:Q * 0.7) + (R:R * 0.3), Q:Q)),)} -> Rata-rata Tertimbang (Bobot PR 70% + SPR 30%) | U1: {=MAP(A1:A883, S1:S883, T1:T883, LAMBDA(item, q, r, IF(ROW(item)=1, "Rekomendasi Max Berdasarkan Tren Per Tahun", IF(ISBLANK(item), "", IF(q > r, q, r)))))} -> Rekomendasi Max Berdasarkan Tren Per Tahun
A2: O-50834-00 | B2: Autoclave Fedegari FOF / 6 AC - P/N. GM805664 Pressure Transducer and Mouting Par Replaces CD230046 | C2: Autoclave | D2: 1 | E2: 2 | F2: =IFERROR(__xludf.DUMMYFUNCTION("""COMPUTED_VALUE"""),0.0) -> 0 | G2: Kurang | H2: Aktif | I2: Discontinue | J2: - | K2: 0 | L2: 0 | M2: =IFERROR(__xludf.DUMMYFUNCTION("""COMPUTED_VALUE"""),"Critical Sparepart") -> Critical Sparepart | N2: 36 | O2: 0 | P2: TIDAK AKTIF | Q2: 0 | R2: 0 | S2: 0 | T2: 0 | U2: 0
A3: O-52922-00 | B3: Autoclave Fedegari FOF / 6 AC - Temperaure transmitter; IPAQ-L Plus 70IPLP0001; | C3: Autoclave | D3: 1 | E3: 2 | F3: =IFERROR(__xludf.DUMMYFUNCTION("""COMPUTED_VALUE"""),0.0) -> 0 | G3: Kurang | H3: Inactive | I3: Inactive | J3: - | K3: 0 | L3: 0 | M3: =IFERROR(__xludf.DUMMYFUNCTION("""COMPUTED_VALUE"""),"Critical Sparepart") -> Critical Sparepart | N3: 36 | O3: 0 | P3: TIDAK AKTIF | Q3: 0 | R3: 0 | S3: 0 | T3: 0 | U3: 0
A4: O-18687-00 | B4: Autoclave Fedegari FVA2/A1 NB2963AT - DN10/DN16 CLAMP P/N: GM100017; ; ; | C4: Autoclave | D4: 3 | E4: 6 | F4: =IFERROR(__xludf.DUMMYFUNCTION("""COMPUTED_VALUE"""),8.0) -> 8 | G4: Lebih | H4: Aktif | I4: - | J4: - | K4: 0 | L4: 0 | M4: =IFERROR(__xludf.DUMMYFUNCTION("""COMPUTED_VALUE"""),"Fast Moving / Consumable") -> Fast Moving / Consumable | N4: 18 | O4: 45009 | P4: TIDAK AKTIF | Q4: 2 | R4: 0 | S4: 0 | T4: 2 | U4: 2
A5: O-18688-00 | B5: Autoclave Fedegari FVA2/A1 NB2963AT - DN20/DN22 CLAMP P/N: GM100067; ; ; | C5: Autoclave | D5: 3 | E5: 6 | F5: =IFERROR(__xludf.DUMMYFUNCTION("""COMPUTED_VALUE"""),3.0) -> 3 | G5: Sama | H5: Aktif | I5: - | J5: - | K5: 1 | L5: 1 | M5: =IFERROR(__xludf.DUMMYFUNCTION("""COMPUTED_VALUE"""),"Fast Moving / Consumable") -> Fast Moving / Consumable | N5: 18 | O5: 45989 | P5: AKTIF | Q5: 1 | R5: 0.54545455 | S5: 0 | T5: 0.86363636 | U5: 0.86363636
A6: O-18690-00 | B6: Autoclave Fedegari FVA2/A1 NB2963AT - DN48/DN50 CLAMP P/N: GM100049; ; ; | C6: Autoclave | D6: 3 | E6: 6 | F6: =IFERROR(__xludf.DUMMYFUNCTION("""COMPUTED_VALUE"""),5.0) -> 5 | G6: Lebih | H6: Aktif | I6: - | J6: - | K6: 0 | L6: 0 | M6: =IFERROR(__xludf.DUMMYFUNCTION("""COMPUTED_VALUE"""),"Fast Moving / Consumable") -> Fast Moving / Consumable | N6: 18 | O6: 45009 | P6: TIDAK AKTIF | Q6: 1 | R6: 0 | S6: 0 | T6: 1 | U6: 1
A7: O-18686-00 | B7: Autoclave Fedegari FVA2/A1 NB2963AT - DN6-8 CLAMP P/N: GM100029; ; ; | C7: Autoclave | D7: 3 | E7: 6 | F7: =IFERROR(__xludf.DUMMYFUNCTION("""COMPUTED_VALUE"""),3.0) -> 3 | G7: Sama | H7: Aktif | I7: - | J7: - | K7: 0 | L7: 0 | M7: =IFERROR(__xludf.DUMMYFUNCTION("""COMPUTED_VALUE"""),"Fast Moving / Consumable") -> Fast Moving / Consumable | N7: 18 | O7: 45009 | P7: TIDAK AKTIF | Q7: 1 | R7: 0 | S7: 0 | T7: 1 | U7: 1
A8: O-16731-00 | B8: Autoclave Fedegari FVA2/A1 NB2963AT - KIT Ricambi Valv. DN10 ON-OFF FEDEGARI ASIA PTE LTD P/N : KK000301 pc | C8: Autoclave | D8: 8 | E8: 16 | F8: =IFERROR(__xludf.DUMMYFUNCTION("""COMPUTED_VALUE"""),0.0) -> 0 | G8: Kurang | H8: Aktif | I8: - | J8: - | K8: 1 | L8: 8 | M8: =IFERROR(__xludf.DUMMYFUNCTION("""COMPUTED_VALUE"""),"Critical Sparepart") -> Critical Sparepart | N8: 36 | O8: 46234 | P8: AKTIF | Q8: 7 | R8: 9.2727273 | S8: 5 | T8: 7.6818182 | U8: 7.6818182
A9: O-16732-00 | B9: Autoclave Fedegari FVA2/A1 NB2963AT - KIT Ricambi Valv. DN10 ON-OFF FEDEGARI ASIA PTE LTD P/N : KS000025 pc | C9: Autoclave | D9: 4 | E9: 20 | F9: =IFERROR(__xludf.DUMMYFUNCTION("""COMPUTED_VALUE"""),3.0) -> 3 | G9: Kurang | H9: Aktif | I9: - | J9: - | K9: 3 | L9: 20 | M9: =IFERROR(__xludf.DUMMYFUNCTION("""COMPUTED_VALUE"""),"Critical Sparepart") -> Critical Sparepart | N9: 36 | O9: 46234 | P9: AKTIF | Q9: 5 | R9: 4.9090909 | S9: 20 | T9: 4.9727273 | U9: 20
A10: P-13714-00 | B10: Autoclave Fedegari FVA2/A1 NB2963AT - Oring Viton 29 x 22 x 3.5 mm; ; ; | C10: Autoclave | D10: 10 | E10: 20 | F10: =IFERROR(__xludf.DUMMYFUNCTION("""COMPUTED_VALUE"""),0.0) -> 0 | G10: Kurang | H10: Inactive | I10: Inactive | J10: - | K10: 0 | L10: 0 | M10: =IFERROR(__xludf.DUMMYFUNCTION("""COMPUTED_VALUE"""),"Fast Moving / Consumable") -> Fast Moving / Consumable | N10: 18 | O10: 45261 | P10: TIDAK AKTIF | Q10: 1 | R10: 1.3636364 | S10: 0 | T10: 1.1090909 | U10: 1.1090909
A11: O-20982-00 | B11: Autoclave FVA2/A1 - SILICONE GASKET FO-5 900X1300 | C11: Autoclave | D11: 1 | E11: 2 | F11: =IFERROR(__xludf.DUMMYFUNCTION("""COMPUTED_VALUE"""),1.0) -> 1 | G11: Sama | H11: Aktif | I11: - | J11: - | K11: 1 | L11: 1 | M11: =IFERROR(__xludf.DUMMYFUNCTION("""COMPUTED_VALUE"""),"Fast Moving / Consumable") -> Fast Moving / Consumable | N11: 18 | O11: 45960 | P11: AKTIF | Q11: 1 | R11: 0 | S11: 1 | T11: 1 | U11: 1
A12: - | B12: Autoclave Service NA2247AU - AUTODIAGNOSIS ON CLEAN STEAM LINE, Fedegari, GP400045, , , | C12: Autoclave | D12: - | E12: - | F12: =IFERROR(__xludf.DUMMYFUNCTION("""COMPUTED_VALUE"""),0.0) -> 0 | G12: Kurang | H12: - | I12: Setara | J12: Setara dengan O-53442-00 | K12: 4 | L12: 31 | M12: =IFERROR(__xludf.DUMMYFUNCTION("""COMPUTED_VALUE"""),"General Sparepart") -> General Sparepart | N12: 24 | O12: 46260 | P12: AKTIF | Q12: 0 | R12: 100.63636 | S12: 0 | T12: 30.190909 | U12: 30.190909
A13: O-18692-00 | B13: Autoclave Service NA2247AU - Blind size F1, Fedegari, , , Size F1, | C13: Autoclave | D13: 1 | E13: 3 | F13: =IFERROR(__xludf.DUMMYFUNCTION("""COMPUTED_VALUE"""),1.0) -> 1 | G13: Sama | H13: Aktif | I13: - | J13: - | K13: 0 | L13: 0 | M13: =IFERROR(__xludf.DUMMYFUNCTION("""COMPUTED_VALUE"""),"General Sparepart") -> General Sparepart | N13: 24 | O13: 45009 | P13: TIDAK AKTIF | Q13: 1 | R13: 0 | S13: 0 | T13: 1 | U13: 1
A14: O-18693-00 | B14: Autoclave Service NA2247AU - Blind size F2, Fedegari, , , Size F2, | C14: Autoclave | D14: 1 | E14: 3 | F14: =IFERROR(__xludf.DUMMYFUNCTION("""COMPUTED_VALUE"""),3.0) -> 3 | G14: Lebih | H14: Aktif | I14: - | J14: - | K14: 0 | L14: 0 | M14: =IFERROR(__xludf.DUMMYFUNCTION("""COMPUTED_VALUE"""),"General Sparepart") -> General Sparepart | N14: 24 | O14: 45009 | P14: TIDAK AKTIF | Q14: 1 | R14: 0 | S14: 0 | T14: 1 | U14: 1
A15: O-18694-00 | B15: Autoclave Service NA2247AU - Blind size F3, Fedegari, , , Size F3, | C15: Autoclave | D15: 1 | E15: 3 | F15: =IFERROR(__xludf.DUMMYFUNCTION("""COMPUTED_VALUE"""),2.0) -> 2 | G15: Lebih | H15: Aktif | I15: - | J15: - | K15: 0 | L15: 0 | M15: =IFERROR(__xludf.DUMMYFUNCTION("""COMPUTED_VALUE"""),"General Sparepart") -> General Sparepart | N15: 24 | O15: 45009 | P15: TIDAK AKTIF | Q15: 1 | R15: 0 | S15: 0 | T15: 1 | U15: 1
A16: O-21124-00 | B16: Autoclave Service NA2247AU - O ring 15.47x3.53 | C16: Autoclave | D16: 5 | E16: 10 | F16: =IFERROR(__xludf.DUMMYFUNCTION("""COMPUTED_VALUE"""),5.0) -> 5 | G16: Sama | H16: Aktif | I16: Setara | J16: Setara dengan O-15918-00 | K16: 1 | L16: 6 | M16: =IFERROR(__xludf.DUMMYFUNCTION("""COMPUTED_VALUE"""),"Fast Moving / Consumable") -> Fast Moving / Consumable | N16: 18 | O16: 45960 | P16: AKTIF | Q16: 6 | R16: 0 | S16: 5 | T16: 6 | U16: 6
A17: O-21125-00 | B17: Autoclave Service NA2247AU - O ring 34.52x3.53 | C17: Autoclave | D17: 5 | E17: 10 | F17: =IFERROR(__xludf.DUMMYFUNCTION("""COMPUTED_VALUE"""),5.0) -> 5 | G17: Sama | H17: Aktif | I17: Setara | J17: Setara dengan O-15914-00 | K17: 1 | L17: 6 | M17: =IFERROR(__xludf.DUMMYFUNCTION("""COMPUTED_VALUE"""),"Fast Moving / Consumable") -> Fast Moving / Consumable | N17: 18 | O17: 45960 | P17: AKTIF | Q17: 6 | R17: 0 | S17: 5 | T17: 6 | U17: 6
A18: O-53442-00 | B18: Autoclave Service NA2247AU - Pressure Switch Alco Controls PS3-AJR 0.8-1 bar Assy | C18: Autoclave | D18: 1 | E18: 2 | F18: =IFERROR(__xludf.DUMMYFUNCTION("""COMPUTED_VALUE"""),1.0) -> 1 | G18: Sama | H18: Aktif | I18: - | J18: - | K18: 1 | L18: 1 | M18: =IFERROR(__xludf.DUMMYFUNCTION("""COMPUTED_VALUE"""),"General Sparepart") -> General Sparepart | N18: 24 | O18: 45960 | P18: AKTIF | Q18: 1 | R18: 0 | S18: 1 | T18: 1 | U18: 1
A19: O-53441-00 | B19: Autoclave Service NA2247AU - Pressure Transducer MOD. PBMH 24 | C19: Autoclave | D19: 1 | E19: 2 | F19: =IFERROR(__xludf.DUMMYFUNCTION("""COMPUTED_VALUE"""),1.0) -> 1 | G19: Sama | H19: Aktif | I19: - | J19: - | K19: 1 | L19: 1 | M19: =IFERROR(__xludf.DUMMYFUNCTION("""COMPUTED_VALUE"""),"Critical Sparepart") -> Critical Sparepart | N19: 36 | O19: 45960 | P19: AKTIF | Q19: 1 | R19: 0 | S19: 1 | T19: 1 | U19: 1
A20: O-15917-00 | B20: Fedegari FVA2/A1 - CENTERING RING DN16 CLAMP; Code : PP100907; ; ; | C20: Autoclave | D20: 1 | E20: 1 | F20: =IFERROR(__xludf.DUMMYFUNCTION("""COMPUTED_VALUE"""),3.0) -> 3 | G20: Lebih | H20: Aktif | I20: - | J20: - | K20: 0 | L20: 0 | M20: =IFERROR(__xludf.DUMMYFUNCTION("""COMPUTED_VALUE"""),"Fast Moving / Consumable") -> Fast Moving / Consumable | N20: 18 | O20: 43153 | P20: TIDAK AKTIF | Q20: 1 | R20: 0 | S20: 0 | T20: 1 | U20: 1
A21: O-15913-00 | B21: Fedegari FVA2/A1 - CENTERING RING DN35 CLAMP; Code : PP100897; ; ; | C21: Autoclave | D21: 1 | E21: 2 | F21: =IFERROR(__xludf.DUMMYFUNCTION("""COMPUTED_VALUE"""),1.0) -> 1 | G21: Sama | H21: Aktif | I21: - | J21: - | K21: 0 | L21: 0 | M21: =IFERROR(__xludf.DUMMYFUNCTION("""COMPUTED_VALUE"""),"Fast Moving / Consumable") -> Fast Moving / Consumable | N21: 18 | O21: 43153 | P21: TIDAK AKTIF | Q21: 1 | R21: 0 | S21: 0 | T21: 1 | U21: 1
A22: O-15916-00 | B22: Fedegari FVA2/A1 - CLAMP DN10 1/2" (MICROCASTED); Code : GM100017; ; ; | C22: Autoclave | D22: 1 | E22: 1 | F22: =IFERROR(__xludf.DUMMYFUNCTION("""COMPUTED_VALUE"""),1.0) -> 1 | G22: Sama | H22: Aktif | I22: - | J22: - | K22: 0 | L22: 0 | M22: =IFERROR(__xludf.DUMMYFUNCTION("""COMPUTED_VALUE"""),"Fast Moving / Consumable") -> Fast Moving / Consumable | N22: 18 | O22: 43153 | P22: TIDAK AKTIF | Q22: 0 | R22: 0 | S22: 0 | T22: 0 | U22: 0
A23: O-15912-00 | B23: Fedegari FVA2/A1 - CLAMP DN34-DN35 (MICROCASTED); Code : GM100094; ; ; | C23: Autoclave | D23: 1 | E23: 2 | F23: =IFERROR(__xludf.DUMMYFUNCTION("""COMPUTED_VALUE"""),2.0) -> 2 | G23: Lebih | H23: Aktif | I23: - | J23: - | K23: 1 | L23: 2 | M23: =IFERROR(__xludf.DUMMYFUNCTION("""COMPUTED_VALUE"""),"Fast Moving / Consumable") -> Fast Moving / Consumable | N23: 18 | O23: 46085 | P23: AKTIF | Q23: 1 | R23: 0.27272727 | S23: 2 | T23: 0.78181818 | U23: 2
A24: O-15915-00 | B24: Fedegari FVA2/A1 - DN16 ASTM CAP; Code : PM102747; ; ; | C24: Autoclave | D24: 1 | E24: 1 | F24: =IFERROR(__xludf.DUMMYFUNCTION("""COMPUTED_VALUE"""),1.0) -> 1 | G24: Sama | H24: Aktif | I24: - | J24: - | K24: 0 | L24: 0 | M24: =IFERROR(__xludf.DUMMYFUNCTION("""COMPUTED_VALUE"""),"General Sparepart") -> General Sparepart | N24: 24 | O24: 45762 | P24: AKTIF | Q24: 0 | R24: 0 | S24: 0 | T24: 0 | U24: 0
A25: O-15918-00 | B25: Fedegari FVA2/A1 - O-RING 15.47x3.53 ; Code : CC150170; ; ; | C25: Autoclave | D25: 10 | E25: 20 | F25: =IFERROR(__xludf.DUMMYFUNCTION("""COMPUTED_VALUE"""),17.0) -> 17 | G25: Lebih | H25: Aktif | I25: - | J25: - | K25: 1 | L25: 3 | M25: =IFERROR(__xludf.DUMMYFUNCTION("""COMPUTED_VALUE"""),"Fast Moving / Consumable") -> Fast Moving / Consumable | N25: 18 | O25: 46234 | P25: AKTIF | Q25: 3 | R25: 1.3636364 | S25: 0 | T25: 2.5090909 | U25: 2.5090909
A26: O-15914-00 | B26: Fedegari FVA2/A1 - O-RING 34.52x3.53; Code : CC150171; ; ; | C26: Autoclave | D26: 10 | E26: 20 | F26: =IFERROR(__xludf.DUMMYFUNCTION("""COMPUTED_VALUE"""),15.0) -> 15 | G26: Lebih | H26: Aktif | I26: - | J26: - | K26: 1 | L26: 3 | M26: =IFERROR(__xludf.DUMMYFUNCTION("""COMPUTED_VALUE"""),"Fast Moving / Consumable") -> Fast Moving / Consumable | N26: 18 | O26: 46022 | P26: AKTIF | Q26: 3 | R26: 1.3636364 | S26: 0 | T26: 2.5090909 | U26: 2.5090909
A27: O-15911-00 | B27: Fedegari FVA2/A1 - TAPPO DN35 ASTM; Code : PM102749; ; ; | C27: Autoclave | D27: 4 | E27: 8 | F27: =IFERROR(__xludf.DUMMYFUNCTION("""COMPUTED_VALUE"""),5.0) -> 5 | G27: Lebih | H27: Aktif | I27: - | J27: - | K27: 0 | L27: 0 | M27: =IFERROR(__xludf.DUMMYFUNCTION("""COMPUTED_VALUE"""),"General Sparepart") -> General Sparepart | N27: 24 | O27: 45009 | P27: TIDAK AKTIF | Q27: 1 | R27: 0 | S27: 0 | T27: 1 | U27: 1
A28: P-15429-00 | B28: Fedegari FVA2/A1 S/N : NB2964AT - Cover Seal FVM-A/2 FOB2 (Code: PP600265); ; ; | C28: Autoclave | D28: 1 | E28: 4 | F28: =IFERROR(__xludf.DUMMYFUNCTION("""COMPUTED_VALUE"""),4.0) -> 4 | G28: Lebih | H28: Aktif | I28: - | J28: - | K28: 1 | L28: 2 | M28: =IFERROR(__xludf.DUMMYFUNCTION("""COMPUTED_VALUE"""),"Fast Moving / Consumable") -> Fast Moving / Consumable | N28: 18 | O28: 46043 | P28: AKTIF | Q28: 1 | R28: 0.54545455 | S28: 2 | T28: 0.86363636 | U28: 2
A29: O-17831-00 | B29: Gear Door Autoclave | C29: Autoclave | D29: 1 | E29: 2 | F29: =IFERROR(__xludf.DUMMYFUNCTION("""COMPUTED_VALUE"""),1.0) -> 1 | G29: Sama | H29: Aktif | I29: - | J29: - | K29: 1 | L29: 1 | M29: =IFERROR(__xludf.DUMMYFUNCTION("""COMPUTED_VALUE"""),"General Sparepart") -> General Sparepart | N29: 24 | O29: 46112 | P29: AKTIF | Q29: 1 | R29: 0.27272727 | S29: 0 | T29: 0.78181818 | U29: 0.78181818
A30: P-17361-00 | B30: O-ring EPDM 15 x 9 x 3 mm ; Brand : - ; P/N : - ; Pack Size : pcs | C30: Autoclave | D30: 10 | E30: 20 | F30: =IFERROR(__xludf.DUMMYFUNCTION("""COMPUTED_VALUE"""),20.0) -> 20 | G30: Lebih | H30: Aktif | I30: - | J30: - | K30: 2 | L30: 13 | M30: =IFERROR(__xludf.DUMMYFUNCTION("""COMPUTED_VALUE"""),"Fast Moving / Consumable") -> Fast Moving / Consumable | N30: 18 | O30: 46147 | P30: AKTIF | Q30: 7 | R30: 5.1818182 | S30: 13 | T30: 6.4545455 | U30: 13
A31: P-17359-00 | B31: O-ring EPDM 41.5 x 35 x 3.5 mm ; Brand : - ; P/N : - ; Pack Size : pcs | C31: Autoclave | D31: 10 | E31: 20 | F31: =IFERROR(__xludf.DUMMYFUNCTION("""COMPUTED_VALUE"""),19.0) -> 19 | G31: Lebih | H31: Aktif | I31: - | J31: - | K31: 1 | L31: 4 | M31: =IFERROR(__xludf.DUMMYFUNCTION("""COMPUTED_VALUE"""),"Fast Moving / Consumable") -> Fast Moving / Consumable | N31: 18 | O31: 45863 | P31: AKTIF | Q31: 5 | R31: 0.27272727 | S31: 0 | T31: 3.5818182 | U31: 3.5818182
A32: P-17272-00 | B32: O-ring Epdm 9 x 4 x 2,5 mm ; Brand : - ; P/N : - ; Pack Size : pcs | C32: Autoclave | D32: 10 | E32: 20 | F32: =IFERROR(__xludf.DUMMYFUNCTION("""COMPUTED_VALUE"""),64.0) -> 64 | G32: Lebih | H32: Aktif | I32: - | J32: - | K32: 2 | L32: 16 | M32: =IFERROR(__xludf.DUMMYFUNCTION("""COMPUTED_VALUE"""),"Fast Moving / Consumable") -> Fast Moving / Consumable | N32: 18 | O32: 45989 | P32: AKTIF | Q32: 21 | R32: 1.6363636 | S32: 0 | T32: 15.190909 | U32: 15.190909
A33: P-17273-00 | B33: O-ring Epdm 9 x 5 x 2 mm ; Brand : - ; P/N : - ; Pack Size : pcs | C33: Autoclave | D33: 10 | E33: 20 | F33: =IFERROR(__xludf.DUMMYFUNCTION("""COMPUTED_VALUE"""),13.0) -> 13 | G33: Lebih | H33: Aktif | I33: - | J33: - | K33: 1 | L33: 5 | M33: =IFERROR(__xludf.DUMMYFUNCTION("""COMPUTED_VALUE"""),"Fast Moving / Consumable") -> Fast Moving / Consumable | N33: 18 | O33: 45989 | P33: AKTIF | Q33: 6 | R33: 2.4545455 | S33: 0 | T33: 4.9363636 | U33: 4.9363636
A34: O-19339-00 | B34: Oring 2,5x6x11 mm, Material EPDM; ; ; | C34: Autoclave | D34: 10 | E34: 21 | F34: =IFERROR(__xludf.DUMMYFUNCTION("""COMPUTED_VALUE"""),19.0) -> 19 | G34: Lebih | H34: Aktif | I34: - | J34: - | K34: 2 | L34: 12 | M34: =IFERROR(__xludf.DUMMYFUNCTION("""COMPUTED_VALUE"""),"Fast Moving / Consumable") -> Fast Moving / Consumable | N34: 18 | O34: 45989 | P34: AKTIF | Q34: 14 | R34: 4.3636364 | S34: 0 | T34: 11.109091 | U34: 11.109091
A35: O-51743-00 | B35: SENSOR TEMPERATUR PT100 7 METER 4 WIRE; PART NO :PM600083 | C35: Autoclave | D35: 1 | E35: 2 | F35: =IFERROR(__xludf.DUMMYFUNCTION("""COMPUTED_VALUE"""),0.0) -> 0 | G35: Kurang | H35: Inactive | I35: Setara | J35: Setara dengan O-52278-00 | K35: 0 | L35: 0 | M35: =IFERROR(__xludf.DUMMYFUNCTION("""COMPUTED_VALUE"""),"Critical Sparepart") -> Critical Sparepart | N35: 36 | O35: 0 | P35: TIDAK AKTIF | Q35: 0 | R35: 0 | S35: 0 | T35: 0 | U35: 0
A36: O-51747-00 | B36: TEMPERATURE PROBE ;PRODUCT ; TE2/TE2R ; | C36: Autoclave | D36: 1 | E36: 2 | F36: =IFERROR(__xludf.DUMMYFUNCTION("""COMPUTED_VALUE"""),0.0) -> 0 | G36: Kurang | H36: Inactive | I36: Setara | J36: Pake Radix O-51920-00 | K36: 0 | L36: 0 | M36: =IFERROR(__xludf.DUMMYFUNCTION("""COMPUTED_VALUE"""),"General Sparepart") -> General Sparepart | N36: 24 | O36: 0 | P36: TIDAK AKTIF | Q36: 0 | R36: 0 | S36: 0 | T36: 0 | U36: 0
A37: O-51920-00 | B37: Temperature sensor PT100, 4 wire, class AA, Duplex, c/w 10m silicon cable Radix RAC241-D-10-PN; ; ; | C37: Autoclave | D37: 1 | E37: 6 | F37: =IFERROR(__xludf.DUMMYFUNCTION("""COMPUTED_VALUE"""),0.0) -> 0 | G37: Kurang | H37: Aktif | I37: Setara | J37: Setara dengan O-53568-00 | K37: 1 | L37: 1 | M37: =IFERROR(__xludf.DUMMYFUNCTION("""COMPUTED_VALUE"""),"Critical Sparepart") -> Critical Sparepart | N37: 36 | O37: 46022 | P37: AKTIF | Q37: 1 | R37: 0.81818182 | S37: 0 | T37: 0.94545455 | U37: 0.94545455
A38: O-53414-00 | B38: Fedegari FVA2/A1 - Transition joint RTD Sensor PT100 4Wire, Sx, 1/3 DIN, 5x70mm, SSL, 0-150 C 10M; Radix; RTJ201-1-C-S-3-0-NA-XNA-05-0070-10-Si-PN; 1 Pc | C38: Autoclave | D38: 2 | E38: 8 | F38: =IFERROR(__xludf.DUMMYFUNCTION("""COMPUTED_VALUE"""),0.0) -> 0 | G38: Kurang | H38: Aktif | I38: - | J38: GL2505051 | K38: 1 | L38: 7 | M38: =IFERROR(__xludf.DUMMYFUNCTION("""COMPUTED_VALUE"""),"Critical Sparepart") -> Critical Sparepart | N38: 36 | O38: 46260 | P38: AKTIF | Q38: 8 | R38: 1.0909091 | S38: 7 | T38: 5.9272727 | U38: 7
A39: P-10564-00 | B39: Bearing 6000 2RS H SKF | C39: Capping | D39: 10 | E39: 30 | F39: =IFERROR(__xludf.DUMMYFUNCTION("""COMPUTED_VALUE"""),40.0) -> 40 | G39: Lebih | H39: Aktif | I39: - | J39: 121703198 - APPROVED | K39: 1 | L39: 7 | M39: =IFERROR(__xludf.DUMMYFUNCTION("""COMPUTED_VALUE"""),"Fast Moving / Consumable") -> Fast Moving / Consumable | N39: 18 | O39: 45909 | P39: AKTIF | Q39: 9 | R39: 0.54545455 | S39: 0 | T39: 6.4636364 | U39: 6.4636364
A40: O-11181-00 | B40: Bearing 626-2Z | C40: Capping | D40: 10 | E40: 32 | F40: =IFERROR(__xludf.DUMMYFUNCTION("""COMPUTED_VALUE"""),110.0) -> 110 | G40: Lebih | H40: Aktif | I40: - | J40: - | K40: 3 | L40: 26 | M40: =IFERROR(__xludf.DUMMYFUNCTION("""COMPUTED_VALUE"""),"Fast Moving / Consumable") -> Fast Moving / Consumable | N40: 18 | O40: 46171 | P40: AKTIF | Q40: 26 | R40: 24.545455 | S40: 0 | T40: 25.563636 | U40: 25.563636
A41: O-17988-00 | B41: Cam Follow (Idle Pin); INA; KR16-X-PP-A; pc | C41: Capping | D41: 10 | E41: 10 | F41: =IFERROR(__xludf.DUMMYFUNCTION("""COMPUTED_VALUE"""),16.0) -> 16 | G41: Lebih | H41: Aktif | I41: - | J41: - | K41: 0 | L41: 0 | M41: =IFERROR(__xludf.DUMMYFUNCTION("""COMPUTED_VALUE"""),"Fast Moving / Consumable") -> Fast Moving / Consumable | N41: 18 | O41: 45565 | P41: TIDAK AKTIF | Q41: 4 | R41: 5.4545455 | S41: 0 | T41: 4.4363636 | U41: 4.4363636
A42: O-18962-00 | B42: Capping VCM200 - Adjuster Screw Blade; ; ; | C42: Capping | D42: 1 | E42: 1 | F42: =IFERROR(__xludf.DUMMYFUNCTION("""COMPUTED_VALUE"""),1.0) -> 1 | G42: Sama | H42: Aktif | I42: - | J42: GL2509450 | K42: 1 | L42: 3 | M42: =IFERROR(__xludf.DUMMYFUNCTION("""COMPUTED_VALUE"""),"Fast Moving / Consumable") -> Fast Moving / Consumable | N42: 18 | O42: 45874 | P42: AKTIF | Q42: 3 | R42: 2.7272727 | S42: 0 | T42: 2.9181818 | U42: 2.9181818
A43: O-20041-00 | B43: Capping VCM200 - Bearing NKIA5902; INA; ; | C43: Capping | D43: 20 | E43: 60 | F43: =IFERROR(__xludf.DUMMYFUNCTION("""COMPUTED_VALUE"""),40.0) -> 40 | G43: Lebih | H43: Aktif | I43: - | J43: 121703267 - INCOMPLETE | K43: 5 | L43: 40 | M43: =IFERROR(__xludf.DUMMYFUNCTION("""COMPUTED_VALUE"""),"Fast Moving / Consumable") -> Fast Moving / Consumable | N43: 18 | O43: 45928 | P43: AKTIF | Q43: 30 | R43: 0 | S43: 40 | T43: 30 | U43: 40
A44: O-18963-00 | B44: Capping VCM200 - Clamp Holder; ; ; | C44: Capping | D44: 1 | E44: 5 | F44: =IFERROR(__xludf.DUMMYFUNCTION("""COMPUTED_VALUE"""),1.0) -> 1 | G44: Sama | H44: Aktif | I44: - | J44: GL2509450 | K44: 1 | L44: 3 | M44: =IFERROR(__xludf.DUMMYFUNCTION("""COMPUTED_VALUE"""),"Fast Moving / Consumable") -> Fast Moving / Consumable | N44: 18 | O44: 45874 | P44: AKTIF | Q44: 3 | R44: 2.7272727 | S44: 0 | T44: 2.9181818 | U44: 2.9181818
A45: O-16706-00 | B45: Capping VCM200 - Coupling for Encoder NBK MST 32 | C45: Capping | D45: 1 | E45: 2 | F45: =IFERROR(__xludf.DUMMYFUNCTION("""COMPUTED_VALUE"""),2.0) -> 2 | G45: Lebih | H45: Aktif | I45: - | J45: 121703078 - APPROVED | K45: 1 | L45: 1 | M45: =IFERROR(__xludf.DUMMYFUNCTION("""COMPUTED_VALUE"""),"Critical Sparepart") -> Critical Sparepart | N45: 36 | O45: 45875 | P45: AKTIF | Q45: 1 | R45: 0 | S45: 0 | T45: 1 | U45: 1
A46: O-54163-00 | B46: Capping VCM200 - Fieldline Modular Bus Coupler; Steriline; P/N 201798; | C46: Capping | D46: 0 | E46: 1 | F46: =IFERROR(__xludf.DUMMYFUNCTION("""COMPUTED_VALUE"""),0.0) -> 0 | G46: Sama | H46: Aktif | I46: - | J46: - | K46: 0 | L46: 0 | M46: =IFERROR(__xludf.DUMMYFUNCTION("""COMPUTED_VALUE"""),"General Sparepart") -> General Sparepart | N46: 24 | O46: 0 | P46: TIDAK AKTIF | Q46: 0 | R46: 0 | S46: 0 | T46: 0 | U46: 0
A47: O-54164-00 | B47: Capping VCM200 - Fieldline Modular Device; Steriline; P/N 202024; | C47: Capping | D47: 0 | E47: 1 | F47: =IFERROR(__xludf.DUMMYFUNCTION("""COMPUTED_VALUE"""),1.0) -> 1 | G47: Lebih | H47: Aktif | I47: - | J47: - | K47: 0 | L47: 0 | M47: =IFERROR(__xludf.DUMMYFUNCTION("""COMPUTED_VALUE"""),"General Sparepart") -> General Sparepart | N47: 24 | O47: 45338 | P47: TIDAK AKTIF | Q47: 0 | R47: 0 | S47: 0 | T47: 0 | U47: 0
A48: O-19894-00 | B48: Capping VCM200 - Guide Starwheel Vial Pom hitam 319x329x17 mm; Custom; ; | C48: Capping | D48: 1 | E48: 2 | F48: =IFERROR(__xludf.DUMMYFUNCTION("""COMPUTED_VALUE"""),1.0) -> 1 | G48: Sama | H48: Aktif | I48: - | J48: GL2510476 | K48: 1 | L48: 1 | M48: =IFERROR(__xludf.DUMMYFUNCTION("""COMPUTED_VALUE"""),"General Sparepart") -> General Sparepart | N48: 24 | O48: 45928 | P48: AKTIF | Q48: 1 | R48: 0.27272727 | S48: 1 | T48: 0.78181818 | U48: 1
A49: O-18964-00 | B49: Capping VCM200 - Holder; ; ; | C49: Capping | D49: 1 | E49: 5 | F49: =IFERROR(__xludf.DUMMYFUNCTION("""COMPUTED_VALUE"""),1.0) -> 1 | G49: Sama | H49: Aktif | I49: - | J49: GL2509450 | K49: 1 | L49: 3 | M49: =IFERROR(__xludf.DUMMYFUNCTION("""COMPUTED_VALUE"""),"General Sparepart") -> General Sparepart | N49: 24 | O49: 45874 | P49: AKTIF | Q49: 3 | R49: 2.7272727 | S49: 0 | T49: 2.9181818 | U49: 2.9181818
A50: O-18120-00 | B50: Capping VCM200 - Lock Nut Cramping; ; ; | C50: Capping | D50: 1 | E50: 6 | F50: =IFERROR(__xludf.DUMMYFUNCTION("""COMPUTED_VALUE"""),5.0) -> 5 | G50: Lebih | H50: Aktif | I50: - | J50: GL2507039 | K50: 1 | L50: 5 | M50: =IFERROR(__xludf.DUMMYFUNCTION("""COMPUTED_VALUE"""),"Fast Moving / Consumable") -> Fast Moving / Consumable | N50: 18 | O50: 45831 | P50: AKTIF | Q50: 4 | R50: 4.0909091 | S50: 0 | T50: 4.0272727 | U50: 4.0272727
A51: O-20897-00 | B51: Capping VCM200 - Oring Silicone 2.5 x 30.50 x 30.50; Custom/Lokal; -; 1 Pc | C51: Capping | D51: 10 | E51: 30 | F51: =IFERROR(__xludf.DUMMYFUNCTION("""COMPUTED_VALUE"""),20.0) -> 20 | G51: Lebih | H51: Aktif | I51: - | J51: GL2508436 | K51: 2 | L51: 14 | M51: =IFERROR(__xludf.DUMMYFUNCTION("""COMPUTED_VALUE"""),"Fast Moving / Consumable") -> Fast Moving / Consumable | N51: 18 | O51: 46087 | P51: AKTIF | Q51: 19 | R51: 0.27272727 | S51: 11 | T51: 13.381818 | U51: 13.381818
A52: O-17073-00 | B52: Capping VCM200 - Plate P/n: 307790 | C52: Capping | D52: 1 | E52: 3 | F52: =IFERROR(__xludf.DUMMYFUNCTION("""COMPUTED_VALUE"""),2.0) -> 2 | G52: Lebih | H52: Aktif | I52: - | J52: - | K52: 1 | L52: 2 | M52: =IFERROR(__xludf.DUMMYFUNCTION("""COMPUTED_VALUE"""),"General Sparepart") -> General Sparepart | N52: 24 | O52: 45961 | P52: AKTIF | Q52: 2 | R52: 0.81818182 | S52: 0 | T52: 1.6454545 | U52: 1.6454545
A53: O-18966-00 | B53: Capping VCM200 - Ring Washer; ; ; | C53: Capping | D53: 1 | E53: 5 | F53: =IFERROR(__xludf.DUMMYFUNCTION("""COMPUTED_VALUE"""),1.0) -> 1 | G53: Sama | H53: Aktif | I53: - | J53: GL2509450 | K53: 1 | L53: 3 | M53: =IFERROR(__xludf.DUMMYFUNCTION("""COMPUTED_VALUE"""),"General Sparepart") -> General Sparepart | N53: 24 | O53: 45874 | P53: AKTIF | Q53: 3 | R53: 2.7272727 | S53: 0 | T53: 2.9181818 | U53: 2.9181818
A54: O-18344-00 | B54: Capping VCM200 - Roller trimmer D=48X18 inclination=7 for alucap D=20 | C54: Capping | D54: 2 | E54: 4 | F54: =IFERROR(__xludf.DUMMYFUNCTION("""COMPUTED_VALUE"""),0.0) -> 0 | G54: Kurang | H54: Aktif | I54: Hold | J54: - | K54: 1 | L54: 3 | M54: =IFERROR(__xludf.DUMMYFUNCTION("""COMPUTED_VALUE"""),"General Sparepart") -> General Sparepart | N54: 24 | O54: 45833 | P54: AKTIF | Q54: 3 | R54: 2.7272727 | S54: 0 | T54: 2.9181818 | U54: 2.9181818
A55: O-20950-00 | B55: Capping VCM200 - Silicone Sucker 01.10.10 | C55: Capping | D55: 20 | E55: 40 | F55: =IFERROR(__xludf.DUMMYFUNCTION("""COMPUTED_VALUE"""),0.0) -> 0 | G55: Kurang | H55: Aktif | I55: Setara | J55: Setara dengan O-15902-00 | K55: 0 | L55: 0 | M55: =IFERROR(__xludf.DUMMYFUNCTION("""COMPUTED_VALUE"""),"General Sparepart") -> General Sparepart | N55: 24 | O55: 0 | P55: TIDAK AKTIF | Q55: 0 | R55: 0 | S55: 0 | T55: 0 | U55: 0
A56: O-21091-00 | B56: Capping VCM200 - SILICONE SUCKER 01.11.16; | C56: Capping | D56: 10 | E56: 40 | F56: =IFERROR(__xludf.DUMMYFUNCTION("""COMPUTED_VALUE"""),0.0) -> 0 | G56: Kurang | H56: Aktif | I56: Setara | J56: Setara dengan O-18345-00 | K56: 0 | L56: 0 | M56: =IFERROR(__xludf.DUMMYFUNCTION("""COMPUTED_VALUE"""),"General Sparepart") -> General Sparepart | N56: 24 | O56: 0 | P56: TIDAK AKTIF | Q56: 0 | R56: 0 | S56: 0 | T56: 0 | U56: 0
A57: O-18965-00 | B57: Capping VCM200 - Spring Head; ; ; | C57: Capping | D57: 1 | E57: 5 | F57: =IFERROR(__xludf.DUMMYFUNCTION("""COMPUTED_VALUE"""),1.0) -> 1 | G57: Sama | H57: Aktif | I57: - | J57: GL2509450 | K57: 1 | L57: 3 | M57: =IFERROR(__xludf.DUMMYFUNCTION("""COMPUTED_VALUE"""),"General Sparepart") -> General Sparepart | N57: 24 | O57: 45874 | P57: AKTIF | Q57: 3 | R57: 2.7272727 | S57: 0 | T57: 2.9181818 | U57: 2.9181818
A58: O-19862-00 | B58: Capping VCM200 - Transfer Plate material SS304Custom | C58: Capping | D58: 10 | E58: 23 | F58: =IFERROR(__xludf.DUMMYFUNCTION("""COMPUTED_VALUE"""),20.0) -> 20 | G58: Lebih | H58: Aktif | I58: - | J58: GL2510476 | K58: 3 | L58: 20 | M58: =IFERROR(__xludf.DUMMYFUNCTION("""COMPUTED_VALUE"""),"General Sparepart") -> General Sparepart | N58: 24 | O58: 45928 | P58: AKTIF | Q58: 13 | R58: 0 | S58: 20 | T58: 13 | U58: 20
A59: O-18967-00 | B59: Capping VCM200 - Washer A; ; ; | C59: Capping | D59: 1 | E59: 5 | F59: =IFERROR(__xludf.DUMMYFUNCTION("""COMPUTED_VALUE"""),1.0) -> 1 | G59: Sama | H59: Aktif | I59: - | J59: GL2509450 | K59: 1 | L59: 3 | M59: =IFERROR(__xludf.DUMMYFUNCTION("""COMPUTED_VALUE"""),"General Sparepart") -> General Sparepart | N59: 24 | O59: 45874 | P59: AKTIF | Q59: 3 | R59: 2.7272727 | S59: 0 | T59: 2.9181818 | U59: 2.9181818
A60: O-18968-00 | B60: Capping VCM200 - Washer B; ; ; | C60: Capping | D60: 1 | E60: 1 | F60: =IFERROR(__xludf.DUMMYFUNCTION("""COMPUTED_VALUE"""),1.0) -> 1 | G60: Sama | H60: Aktif | I60: - | J60: GL2509450 | K60: 1 | L60: 3 | M60: =IFERROR(__xludf.DUMMYFUNCTION("""COMPUTED_VALUE"""),"General Sparepart") -> General Sparepart | N60: 24 | O60: 45874 | P60: AKTIF | Q60: 3 | R60: 2.7272727 | S60: 0 | T60: 2.9181818 | U60: 2.9181818
A61: O-15567-00 | B61: CAPS MINIMUM LOAD SENSOR ; HIGH PRECISION OPTICAL FIBER FU-7F | C61: Capping | D61: 1 | E61: 1 | F61: =IFERROR(__xludf.DUMMYFUNCTION("""COMPUTED_VALUE"""),0.0) -> 0 | G61: Kurang | H61: Inactive | I61: Setara | J61: Setara dengan O-53439-00 | K61: 0 | L61: 0 | M61: =IFERROR(__xludf.DUMMYFUNCTION("""COMPUTED_VALUE"""),"Critical Sparepart") -> Critical Sparepart | N61: 36 | O61: 0 | P61: TIDAK AKTIF | Q61: 0 | R61: 0 | S61: 0 | T61: 0 | U61: 0
A62: O-51651-00 | B62: CSP 12 s.n. 82.017 - Gear box Bonfiglioli type W63 U24 P80 B5 B3 RB | C62: Capping | D62: 0 | E62: 0 | F62: =IFERROR(__xludf.DUMMYFUNCTION("""COMPUTED_VALUE"""),0.0) -> 0 | G62: Sama | H62: Inactive | I62: Inactive | J62: - | K62: 0 | L62: 0 | M62: =IFERROR(__xludf.DUMMYFUNCTION("""COMPUTED_VALUE"""),"Fast Moving / Consumable") -> Fast Moving / Consumable | N62: 18 | O62: 0 | P62: TIDAK AKTIF | Q62: 0 | R62: 0 | S62: 0 | T62: 0 | U62: 0
A63: O-15629-00 | B63: ENCODER ;Sick Stegmann;ABSOLUTE ENCODER A4A08192 GRAY RADIAL CONNECTOR | C63: Capping | D63: 0 | E63: 1 | F63: =IFERROR(__xludf.DUMMYFUNCTION("""COMPUTED_VALUE"""),0.0) -> 0 | G63: Sama | H63: Inactive | I63: Inactive | J63: Tidak di Stok | K63: 0 | L63: 0 | M63: =IFERROR(__xludf.DUMMYFUNCTION("""COMPUTED_VALUE"""),"Critical Sparepart") -> Critical Sparepart | N63: 36 | O63: 0 | P63: TIDAK AKTIF | Q63: 0 | R63: 0 | S63: 0 | T63: 0 | U63: 0
A64: P-19410-00 | B64: General - Bearing NATA5902; IKO; -; 1 pc | C64: Capping | D64: 20 | E64: 40 | F64: =IFERROR(__xludf.DUMMYFUNCTION("""COMPUTED_VALUE"""),22.0) -> 22 | G64: Lebih | H64: Aktif | I64: - | J64: - | K64: 3 | L64: 20 | M64: =IFERROR(__xludf.DUMMYFUNCTION("""COMPUTED_VALUE"""),"Fast Moving / Consumable") -> Fast Moving / Consumable | N64: 18 | O64: 45975 | P64: AKTIF | Q64: 22 | R64: 4.9090909 | S64: 20 | T64: 16.872727 | U64: 20
A65: O-53439-00 | B65: General - Photoelectric Fiber Sensor Head | C65: Capping | D65: 1 | E65: 2 | F65: =IFERROR(__xludf.DUMMYFUNCTION("""COMPUTED_VALUE"""),1.0) -> 1 | G65: Sama | H65: Aktif | I65: - | J65: GL2511302 | K65: 1 | L65: 1 | M65: =IFERROR(__xludf.DUMMYFUNCTION("""COMPUTED_VALUE"""),"Critical Sparepart") -> Critical Sparepart | N65: 36 | O65: 45960 | P65: AKTIF | Q65: 1 | R65: 0 | S65: 1 | T65: 1 | U65: 1
A66: O-15615-00 | B66: HIGH PRECISION OPTICAL FIBER 10MM WIDTH FU-12; PART NO :201020 | C66: Capping | D66: 1 | E66: 1 | F66: =IFERROR(__xludf.DUMMYFUNCTION("""COMPUTED_VALUE"""),0.0) -> 0 | G66: Kurang | H66: Inactive | I66: Setara | J66: Setara dengan O-15619-00 | K66: 0 | L66: 0 | M66: =IFERROR(__xludf.DUMMYFUNCTION("""COMPUTED_VALUE"""),"General Sparepart") -> General Sparepart | N66: 24 | O66: 0 | P66: TIDAK AKTIF | Q66: 0 | R66: 0 | S66: 0 | T66: 0 | U66: 0
A67: O-15616-00 | B67: HIGH PRECISION OPTICAL FIBER FU-7F; PART NO :201061 | C67: Capping | D67: 1 | E67: 1 | F67: =IFERROR(__xludf.DUMMYFUNCTION("""COMPUTED_VALUE"""),0.0) -> 0 | G67: Kurang | H67: Inactive | I67: Setara | J67: Setara dengan O-15567-00 | K67: 0 | L67: 0 | M67: =IFERROR(__xludf.DUMMYFUNCTION("""COMPUTED_VALUE"""),"General Sparepart") -> General Sparepart | N67: 24 | O67: 0 | P67: TIDAK AKTIF | Q67: 0 | R67: 0 | S67: 0 | T67: 0 | U67: 0
A68: O-15620-00 | B68: HIGH PRECISION OPTICAL FIBER SUPER TOUGH FLEX FIBERS-FU67V; VIAL CHECK AT INFEED SENSOR ; | C68: Capping | D68: 1 | E68: 1 | F68: =IFERROR(__xludf.DUMMYFUNCTION("""COMPUTED_VALUE"""),0.0) -> 0 | G68: Kurang | H68: Inactive | I68: Setara | J68: Sama dengan O-15713-00 Item Inactive | K68: 0 | L68: 0 | M68: =IFERROR(__xludf.DUMMYFUNCTION("""COMPUTED_VALUE"""),"Critical Sparepart") -> Critical Sparepart | N68: 36 | O68: 0 | P68: TIDAK AKTIF | Q68: 0 | R68: 0 | S68: 0 | T68: 0 | U68: 0
A69: O-15731-00 | B69: KEYENCE; HIGH PRECISION OPTICAL FIBER SUPER TOUGH FLEX FIBERS-FU67V; PART NO :201021 | C69: Capping | D69: 0 | E69: 1 | F69: =IFERROR(__xludf.DUMMYFUNCTION("""COMPUTED_VALUE"""),0.0) -> 0 | G69: Sama | H69: Inactive | I69: Inactive | J69: Tidak di Stok | K69: 0 | L69: 0 | M69: =IFERROR(__xludf.DUMMYFUNCTION("""COMPUTED_VALUE"""),"General Sparepart") -> General Sparepart | N69: 24 | O69: 0 | P69: TIDAK AKTIF | Q69: 0 | R69: 0 | S69: 0 | T69: 0 | U69: 0
A70: O-19005-00 | B70: Misumi - Linear Shaft PSFAA8-46-F11-P6-M3-N3; ; ; | C70: Capping | D70: 1 | E70: 5 | F70: =IFERROR(__xludf.DUMMYFUNCTION("""COMPUTED_VALUE"""),1.0) -> 1 | G70: Sama | H70: Aktif | I70: - | J70: GL2508437 | K70: 1 | L70: 3 | M70: =IFERROR(__xludf.DUMMYFUNCTION("""COMPUTED_VALUE"""),"General Sparepart") -> General Sparepart | N70: 24 | O70: 45875 | P70: AKTIF | Q70: 3 | R70: 2.7272727 | S70: 0 | T70: 2.9181818 | U70: 2.9181818
A71: O-15621-00 | B71: MOTOR AND REDUCTION GEAR, BONFIGLIOLI TYPE BN63B4 0.18 KW 50HZ 1320RPM, 3PHASE | C71: Capping | D71: 0 | E71: 1 | F71: =IFERROR(__xludf.DUMMYFUNCTION("""COMPUTED_VALUE"""),0.0) -> 0 | G71: Sama | H71: Inactive | I71: Inactive | J71: Tidak di Stok | K71: 0 | L71: 0 | M71: =IFERROR(__xludf.DUMMYFUNCTION("""COMPUTED_VALUE"""),"Critical Sparepart") -> Critical Sparepart | N71: 36 | O71: 0 | P71: TIDAK AKTIF | Q71: 0 | R71: 0 | S71: 0 | T71: 0 | U71: 0
A72: O-15595-00 | B72: MOTOR, BONFIGLIOLI TYPE BN63B4 0,18-0,21KW, 50-60HZ 1320RPM; | C72: Capping | D72: 0 | E72: 1 | F72: =IFERROR(__xludf.DUMMYFUNCTION("""COMPUTED_VALUE"""),0.0) -> 0 | G72: Sama | H72: Aktif | I72: - | J72: Setara dengan O-15621-00 | K72: 0 | L72: 0 | M72: =IFERROR(__xludf.DUMMYFUNCTION("""COMPUTED_VALUE"""),"Critical Sparepart") -> Critical Sparepart | N72: 36 | O72: 0 | P72: TIDAK AKTIF | Q72: 0 | R72: 0 | S72: 0 | T72: 0 | U72: 0
A73: O-18876-00 | B73: Oring Silicone Merah 40.6x37x1.8 mm; ; ; | C73: Capping | D73: 10 | E73: 20 | F73: =IFERROR(__xludf.DUMMYFUNCTION("""COMPUTED_VALUE"""),20.0) -> 20 | G73: Lebih | H73: Aktif | I73: - | J73: 121703275 - INCOMPLETE | K73: 3 | L73: 20 | M73: =IFERROR(__xludf.DUMMYFUNCTION("""COMPUTED_VALUE"""),"Fast Moving / Consumable") -> Fast Moving / Consumable | N73: 18 | O73: 45928 | P73: AKTIF | Q73: 7 | R73: 1.3636364 | S73: 20 | T73: 5.3090909 | U73: 20
A74: O-51652-00 | B74: Safety Sensor, Type : BNS 120-11z, 250mA, 3VA/W,100 VAC/DC,M12 x 1 K-ST; ; ; | C74: Capping | D74: 1 | E74: 2 | F74: =IFERROR(__xludf.DUMMYFUNCTION("""COMPUTED_VALUE"""),0.0) -> 0 | G74: Kurang | H74: Inactive | I74: Setara | J74: Setara dengan O-53392-00 | K74: 0 | L74: 0 | M74: =IFERROR(__xludf.DUMMYFUNCTION("""COMPUTED_VALUE"""),"Critical Sparepart") -> Critical Sparepart | N74: 36 | O74: 0 | P74: TIDAK AKTIF | Q74: 0 | R74: 0 | S74: 0 | T74: 0 | U74: 0
A75: O-15679-00 | B75: SECURITY PHOTOCELLS; PART NO :7209 | C75: Capping | D75: 0 | E75: 1 | F75: =IFERROR(__xludf.DUMMYFUNCTION("""COMPUTED_VALUE"""),0.0) -> 0 | G75: Sama | H75: Inactive | I75: Inactive | J75: Tidak di Stok | K75: 0 | L75: 0 | M75: =IFERROR(__xludf.DUMMYFUNCTION("""COMPUTED_VALUE"""),"General Sparepart") -> General Sparepart | N75: 24 | O75: 0 | P75: TIDAK AKTIF | Q75: 0 | R75: 0 | S75: 0 | T75: 0 | U75: 0
A76: O-51735-00 | B76: SENSOR OPTICAL FIBER, KEYENCE PNP OUTPUT CONNECTOR M8 FS-V31CP AMPLIFIER ; | C76: Capping | D76: 1 | E76: 1 | F76: =IFERROR(__xludf.DUMMYFUNCTION("""COMPUTED_VALUE"""),0.0) -> 0 | G76: Kurang | H76: Inactive | I76: Setara | J76: Setara dengan O-54115-00 | K76: 0 | L76: 0 | M76: =IFERROR(__xludf.DUMMYFUNCTION("""COMPUTED_VALUE"""),"Critical Sparepart") -> Critical Sparepart | N76: 36 | O76: 0 | P76: TIDAK AKTIF | Q76: 0 | R76: 0 | S76: 0 | T76: 0 | U76: 0
A77: O-18345-00 | B77: Silicon suction cup 01.11.16 PN: 202082; ; ; (20R) | C77: Capping | D77: 10 | E77: 100 | F77: =IFERROR(__xludf.DUMMYFUNCTION("""COMPUTED_VALUE"""),108.0) -> 108 | G77: Lebih | H77: Aktif | I77: - | J77: - | K77: 11 | L77: 100 | M77: =IFERROR(__xludf.DUMMYFUNCTION("""COMPUTED_VALUE"""),"General Sparepart") -> General Sparepart | N77: 24 | O77: 45974 | P77: AKTIF | Q77: 27 | R77: 2.7272727 | S77: 100 | T77: 19.718182 | U77: 100
A78: O-16007-00 | B78: Silicone Sucker 01.10.10; P/N : 201119; ; ; | C78: Capping | D78: 20 | E78: 40 | F78: =IFERROR(__xludf.DUMMYFUNCTION("""COMPUTED_VALUE"""),0.0) -> 0 | G78: Kurang | H78: Inactive | I78: Setara | J78: Setara dengan O-20950-00 | K78: 0 | L78: 0 | M78: =IFERROR(__xludf.DUMMYFUNCTION("""COMPUTED_VALUE"""),"General Sparepart") -> General Sparepart | N78: 24 | O78: 43185 | P78: TIDAK AKTIF | Q78: 4 | R78: 0 | S78: 0 | T78: 4 | U78: 4
A79: O-15696-00 | B79: SILICONE SUCKER 01.11.16; PART NO :202082 | C79: Capping | D79: 10 | E79: 40 | F79: =IFERROR(__xludf.DUMMYFUNCTION("""COMPUTED_VALUE"""),0.0) -> 0 | G79: Kurang | H79: Inactive | I79: Setara | J79: Setara dengan O-21091-00 | K79: 0 | L79: 0 | M79: =IFERROR(__xludf.DUMMYFUNCTION("""COMPUTED_VALUE"""),"General Sparepart") -> General Sparepart | N79: 24 | O79: 0 | P79: TIDAK AKTIF | Q79: 0 | R79: 0 | S79: 0 | T79: 0 | U79: 0
A80: O-15697-00 | B80: SILICONE SUCKER 01.16.20; PART NO :202370 | C80: Capping | D80: 10 | E80: 50 | F80: =IFERROR(__xludf.DUMMYFUNCTION("""COMPUTED_VALUE"""),55.0) -> 55 | G80: Lebih | H80: Aktif | I80: - | J80: - | K80: 6 | L80: 50 | M80: =IFERROR(__xludf.DUMMYFUNCTION("""COMPUTED_VALUE"""),"General Sparepart") -> General Sparepart | N80: 24 | O80: 46234 | P80: AKTIF | Q80: 16 | R80: 5.4545455 | S80: 50 | T80: 12.836364 | U80: 50
A81: O-15712-00 | B81: STOPPERS HOPPER MINIMUM LOAD SENSOR ; banner ; WORLD BEAM QS18VP6LAF250Q5 LASER ADJUSTABLE FIELD QS18VP6LAF250 | C81: Capping | D81: 1 | E81: 2 | F81: =IFERROR(__xludf.DUMMYFUNCTION("""COMPUTED_VALUE"""),0.0) -> 0 | G81: Kurang | H81: Inactive | I81: Setara | J81: sama dengan O-52884-00 | K81: 0 | L81: 0 | M81: =IFERROR(__xludf.DUMMYFUNCTION("""COMPUTED_VALUE"""),"Critical Sparepart") -> Critical Sparepart | N81: 36 | O81: 0 | P81: TIDAK AKTIF | Q81: 0 | R81: 0 | S81: 0 | T81: 0 | U81: 0
A82: O-15713-00 | B82: STOPPERS MINIMUM LOAD LANE 1 SENSOR ; KEYENCE ;HIGH PRECISION OPTICAL FIBER SUPER TOUGH FLEX FIBERS FU-67V | C82: Capping | D82: 1 | E82: 2 | F82: =IFERROR(__xludf.DUMMYFUNCTION("""COMPUTED_VALUE"""),0.0) -> 0 | G82: Kurang | H82: Inactive | I82: Setara | J82: Setara dengan O-54116-00 | K82: 0 | L82: 0 | M82: =IFERROR(__xludf.DUMMYFUNCTION("""COMPUTED_VALUE"""),"Critical Sparepart") -> Critical Sparepart | N82: 36 | O82: 0 | P82: TIDAK AKTIF | Q82: 0 | R82: 0 | S82: 0 | T82: 0 | U82: 0
A83: O-15714-00 | B83: STOPPERS MINIMUM LOAD LANE 1 SENSOR ; KEYENCE; AMPLIFIER SENSOR OPTICAL FIBER PNP OUTPUT CONNECTOR M8 FS-V31CP | C83: Capping | D83: 1 | E83: 2 | F83: =IFERROR(__xludf.DUMMYFUNCTION("""COMPUTED_VALUE"""),0.0) -> 0 | G83: Kurang | H83: Inactive | I83: Setara | J83: Setara dengan O-51735-00 | K83: 0 | L83: 0 | M83: =IFERROR(__xludf.DUMMYFUNCTION("""COMPUTED_VALUE"""),"Critical Sparepart") -> Critical Sparepart | N83: 36 | O83: 0 | P83: TIDAK AKTIF | Q83: 0 | R83: 0 | S83: 0 | T83: 0 | U83: 0
A84: O-15902-00 | B84: Suction Cup capping size 6R; P/N : 011010; ; ; | C84: Capping | D84: 6 | E84: 32 | F84: =IFERROR(__xludf.DUMMYFUNCTION("""COMPUTED_VALUE"""),107.0) -> 107 | G84: Lebih | H84: Aktif | I84: - | J84: - | K84: 3 | L84: 26 | M84: =IFERROR(__xludf.DUMMYFUNCTION("""COMPUTED_VALUE"""),"General Sparepart") -> General Sparepart | N84: 24 | O84: 46234 | P84: AKTIF | Q84: 28 | R84: 21.272727 | S84: 0 | T84: 25.981818 | U84: 25.981818
A85: O-51749-00 | B85: VIALS MAXIMUM LOAD SENSOR ; KEYENCE ; AMPLIFIER SENSOR OPTICAL FIBER PNP OUTPUT CONNECTOR M8 code: FS-V31CP; | C85: Capping | D85: 1 | E85: 1 | F85: =IFERROR(__xludf.DUMMYFUNCTION("""COMPUTED_VALUE"""),0.0) -> 0 | G85: Kurang | H85: Inactive | I85: Setara | J85: Setara dengan O-51735-00 | K85: 0 | L85: 0 | M85: =IFERROR(__xludf.DUMMYFUNCTION("""COMPUTED_VALUE"""),"Critical Sparepart") -> Critical Sparepart | N85: 36 | O85: 0 | P85: TIDAK AKTIF | Q85: 0 | R85: 0 | S85: 0 | T85: 0 | U85: 0
A86: O-53392-00 | B86: VIALS MAXIMUM LOAD SENSOR ; KEYENCE ; AMPLIFIER SENSOR OPTICAL FIBER PNP OUTPUT CONNECTOR M8 code: FS-V31CP; | C86: Capping | D86: 1 | E86: 8 | F86: =IFERROR(__xludf.DUMMYFUNCTION("""COMPUTED_VALUE"""),2.0) -> 2 | G86: Lebih | H86: Aktif | I86: - | J86: - | K86: 1 | L86: 6 | M86: =IFERROR(__xludf.DUMMYFUNCTION("""COMPUTED_VALUE"""),"Critical Sparepart") -> Critical Sparepart | N86: 36 | O86: 46147 | P86: AKTIF | Q86: 6 | R86: 0 | S86: 2 | T86: 6 | U86: 6
A87: O-16647-00 | B87: Washing RAR4 - Oring Silicone Merah 23x18x2.5 mm; ; ; | C87: Capping | D87: 40 | E87: 700 | F87: =IFERROR(__xludf.DUMMYFUNCTION("""COMPUTED_VALUE"""),391.0) -> 391 | G87: Lebih | H87: Aktif | I87: - | J87: - | K87: 73 | L87: 700 | M87: =IFERROR(__xludf.DUMMYFUNCTION("""COMPUTED_VALUE"""),"Fast Moving / Consumable") -> Fast Moving / Consumable | N87: 18 | O87: 46260 | P87: AKTIF | Q87: 189 | R87: 263.45455 | S87: 700 | T87: 211.33636 | U87: 700
A88: O-15569-00 | B88: CHAMBER AIR INLET PNEUMATIC VALVE ; VP3 ; | C88: cRABS | D88: 0 | E88: 1 | F88: =IFERROR(__xludf.DUMMYFUNCTION("""COMPUTED_VALUE"""),0.0) -> 0 | G88: Sama | H88: Inactive | I88: Inactive | J88: Tidak di Stok | K88: 0 | L88: 0 | M88: =IFERROR(__xludf.DUMMYFUNCTION("""COMPUTED_VALUE"""),"Critical Sparepart") -> Critical Sparepart | N88: 36 | O88: 0 | P88: TIDAK AKTIF | Q88: 0 | R88: 0 | S88: 0 | T88: 0 | U88: 0
A89: O-15570-00 | B89: CHAMBER PRESSURE TRANSDUCER ; TP ; | C89: cRABS | D89: 0 | E89: 1 | F89: =IFERROR(__xludf.DUMMYFUNCTION("""COMPUTED_VALUE"""),0.0) -> 0 | G89: Sama | H89: Inactive | I89: Inactive | J89: Tidak di Stok | K89: 0 | L89: 0 | M89: =IFERROR(__xludf.DUMMYFUNCTION("""COMPUTED_VALUE"""),"Critical Sparepart") -> Critical Sparepart | N89: 36 | O89: 0 | P89: TIDAK AKTIF | Q89: 0 | R89: 0 | S89: 0 | T89: 0 | U89: 0
A90: O-14621-00 | B90: Coil U2 11W 24VDC; Univer; c/n 5233; | C90: cRABS | D90: 1 | E90: 2 | F90: =IFERROR(__xludf.DUMMYFUNCTION("""COMPUTED_VALUE"""),4.0) -> 4 | G90: Lebih | H90: Inactive | I90: Inactive | J90: Ganti festo | K90: 0 | L90: 0 | M90: =IFERROR(__xludf.DUMMYFUNCTION("""COMPUTED_VALUE"""),"Fast Moving / Consumable") -> Fast Moving / Consumable | N90: 18 | O90: 43161 | P90: TIDAK AKTIF | Q90: 0 | R90: 0 | S90: 0 | T90: 0 | U90: 0
A91: O-17030-00 | B91: cRABS Z064CR - Treaded Three Port Seat Valve VOBG320 3/4inch G | C91: cRABS | D91: 1 | E91: 2 | F91: =IFERROR(__xludf.DUMMYFUNCTION("""COMPUTED_VALUE"""),0.0) -> 0 | G91: Kurang | H91: Inactive | I91: Setara | J91: Setara dengan O-20951-00 | K91: 0 | L91: 0 | M91: =IFERROR(__xludf.DUMMYFUNCTION("""COMPUTED_VALUE"""),"Critical Sparepart") -> Critical Sparepart | N91: 36 | O91: 0 | P91: TIDAK AKTIF | Q91: 0 | R91: 0 | S91: 0 | T91: 0 | U91: 0
A92: O-53479-00 | B92: cRABS Z064CR - Chilled water Pump, DAB, 60150944, Three-phase pump type EVOPLUS, 80/180 XM power: 22 | C92: cRABS | D92: 0 | E92: 1 | F92: =IFERROR(__xludf.DUMMYFUNCTION("""COMPUTED_VALUE"""),0.0) -> 0 | G92: Sama | H92: Aktif | I92: - | J92: - | K92: 0 | L92: 0 | M92: =IFERROR(__xludf.DUMMYFUNCTION("""COMPUTED_VALUE"""),"Critical Sparepart") -> Critical Sparepart | N92: 36 | O92: 0 | P92: TIDAK AKTIF | Q92: 0 | R92: 0 | S92: 0 | T92: 0 | U92: 0
A93: O-53475-00 | B93: cRABS Z064CR - Cooling water three way Actuator, Coster, 28715, CLNV150, Linear actuator for three w | C93: cRABS | D93: 1 | E93: 1 | F93: =IFERROR(__xludf.DUMMYFUNCTION("""COMPUTED_VALUE"""),0.0) -> 0 | G93: Kurang | H93: Aktif | I93: - | J93: 121703511 | K93: 0 | L93: 0 | M93: =IFERROR(__xludf.DUMMYFUNCTION("""COMPUTED_VALUE"""),"Fast Moving / Consumable") -> Fast Moving / Consumable | N93: 18 | O93: 0 | P93: TIDAK AKTIF | Q93: 0 | R93: 0 | S93: 0 | T93: 0 | U93: 0
A94: O-53466-00 | B94: cRABS Z064CR - DOOR SAFETY SWITCHES ; SCHMERSAL ; MAGNET BPS-260 | C94: cRABS | D94: 1 | E94: 2 | F94: =IFERROR(__xludf.DUMMYFUNCTION("""COMPUTED_VALUE"""),1.0) -> 1 | G94: Sama | H94: Aktif | I94: - | J94: 121703438 | K94: 1 | L94: 1 | M94: =IFERROR(__xludf.DUMMYFUNCTION("""COMPUTED_VALUE"""),"General Sparepart") -> General Sparepart | N94: 24 | O94: 45960 | P94: AKTIF | Q94: 1 | R94: 0 | S94: 1 | T94: 1 | U94: 1
A95: O-53461-00 | B95: cRABS Z064CR - Pressure transmitter -50/ +200 Pa output 4-20 mA 24VDC Precision: +-1%; Model: PIZ (2 | C95: cRABS | D95: 1 | E95: 2 | F95: =IFERROR(__xludf.DUMMYFUNCTION("""COMPUTED_VALUE"""),0.0) -> 0 | G95: Kurang | H95: Aktif | I95: - | J95: 121703511 | K95: 0 | L95: 0 | M95: =IFERROR(__xludf.DUMMYFUNCTION("""COMPUTED_VALUE"""),"Critical Sparepart") -> Critical Sparepart | N95: 36 | O95: 0 | P95: TIDAK AKTIF | Q95: 0 | R95: 0 | S95: 0 | T95: 0 | U95: 0
A96: O-21126-00 | B96: cRABS Z064CR - Security PHOCELLS 7209 - plastic body; Protection P67; Receiver, max. di | C96: cRABS | D96: 1 | E96: 2 | F96: =IFERROR(__xludf.DUMMYFUNCTION("""COMPUTED_VALUE"""),0.0) -> 0 | G96: Kurang | H96: Aktif | I96: Discontinue | J96: - | K96: 0 | L96: 0 | M96: =IFERROR(__xludf.DUMMYFUNCTION("""COMPUTED_VALUE"""),"General Sparepart") -> General Sparepart | N96: 24 | O96: 0 | P96: TIDAK AKTIF | Q96: 0 | R96: 0 | S96: 0 | T96: 0 | U96: 0
A97: O-53465-00 | B97: cRABS Z064CR - SENSOR PROXIMITY M12 NON FLUSH SHORT PNP NO ; DATA LOGIC | C97: cRABS | D97: 1 | E97: 2 | F97: =IFERROR(__xludf.DUMMYFUNCTION("""COMPUTED_VALUE"""),1.0) -> 1 | G97: Sama | H97: Aktif | I97: - | J97: 121703490 | K97: 1 | L97: 1 | M97: =IFERROR(__xludf.DUMMYFUNCTION("""COMPUTED_VALUE"""),"Critical Sparepart") -> Critical Sparepart | N97: 36 | O97: 45974 | P97: AKTIF | Q97: 1 | R97: 0 | S97: 1 | T97: 1 | U97: 1
A98: O-53455-00 | B98: cRABS Z064CR - Supply Fan inverter, Ziehl Abegg Frequency converter PXDM6A | C98: cRABS | D98: 1 | E98: 2 | F98: =IFERROR(__xludf.DUMMYFUNCTION("""COMPUTED_VALUE"""),0.0) -> 0 | G98: Kurang | H98: Aktif | I98: - | J98: 121703511 | K98: 0 | L98: 0 | M98: =IFERROR(__xludf.DUMMYFUNCTION("""COMPUTED_VALUE"""),"Critical Sparepart") -> Critical Sparepart | N98: 36 | O98: 0 | P98: TIDAK AKTIF | Q98: 0 | R98: 0 | S98: 0 | T98: 0 | U98: 0
A99: O-20951-00 | B99: cRABS Z064CR - Treaded Three Port Seat Valve VOBG320 3/4inch; Steriline; 28725; 1 Pc | C99: cRABS | D99: 1 | E99: 2 | F99: =IFERROR(__xludf.DUMMYFUNCTION("""COMPUTED_VALUE"""),0.0) -> 0 | G99: Kurang | H99: Aktif | I99: - | J99: - | K99: 0 | L99: 0 | M99: =IFERROR(__xludf.DUMMYFUNCTION("""COMPUTED_VALUE"""),"Critical Sparepart") -> Critical Sparepart | N99: 36 | O99: 0 | P99: TIDAK AKTIF | Q99: 0 | R99: 0 | S99: 0 | T99: 0 | U99: 0
A100: O-52478-00 | B100: CRABS Z064CR-Proximity Sensor | C100: cRABS | D100: 1 | E100: 2 | F100: =IFERROR(__xludf.DUMMYFUNCTION("""COMPUTED_VALUE"""),2.0) -> 2 | G100: Lebih | H100: Aktif | I100: - | J100: - | K100: 1 | L100: 2 | M100: =IFERROR(__xludf.DUMMYFUNCTION("""COMPUTED_VALUE"""),"Critical Sparepart") -> Critical Sparepart | N100: 36 | O100: 46083 | P100: AKTIF | Q100: 1 | R100: 0.27272727 | S100: 2 | T100: 0.78181818 | U100: 2
...

Sheet MPP Fast Moving Critical & Expe
A1: O-16033-00 atau O-20487-00 Glove cRABS
A2: Tahun | B2: 2026 | G2: 2027
A3: Bulan | B3: Agu | C3: Sep | D3: Okt | E3: Nov | F3: Des | G3: Jan | H3: Feb | I3: Mar | J3: Apr | K3: Mei | L3: Jun | M3: Jul | N3: Agu | O3: Sep | P3: Okt | Q3: Nov | R3: Des
A4: Stok Awal | B4: 47 | C4: =B8 -> 35 | D4: =C8 -> 30 | E4: =D8 -> 25 | F4: =E8 -> 25 | G4: =F8 -> 25 | H4: =G8 -> 20 | I4: =H8 -> 15 | J4: =I8 -> 10 | ... R4: =Q8 -> 70
A5: Pemakaian Per Bulan | B5: 12 | C5: 5 | D5: 5 | E5: 0 | F5: 0 | G5: 5 | H5: 5 | I5: 5 | J5: 5 | K5: 5 | L5: 5 | M5: 5 | N5: 5 | O5: 5 | P5: 5 | Q5: 5 | R5: 5
A6: PR | B6: 60 | C6: 0 | D6: 0 | E6: 0 | F6: 0 | G6: 0 | H6: 40 | I6: 0 | J6: 0 | K6: 0 | L6: 0 | M6: 0 | N6: 0 | O6: 0 | P6: 0 | Q6: 0 | R6: 40
A7: Kedatangan | B7: 0 | C7: 0 | D7: 0 | E7: 0 | F7: 0 | G7: 0 | H7: 0 | I7: 0 | J7: 60 | K7: 0 | L7: 0 | M7: 0 | N7: 0 | O7: 0 | P7: 40 | Q7: 0 | R7: 0
A8: Stok Akhir | B8: =B4-B5+B7 -> 35 | C8: =C4-C5+C7 -> 30 | D8: =D4-D5+D7 -> 25 | E8: =E4-E5+E7 -> 25 | F8: =F4-F5+F7 -> 25 | G8: =G4-G5+G7 -> 20 | H8: =H4-H5+H7 -> 15 | I8: =I4-I5+I7 -> 10 | ... R8: =R4-R5+R7 -> 65
A10: O-21720-00 General - Sleeves CSM 001642 M200/90 Y 550 E4 Bt5/5 Thikness 4/10; Piercan; SP010822; 1 Pc
A11: Tahun | B11: 2026 | G11: 2027
A12: Bulan | B12: Agu | C12: Sep | D12: Okt | E12: Nov | F12: Des | G12: Jan | H12: Feb | I12: Mar | J12: Apr | K12: Mei | L12: Jun | M12: Jul | N12: Agu | O12: Sep | P12: Okt | Q12: Nov | R12: Des
A13: Stok Awal | B13: 20 | C13: =B17 -> 14 | D13: =C17 -> 11 | E13: =D17 -> 8 | F13: =E17 -> 8 | G13: =F17 -> 8 | H13: =G17 -> 5 | I13: =H17 -> 2 | J13: =I17 -> -1 | ... R13: =Q17 -> 23
A14: Pemakaian Per Bulan | B14: 6 | C14: 3 | D14: 3 | E14: 0 | F14: 0 | G14: 3 | H14: 3 | I14: 3 | J14: 3 | K14: 3 | L14: 3 | M14: 3 | N14: 3 | O14: 3 | P14: 3 | Q14: 3 | R14: 3
A15: PR | B15: 48 | C15: 0 | D15: 0 | E15: 0 | F15: 0 | G15: 0 | H15: 0 | I15: 0 | J15: 0 | K15: 24 | L15: 0 | M15: 0 | N15: 0 | O15: 0 | P15: 0 | Q15: 0 | R15: 0
A16: Kedatangan | B16: 0 | C16: 0 | D16: 0 | E16: 0 | F16: 0 | G16: 0 | H16: 0 | I16: 0 | J16: 48 | K16: 0 | L16: 0 | M16: 0 | N16: 0 | O16: 0 | P16: 0 | Q16: 0 | R16: 0
A17: Stok Akhir | B17: =B13-B14+B16 -> 14 | C17: =C13-C14+C16 -> 11 | D17: =D13-D14+D16 -> 8 | E17: =E13-E14+E16 -> 8 | F17: =F13-F14+F16 -> 8 | G17: =G13-G14+G16 -> 5 | H17: =H13-H14+H16 -> 2 | I17: =I13-I14+I16 -> -1 | ... R17: =R13-R14+R16 -> 20
A19: O-16030-00 General - Dry box glove, 4/10 mm, CSM, 97800 Y 8.5 E4 5; Piercan; 1292; 10 pcs per pack
A20: Tahun | B20: 2026 | G20: 2027
A21: Bulan | B21: Agu | C21: Sep | D21: Okt | E21: Nov | F21: Des | G21: Jan | H21: Feb | I21: Mar | J21: Apr | K21: Mei | L21: Jun | M21: Jul | N21: Agu | O21: Sep | P21: Okt | Q21: Nov | R21: Des
A22: Stok Awal | B22: 29 | C22: =B26 -> 29 | D22: =C26 -> 28 | E22: =D26 -> 47 | F22: =E26 -> 47 | G22: =F26 -> 47 | H22: =G26 -> 46 | I22: =H26 -> 45 | J22: =I26 -> 44 | ... R22: =Q26 -> 36
A23: Pemakaian Per Bulan | B23: 0 | C23: 1 | D23: 1 | E23: 0 | F23: 0 | G23: 1 | H23: 1 | I23: 1 | J23: 1 | K23: 1 | L23: 1 | M23: 1 | N23: 1 | O23: 1 | P23: 1 | Q23: 1 | R23: 1
A24: PR | B24: 0 | C24: 0 | D24: 0 | E24: 0 | F24: 0 | G24: 0 | H24: 0 | I24: 0 | J24: 0 | K24: 0 | L24: 0 | M24: 0 | N24: 0 | O24: 0 | P24: 0 | Q24: 0 | R24: 10
A25: Kedatangan | B25: 0 | C25: 0 | D25: 20 | E25: 0 | F25: 0 | G25: 0 | H25: 0 | I25: 0 | J25: 0 | K25: 0 | L25: 0 | M25: 0 | N25: 0 | O25: 0 | P25: 0 | Q25: 0 | R25: 0
A26: Stok Akhir | B26: =B22-B23+B25 -> 29 | C26: =C22-C23+C25 -> 28 | D26: =D22-D23+D25 -> 47 | E26: =E22-E23+E25 -> 47 | F26: =F22-F23+F25 -> 47 | G26: =G22-G23+G25 -> 46 | H26: =H22-H23+H25 -> 45 | I26: =I22-I23+I25 -> 44 | ... R26: =R22-R23+R25 -> 35
A28: O-21284-00 General - Isolator Gloves 000080 E10330 CNS 7 E3 5 Neoprene No Staining; Piercan; SG010138; 1 Pc
A29: Tahun | B29: 2026 | G29: 2027
A30: Bulan | B30: Agu | C30: Sep | D30: Okt | E30: Nov | F30: Des | G30: Jan | H30: Feb | I30: Mar | J30: Apr | K30: Mei | L30: Jun | M30: Jul | N30: Agu | O30: Sep | P30: Okt | Q30: Nov | R30: Des
A31: Stok Awal | B31: 30 | C31: =B35 -> 23 | D31: =C35 -> 21 | E31: =D35 -> 19 | F31: =E35 -> 17 | G31: =F35 -> 15 | H31: =G35 -> 13 | I31: =H35 -> 11 | J31: =I35 -> 19 | ... R31: =Q35 -> 13
A32: Pemakaian Per Bulan | B32: 7 | C32: 2 | D32: 2 | E32: 2 | F32: 2 | G32: 2 | H32: 2 | I32: 2 | J32: 2 | K32: 2 | L32: 2 | M32: 2 | N32: 2 | O32: 2 | P32: 2 | Q32: 2 | R32: 2
A33: PR | B33: 0 | C33: 0 | D33: 10 | E33: 0 | F33: 0 | G33: 0 | H33: 0 | I33: 0 | J33: 10 | K33: 0 | L33: 0 | M33: 0 | N33: 0 | O33: 0 | P33: 10 | Q33: 0 | R33: 0
A34: Kedatangan | B34: 0 | C34: 0 | D34: 0 | E34: 0 | F34: 0 | G34: 0 | H34: 0 | I34: 10 | J34: 0 | K34: 0 | L34: 0 | M34: 0 | N34: 0 | O34: 10 | P34: 0 | Q34: 0 | R34: 0
A35: Stok Akhir | B35: =B31-B32+B34 -> 23 | C35: =C31-C32+C34 -> 21 | D35: =D31-D32+D34 -> 19 | E35: =E31-E32+E34 -> 17 | F35: =F31-F32+F34 -> 15 | G35: =G31-G32+G34 -> 13 | H35: =H31-H32+H34 -> 11 | I35: =I31-I32+I34 -> 19 | ... R35: =R31-R32+R34 -> 11
A37: O-21485-00 General - Isolator Glove CSM Port size 8 Inch Length : 800 mm, Thick : 15mil/0.4mm; TRON; 8Y1532A0975; 1 Pc
A38: Tahun | B38: 2026 | G38: 2027
A39: Bulan | B39: Agu | C39: Sep | D39: Okt | E39: Nov | F39: Des | G39: Jan | H39: Feb | I39: Mar | J39: Apr | K39: Mei | L39: Jun | M39: Jul | N39: Agu | O39: Sep | P39: Okt | Q39: Nov | R39: Des
A40: Stok Awal | B40: 15 | C40: =B44 -> 15 | D40: =C44 -> 13 | E40: =D44 -> 11 | F40: =E44 -> 9 | G40: =F44 -> 27 | H40: =G44 -> 25 | I40: =H44 -> 23 | J40: =I44 -> 21 | ... R40: =Q44 -> 15
A41: Pemakaian Per Bulan | B41: 0 | C41: 2 | D41: 2 | E41: 2 | F41: 2 | G41: 2 | H41: 2 | I41: 2 | J41: 2 | K41: 2 | L41: 2 | M41: 2 | N41: 2 | O41: 2 | P41: 2 | Q41: 2 | R41: 2
A42: PR | B42: 20 | C42: 0 | D42: 0 | E42: 0 | F42: 0 | G42: 0 | H42: 0 | I42: 0 | J42: 10 | K42: 0 | L42: 0 | M42: 0 | N42: 10 | O42: 0 | P42: 0 | Q42: 0 | R42: 10
A43: Kedatangan | B43: 0 | C43: 0 | D43: 0 | E43: 0 | F43: 20 | G43: 0 | H43: 0 | I43: 0 | J43: 0 | K43: 0 | L43: 0 | M43: 0 | N43: 10 | O43: 0 | P43: 0 | Q43: 0 | R43: 10
A44: Total | B44: =B40-B41+B43 -> 15 | C44: =C40-C41+C43 -> 13 | D44: =D40-D41+D43 -> 11 | E44: =E40-E41+E43 -> 9 | F44: =F40-F41+F43 -> 27 | G44: =G40-G41+G43 -> 25 | H44: =H40-H41+H43 -> 23 | I44: =I40-I41+I43 -> 21 | ... R44: =R40-R41+R43 -> 23
A46: O-16980-00 General - Diaphragm 40 mm ER Grade EPDM; Saunders; DA040ER M4; 1 Pc
A47: Tahun | B47: 2026 | G47: 2027
A48: Bulan | B48: Agu | C48: Sep | D48: Okt | E48: Nov | F48: Des | G48: Jan | H48: Feb | I48: Mar | J48: Apr | K48: Mei | L48: Jun | M48: Jul | N48: Agu | O48: Sep | P48: Okt | Q48: Nov | R48: Des
A49: Stok Awal | B49: 18 | C49: =B53 -> 14 | D49: =C53 -> 14 | E49: =D53 -> 14 | F49: =E53 -> 14 | G49: =F53 -> 32 | H49: =G53 -> 32 | I49: =H53 -> 26 | J49: =I53 -> 26 | ... R49: =Q53 -> 26
A50: Pemakaian Per Bulan | B50: 4 | C50: 0 | D50: 0 | E50: 0 | F50: 0 | G50: 0 | H50: 6 | I50: 0 | J50: 0 | K50: 6 | L50: 0 | M50: 0 | N50: 6 | O50: 0 | P50: 0 | Q50: 6 | R50: 0
A51: PR | B51: 0 | C51: 18 | D51: 0 | E51: 0 | F51: 0 | G51: 0 | H51: 0 | I51: 0 | J51: 0 | K51: 0 | L51: 0 | M51: 0 | N51: 18 | O51: 0 | P51: 0 | Q51: 0 | R51: 0
A52: Kedatangan | B52: 0 | C52: 0 | D52: 0 | E52: 0 | F52: 18 | G52: 0 | H52: 0 | I52: 0 | J52: 0 | K52: 0 | L52: 0 | M52: 0 | N52: 0 | O52: 0 | P52: 0 | Q52: 18 | R52: 0
A53: Total | B53: =B49-B50+B52 -> 14 | C53: =C49-C50+C52 -> 14 | D53: =D49-D50+D52 -> 14 | E53: =E49-E50+E52 -> 14 | F53: =F49-F50+F52 -> 32 | G53: =G49-G50+G52 -> 32 | H53: =H49-H50+H52 -> 26 | I53: =I49-I50+I52 -> 26 | ... R53: =R49-R50+R52 -> 26
A55: O-16981-00 Freeze Dryer MBE1207 - Diaphrapm DA025E2 M4 Saunders CIPTA SOLUSI ANDALAN, PT P/N : - pc
A56: Tahun | B56: 2026 | G56: 2027
A57: Bulan | B57: Agu | C57: Sep | D57: Okt | E57: Nov | F57: Des | G57: Jan | H57: Feb | I57: Mar | J57: Apr | K57: Mei | L57: Jun | M57: Jul | N57: Agu | O57: Sep | P57: Okt | Q57: Nov | R57: Des
A58: Stok Awal | B58: 30 | C58: =B62 -> 23 | D58: =C62 -> 23 | E58: =D62 -> 23 | F58: =E62 -> 23 | G58: =F62 -> 63 | H58: =G62 -> 63 | I58: =H62 -> 53 | J58: =I62 -> 53 | ... R58: =Q62 -> 63
A59: Pemakaian Per Bulan | B59: 7 | C59: 0 | D59: 0 | E59: 0 | F59: 0 | G59: 0 | H59: 10 | I59: 0 | J59: 0 | K59: 10 | L59: 0 | M59: 0 | N59: 10 | O59: 0 | P59: 0 | Q59: 10 | R59: 0
A60: PR | B60: 0 | C60: 40 | D60: 0 | E60: 0 | F60: 0 | G60: 0 | H60: 0 | I60: 0 | J60: 0 | K60: 0 | L60: 0 | M60: 0 | N60: 40 | O60: 0 | P60: 0 | Q60: 0 | R60: 0
A61: Kedatangan | B61: 0 | C61: 0 | D61: 0 | E61: 0 | F61: 40 | G61: 0 | H61: 0 | I61: 0 | J61: 0 | K61: 0 | L61: 0 | M61: 0 | N61: 0 | O61: 0 | P61: 0 | Q61: 40 | R61: 0
A62: Total | B62: =B58-B59+B61 -> 23 | C62: =C58-C59+C61 -> 23 | D62: =D58-D59+D61 -> 23 | E62: =E58-E59+E61 -> 23 | F62: =F58-F59+F61 -> 63 | G62: =G58-G59+G61 -> 63 | H62: =H58-H59+H61 -> 53 | I62: =I58-I59+I61 -> 53 | ... R62: =R58-R59+R61 -> 63
A64: O-20496-00 General - Diaphragm Grade ER SQUARE Type A EPDM Diaphragm Screw; Saunders; DP008ER; 1 Pc
A65: Tahun | B65: 2026 | G65: 2027
A66: Bulan | B66: Agu | C66: Sep | D66: Okt | E66: Nov | F66: Des | G66: Jan | H66: Feb | I66: Mar | J66: Apr | K66: Mei | L66: Jun | M66: Jul | N66: Agu | O66: Sep | P66: Okt | Q66: Nov | R66: Des
A67: Stok Awal | B67: 6 | C67: =B71 -> 6 | D67: =C71 -> 5 | E67: =D71 -> 5 | F67: =E71 -> 5 | G67: =F71 -> 5 | H67: =G71 -> 8 | I67: =H71 -> 7 | J67: =I71 -> 7 | ... R67: =Q71 -> 4
A68: Pemakaian Per Bulan | B68: 0 | C68: 1 | D68: 0 | E68: 0 | F68: 0 | G68: 0 | H68: 1 | I68: 0 | J68: 0 | K68: 1 | L68: 0 | M68: 0 | N68: 1 | O68: 0 | P68: 0 | Q68: 1 | R68: 0
A69: PR | B69: 0 | C69: 0 | D69: 3 | E69: 0 | F69: 0 | G69: 0 | H69: 0 | I69: 0 | J69: 0 | K69: 0 | L69: 0 | M69: 0 | N69: 0 | O69: 3 | P69: 0 | Q69: 0 | R69: 0
A70: Kedatangan | B70: 0 | C70: 0 | D70: 0 | E70: 0 | F70: 0 | G70: 3 | H70: 0 | I70: 0 | J70: 0 | K70: 0 | L70: 0 | M70: 0 | N70: 0 | O70: 0 | P70: 0 | Q70: 0 | R70: 3
A71: Total | B71: =B67-B68+B70 -> 6 | C71: =C67-C68+C70 -> 5 | D71: =D67-D68+D70 -> 5 | E71: =E67-E68+E70 -> 5 | F71: =F67-F68+F70 -> 5 | G71: =G67-G68+G70 -> 8 | H71: =H67-H68+H70 -> 7 | I71: =I67-I68+I70 -> 7 | ... R71: =R67-R68+R70 -> 7
A73: Q-60025-00 Kuas Eterna 1
A74: Tahun | B74: 2026 | G74: 2027
A75: Bulan | B75: Agu | C75: Sep | D75: Okt | E75: Nov | F75: Des | G75: Jan | H75: Feb | I75: Mar | J75: Apr | K75: Mei | L75: Jun | M75: Jul | N75: Agu | O75: Sep | P75: Okt | Q75: Nov | R75: Des
A76: Stok Awal | B76: 0 | C76: =B80 -> 3 | D76: =C80 -> 1 | E76: =D80 -> 34 | F76: =E80 -> 32 | G76: =F80 -> 30 | H76: =G80 -> 28 | I76: =H80 -> 26 | J76: =I80 -> 24 | ... R76: =Q80 -> 43
A77: Pemakaian Per Bulan | B77: 0 | C77: 2 | D77: 2 | E77: 2 | F77: 2 | G77: 2 | H77: 2 | I77: 2 | J77: 2 | K77: 2 | L77: 2 | M77: 2 | N77: 2 | O77: 2 | P77: 2 | Q77: 2 | R77: 2
A78: PR | B78: 35 | C78: 0 | D78: 0 | E78: 0 | F78: 0 | G78: 0 | H78: 0 | I78: 0 | J78: 0 | K78: 0 | L78: 0 | M78: 0 | N78: 35 | O78: 0 | P78: 0 | Q78: 0 | R78: 0
A79: Kedatangan | B79: 3 | C79: 0 | D79: 35 | E79: 0 | F79: 0 | G79: 0 | H79: 0 | I79: 0 | J79: 0 | K79: 0 | L79: 0 | M79: 0 | N79: 0 | O79: 0 | P79: 35 | Q79: 0 | R79: 0
A80: Total | B80: =B76-B77+B79 -> 3 | C80: =C76-C77+C79 -> 1 | D80: =D76-D77+D79 -> 34 | E80: =E76-E77+E79 -> 32 | F80: =F76-F77+F79 -> 30 | G80: =G76-G77+G79 -> 28 | H80: =H76-H77+H79 -> 26 | I80: =I76-I77+I79 -> 24 | ... R80: =R76-R77+R79 -> 41
A82: T-20123-00 Acquity PDA/TUV 2489/2998 Perf Main Kit (lampu HPLC); Waters; P/N 201000281; 1 pc
A83: Tahun | B83: 2026 | G83: 2027
A84: Bulan | B84: Agu | C84: Sep | D84: Okt | E84: Nov | F84: Des | G84: Jan | H84: Feb | I84: Mar | J84: Apr | K84: Mei | L84: Jun | M84: Jul | N84: Agu | O84: Sep | P84: Okt | Q84: Nov | R84: Des
A85: Stok Awal | B85: 4 | C85: =B89 -> 4 | D85: =C89 -> 3 | E85: =D89 -> 2 | F85: =E89 -> 13 | G85: =F89 -> 12 | H85: =G89 -> 11 | I85: =H89 -> 10 | J85: =I89 -> 9 | ... R85: =Q89 -> 1
A86: Pemakaian Per Bulan | B86: 0 | C86: 1 | D86: 1 | E86: 1 | F86: 1 | G86: 1 | H86: 1 | I86: 1 | J86: 1 | K86: 1 | L86: 1 | M86: 1 | N86: 1 | O86: 1 | P86: 1 | Q86: 1 | R86: 1
A87: PR | B87: 0 | C87: 12 | D87: 0 | E87: 0 | F87: 0 | G87: 0 | H87: 0 | I87: 0 | J87: 0 | K87: 0 | L87: 0 | M87: 0 | N87: 0 | O87: 0 | P87: 0 | Q87: 0 | R87: 0
A88: Kedatangan | B88: 0 | C88: 0 | D88: 0 | E88: 12 | F88: 0 | G88: 0 | H88: 0 | I88: 0 | J88: 0 | K88: 0 | L88: 0 | M88: 0 | N88: 0 | O88: 0 | P88: 0 | Q88: 0 | R88: 0
A89: Total | B89: =B85-B86+B88 -> 4 | C89: =C85-C86+C88 -> 3 | D89: =D85-D86+D88 -> 2 | E89: =E85-E86+E88 -> 13 | F89: =F85-F86+F88 -> 12 | G89: =G85-G86+G88 -> 11 | H89: =H85-H86+H88 -> 10 | I89: =I85-I86+I88 -> 9 | ... R89: =R85-R86+R88 -> 0
A91: Q-60026-00 Kuas Cat Uk. 2 inch;Eterna;Tipe 611;pack size per pcs
A92: Tahun | B92: 2026 | G92: 2027
A93: Bulan | B93: Agu | C93: Sep | D93: Okt | E93: Nov | F93: Des | G93: Jan | H93: Feb | I93: Mar | J93: Apr | K93: Mei | L93: Jun | M93: Jul | N93: Agu | O93: Sep | P93: Okt | Q93: Nov | R93: Des
A94: Stok Awal | B94: 0 | C94: =B98 -> 0 | D94: =C98 -> -1 | E94: =D98 -> 8 | F94: =E98 -> 7 | G94: =F98 -> 6 | H94: =G98 -> 5 | I94: =H98 -> 4 | J94: =I98 -> 3 | ... R94: =Q98 -> 5
A95: Pemakaian Per Bulan | B95: 0 | C95: 1 | D95: 1 | E95: 1 | F95: 1 | G95: 1 | H95: 1 | I95: 1 | J95: 1 | K95: 1 | L95: 1 | M95: 1 | N95: 1 | O95: 1 | P95: 1 | Q95: 1 | R95: 1
A96: PR | B96: 10 | C96: 0 | D96: 0 | E96: 0 | F96: 0 | G96: 0 | H96: 0 | I96: 10 | J96: 0 | K96: 0 | L96: 0 | M96: 0 | N96: 0 | O96: 0 | P96: 0 | Q96: 0 | R96: 0
A97: Kedatangan | B97: 0 | C97: 0 | D97: 10 | E97: 0 | F97: 0 | G97: 0 | H97: 0 | I97: 0 | J97: 0 | K97: 10 | L97: 0 | M97: 0 | N97: 0 | O97: 0 | P97: 0 | Q97: 0 | R97: 0
A98: Total | B98: =B94-B95+B97 -> 0 | C98: =C94-C95+C97 -> -1 | D98: =D94-D95+D97 -> 8 | E98: =E94-E95+E97 -> 7 | F98: =F94-F95+F97 -> 6 | G98: =G94-G95+G97 -> 5 | H98: =H94-H95+H97 -> 4 | I98: =I94-I95+I97 -> 3 | ... R98: =R94-R95+R97 -> 4
A100: T-20055-00 PerformancePlus Check Valve Cartridge; Waters; p/n 700002399;
A101: Tahun | B101: 2026 | G101: 2027
A102: Bulan | B102: Agu | C102: Sep | D102: Okt | E102: Nov | F102: Des | G102: Jan | H102: Feb | I102: Mar | J102: Apr | K102: Mei | L102: Jun | M102: Jul | N102: Agu | O102: Sep | P102: Okt | Q102: Nov | R102: Des
A103: Stok Awal | B103: 3 | C103: =B107 -> 2 | D103: =C107 -> 2 | E103: =D107 -> 2 | F103: =E107 -> 1 | G103: =F107 -> 8 | H103: =G107 -> 8 | I103: =H107 -> 7 | J103: =I107 -> 7 | ... R103: =Q107 -> 4
A104: Pemakaian Per Bulan | B104: 1 | C104: 0 | D104: 0 | E104: 1 | F104: 0 | G104: 0 | H104: 1 | I104: 0 | J104: 0 | K104: 1 | L104: 0 | M104: 0 | N104: 1 | O104: 0 | P104: 0 | Q104: 1 | R104: 0
A105: PR | B105: 0 | C105: 0 | D105: 7 | E105: 0 | F105: 0 | G105: 0 | H105: 0 | I105: 0 | J105: 0 | K105: 0 | L105: 0 | M105: 0 | N105: 0 | O105: 0 | P105: 0 | Q105: 0 | R105: 0
A106: Kedatangan | B106: 0 | C106: 0 | D106: 0 | E106: 0 | F106: 7 | G106: 0 | H106: 0 | I106: 0 | J106: 0 | K106: 0 | L106: 0 | M106: 0 | N106: 0 | O106: 0 | P106: 0 | Q106: 0 | R106: 0
A107: Total | B107: =B103-B104+B106 -> 2 | C107: =C103-C104+C106 -> 2 | D107: =D103-D104+D106 -> 2 | E107: =E103-E104+E106 -> 1 | F107: =F103-F104+F106 -> 8 | G107: =G103-G104+G106 -> 8 | H107: =H103-H104+H106 -> 7 | I107: =I103-I104+I106 -> 7 | ... R107: =R103-R104+R106 -> 4
A109: Q-10715-00 Lem PVC Isarplas Kuas @400gr; ; ;
A110: Tahun | B110: 2026 | G110: 2027
A111: Bulan | B111: Agu | C111: Sep | D111: Okt | E111: Nov | F111: Des | G111: Jan | H111: Feb | I111: Mar | J111: Apr | K111: Mei | L111: Jun | M111: Jul | N111: Agu | O111: Sep | P111: Okt | Q111: Nov | R111: Des
A112: Stok Awal | B112: 2 | C112: =B116 -> 2 | D112: =C116 -> 2 | E112: =D116 -> 2 | F112: =E116 -> 1 | G112: =F116 -> 4 | H112: =G116 -> 4 | I112: =H116 -> 3 | J112: =I116 -> 3 | ... R112: =Q116 -> 3
...

Sheet Sheet2
A1: No | B1: Mesin | C1: Total Critical Part | D1: Tidak Perlu di Stok (Part setara dengan yang lain, Jarang rusak, serta mahal) | E1: Perlu Di Stok | J1: Persentase Sudah Ada | K1: Sudah Terproses | L1: Penawaran Sudah Diterima | M1: FU By Fadhil | O1: P2 | P1: P3 | Q1: Target Terproses 100% | R1: Target Stok 100%
E2: Ada Stok | F2: Tidak Ada Stok
F3: Menunggu Barang Datang | G3: Sudah Ada Item Code | H3: Belum Ada Item Code
H4: Ready Minta Penawaran | I4: Butuh Konfirmasi
A5: 1 | B5: Autoclave | C5: =countif('All Critical Part'!C:C,B5) -> 47 | D5: 11 | E5: 24 | F5: 4 | G5: 6 | H5: 1 | I5: 0 | J5: =E5/(C5-D5) -> 0.66666667 | K5: =(E5+F5)/(C5-D5) -> 0.77777778 | L5: 0 | M5: =sum(G5:I5) -> 7 | N5: =M5/(C5-D5) -> 0.19444444 | O5: 1 | P5: 0 | Q5: 46016 | R5: 45714 | S5: Persentase yang sudah terproses dari 9 mesin | T5: =sum(C5:C55) -> 690
A6: 2 | B6: Capping | C6: =countif('All Critical Part'!C:C,B6) -> 49 | D6: 20 | E6: 22 | F6: 4 | G6: 2 | H6: 1 | I6: 0 | J6: =E6/(C6-D6) -> 0.75862069 | K6: =(E6+F6)/(C6-D6) -> 0.89655172 | L6: 0 | M6: =sum(G6:I6) -> 3 | N6: =M6/(C6-D6) -> 0.10344828 | O6: 1 | P6: 0 | Q6: 45986 | R6: 45714
A7: 3 | B7: cRABS | C7: =countif('All Critical Part'!C:C,B7) -> 65 | D7: 26 | E7: 28 | F7: 11 | G7: 5 | H7: 1 | I7: 0 | J7: =E7/(C7-D7) -> 0.71794872 | K7: =(E7+F7)/(C7-D7) -> 1 | L7: 1 | M7: =sum(G7:I7) -> 6 | N7: =M7/(C7-D7) -> 0.15384615 | O7: 3 | P7: 0 | Q7: 46016 | R7: 45742 | S7: =AVERAGE((K5:K13)) -> 0.93722446
A8: 4 | B8: EDM | C8: =countif('All Critical Part'!C:C,B8) -> 18 | D8: 10 | E8: 4 | F8: 7 | G8: 2 | H8: 2 | I8: 0 | J8: =E8/(C8-D8) -> 0.5 | K8: =(E8+F8)/(C8-D8) -> 1.375 | L8: 0 | M8: =sum(G8:I8) -> 4 | N8: =M8/(C8-D8) -> 0.5 | O8: 0 | P8: 0 | Q8: 46016 | R8: 45742
A9: 5 | B9: FD IMA | C9: =countif('All Critical Part'!C:C,B9) -> 76 | D9: 14 | E9: 55 | F9: 5 | G9: 4 | H9: 4 | I9: 0 | J9: =E9/(C9-D9) -> 0.88709677 | K9: =(E9+F9)/(C9-D9) -> 0.96774194 | L9: 0 | M9: =sum(G9:I9) -> 8 | N9: =M9/(C9-D9) -> 0.12903226 | O9: 0 | P9: 0 | Q9: 45986 | R9: 45683 | S9: Persentase stok yang sudah ada dari 9 mesin
A10: 6 | B10: Filling | C10: =countif('All Critical Part'!C:C,B10) -> 43 | D10: 23 | E10: 13 | F10: 6 | G10: 5 | H10: 3 | I10: 0 | J10: =E10/(C10-D10) -> 0.65 | K10: =(E10+F10)/(C10-D10) -> 0.95 | L10: 1 | M10: =sum(G10:I10) -> 8 | N10: =M10/(C10-D10) -> 0.4 | O10: 1 | P10: 3 | Q10: 46016 | R10: 45742
A11: 7 | B11: Mixing | C11: =countif('All Critical Part'!C:C,B11) -> 13 | D11: 5 | E11: 4 | F11: 1 | G11: 1 | H11: 10 | I11: 3 | J11: =E11/(C11-D11) -> 0.5 | K11: =(E11+F11)/(C11-D11) -> 0.625 | L11: 5 | M11: =sum(G11:I11) -> 14 | N11: =M11/(C11-D11) -> 1.75 | O11: 10 | P11: 1 | Q11: 45683 | R11: 45773 | S11: =AVERAGE(J5:J13) -> 0.68136177
A12: 8 | B12: Tunnel | C12: =countif('All Critical Part'!C:C,B12) -> 45 | D12: 21 | E12: 21 | F12: 2 | G12: 6 | H12: 0 | I12: 2 | J12: =E12/(C12-D12) -> 0.875 | K12: =(E12+F12)/(C12-D12) -> 0.95833333 | L12: 0 | M12: =sum(G12:I12) -> 8 | N12: =M12/(C12-D12) -> 0.33333333 | O12: 1 | P12: 0 | Q12: 46016 | R12: 45742
A13: 9 | B13: Washing | C13: =countif('All Critical Part'!C:C,B13) -> 38 | D13: 12 | E13: 15 | F13: 8 | G13: 2 | H13: 1 | I13: 1 | J13: =E13/(C13-D13) -> 0.57692308 | K13: =(E13+F13)/(C13-D13) -> 0.88461538 | L13: 0 | M13: =sum(G13:I13) -> 4 | N13: =M13/(C13-D13) -> 0.15384615 | O13: 1 | P13: 0 | Q13: 45986 | R13: 45714
A14: 10 | B14: General - Chemical | C14: =countif('All Critical Part'!C:C,B14) -> 18 | D14: 0 | E14: 9 | F14: 0 | G14: 5 | H14: 3 | I14: 0 | J14: =E14/(C14-D14) -> 0.5 | K14: =(E14+F14)/(C14-D14) -> 0.5 | L14: 0 | M14: =sum(G14:I14) -> 8 | N14: =M14/(C14-D14) -> 0.44444444 | O14: 0 | P14: 0 | Q14: 46016 | R14: 45683
A15: 11 | B15: General - Pneumatic | C15: =countif('All Critical Part'!C:C,B15) -> 49 | D15: 0 | E15: 22 | F15: 1 | G15: 22 | H15: 3 | I15: 0 | J15: =E15/(C15-D15) -> 0.44897959 | K15: =(E15+F15)/(C15-D15) -> 0.46938776 | L15: 0 | M15: =sum(G15:I15) -> 25 | N15: =M15/(C15-D15) -> 0.51020408 | O15: 0 | P15: 0 | Q15: 46016 | R15: 45683
A16: 12 | B16: General - Electrical | C16: =countif('All Critical Part'!C:C,B16) -> 73 | D16: 0 | E16: 35 | F16: 0 | G16: 30 | H16: 2 | I16: 0 | J16: =E16/(C16-D16) -> 0.47945205 | K16: =(E16+F16)/(C16-D16) -> 0.47945205 | L16: 0 | M16: =sum(G16:I16) -> 32 | N16: =M16/(C16-D16) -> 0.43835616 | O16: 0 | P16: 0 | Q16: 46016 | R16: 45683
A17: 13 | B17: General - Isolasi | C17: =countif('All Critical Part'!C:C,B17) -> 16 | D17: 0 | E17: 8 | F17: 0 | G17: 3 | H17: 0 | I17: 0 | J17: =E17/(C17-D17) -> 0.5 | K17: =(E17+F17)/(C17-D17) -> 0.5 | L17: 0 | M17: =sum(G17:I17) -> 3 | N17: =M17/(C17-D17) -> 0.1875 | O17: 0 | P17: 0 | Q17: 45986 | R17: 46016
A18: 14 | B18: General - Workshop | C18: =countif('All Critical Part'!C:C,B18) -> 23 | D18: 0 | E18: 5 | F18: 0 | G18: 17 | H18: 0 | I18: 0 | J18: =E18/(C18-D18) -> 0.2173913 | K18: =(E18+F18)/(C18-D18) -> 0.2173913 | L18: 0 | M18: =sum(G18:I18) -> 17 | N18: =M18/(C18-D18) -> 0.73913043 | O18: 0 | P18: 0 | Q18: 45986 | R18: 46016
A19: 15 | B19: General - Baut | C19: =countif('All Critical Part'!C:C,B19) -> 11 | D19: 0 | E19: 1 | F19: 0 | G19: 10 | H19: 0 | I19: 0 | J19: =E19/(C19-D19) -> 0.090909091 | K19: =(E19+F19)/(C19-D19) -> 0.090909091 | L19: 0 | M19: =sum(G19:I19) -> 10 | N19: =M19/(C19-D19) -> 0.90909091 | O19: 0 | P19: 0 | Q19: 45986 | R19: 46016
A20: 16 | B20: General - Plumbing | C20: =countif('All Critical Part'!C:C,B20) -> 80 | D20: 0 | E20: 41 | F20: 0 | G20: 34 | H20: 4 | I20: 0 | J20: =E20/(C20-D20) -> 0.5125 | K20: =(E20+F20)/(C20-D20) -> 0.5125 | L20: 0 | M20: =sum(G20:I20) -> 38 | N20: =M20/(C20-D20) -> 0.475 | O20: 0 | P20: 0 | Q20: 46016 | R20: 45683
A21: 17 | B21: CLU | U21: TRUE
A22: 18 | B22: Cartoning | T22: Sudah punya list | U22: TRUE
A23: 19 | B23: Labelling | T23: Sudah punya list | U23: TRUE
A24: 20 | B24: Isolator SKAN | U24: TRUE
A25: 21 | B25: HPLC | T25: Sudah punya list | U25: TRUE
A26: 22 | B26: Building | T26: Sudah punya list | U26: TRUE
A27: 23 | B27: AHU | C27: =countif('All Critical Part'!C:C,B27) -> 26 | T27: Sudah punya list | U27: TRUE
A28: 24 | B28: PWG & SKID | T28: Sudah punya list | U28: TRUE
A29: 25 | B29: WFIG WFI SKID | T29: Sudah punya list | U29: TRUE
A30: 26 | B30: PSG | T30: Sudah punya list | U30: TRUE
A31: 28 | B31: Isolator Klenzaid | U31: FALSE
A32: 29 | B32: MS30 | T32: Sudah punya list | U32: TRUE
B49: Forklift | C49: =countif('All Critical Part'!C:C,B49) -> 0
B50: GMP Washer | C50: =countif('All Critical Part'!C:C,B50) -> 0
B51: Isolator | C51: =countif('All Critical Part'!C:C,B51) -> 0
B52: N2 Gen | C52: =countif('All Critical Part'!C:C,B52) -> 0
B53: Piping | C53: =countif('All Critical Part'!C:C,B53) -> 0
B54: PWG
B55: WFI Gen
B56: WI Incubator
B57: WIHC
B58: Workshop
B59: WWTP

Sheet Data PR
A1: Uniq Code | B1: PR Number | C1: Line Number | D1: Item Number | E1: Description | F1: Qty | G1: UoM | H1: Curr | I1: Unit Price | J1: Amount | K1: Need By Date | L1: Ship To | M1: User | N1: User Location | O1: CoA | P1: Line Status | Q1: Order Number | R1: Creation Date | S1: Approval Date | T1: Deadline
A2: =IFERROR(__xludf.DUMMYFUNCTION("FILTER( IMPORTRANGE(""1-dQuO-dirpd7144O3pZq8VkGXSA12p4ZTEYRJJJN7zc"", ""Sheet1!B:U""), (IMPORTRANGE(""1-dQuO-dirpd7144O3pZq8VkGXSA12p4ZTEYRJJJN7zc"", ""Sheet1!Q:Q"") = ""PR Open"") + (IMPORTRANGE(""1-dQuO-dirpd7144O3pZq8VkGXSA12p4ZTEYRJJJN7zc"", ""S"&"heet1!Q:Q"") = ""PO Open"") + (IMPORTRANGE(""1-dQuO-dirpd7144O3pZq8VkGXSA12p4ZTEYRJJJN7zc"", ""Sheet1!Q:Q"") = ""PO Closed"") )"),"181750042-1") -> 181750042-1 | B2: =IFERROR(__xludf.DUMMYFUNCTION("""COMPUTED_VALUE"""),"181750042 - Approved") -> 181750042 - Approved | C2: =IFERROR(__xludf.DUMMYFUNCTION("""COMPUTED_VALUE"""),1.0) -> 1 | D2: =IFERROR(__xludf.DUMMYFUNCTION("""COMPUTED_VALUE"""),"P-15905-00") -> P-15905-00 | E2: =IFERROR(__xludf.DUMMYFUNCTION("""COMPUTED_VALUE"""),"Filter Catridge; Type: TefTEC Series; P/N : TefTEC 0.2 - 10 P7S; Lenght : 10 Inch; O-Ring : 226 Fin; ; ;") -> Filter Catridge; Type: TefTEC Series; P/N : TefTEC 0.2 - 10 P7S; Lenght : 10 Inch; O-Ring : 226 Fin; ; ; | F2: =IFERROR(__xludf.DUMMYFUNCTION("""COMPUTED_VALUE"""),1.0) -> 1 | G2: =IFERROR(__xludf.DUMMYFUNCTION("""COMPUTED_VALUE"""),"Unit") -> Unit | H2: =IFERROR(__xludf.DUMMYFUNCTION("""COMPUTED_VALUE"""),"IDR") -> IDR | I2: =IFERROR(__xludf.DUMMYFUNCTION("""COMPUTED_VALUE"""),3575000.0) -> 3575000 | J2: =IFERROR(__xludf.DUMMYFUNCTION("""COMPUTED_VALUE"""),3575000.0) -> 3575000 | K2: =IFERROR(__xludf.DUMMYFUNCTION("""COMPUTED_VALUE"""),43189.0) -> 43189 | L2: =IFERROR(__xludf.DUMMYFUNCTION("""COMPUTED_VALUE"""),"FIP Engineering") -> FIP Engineering | M2: =IFERROR(__xludf.DUMMYFUNCTION("""COMPUTED_VALUE"""),"Joko Nugroho") -> Joko Nugroho | N2: =IFERROR(__xludf.DUMMYFUNCTION("""COMPUTED_VALUE"""),"FIP Engineering") -> FIP Engineering | O2: =IFERROR(__xludf.DUMMYFUNCTION("""COMPUTED_VALUE"""),"FIP-DOM-000-11304-OS00001-INA-000000") -> FIP-DOM-000-11304-OS00001-INA-000000 | P2: =IFERROR(__xludf.DUMMYFUNCTION("""COMPUTED_VALUE"""),"PO Closed") -> PO Closed | Q2: =IFERROR(__xludf.DUMMYFUNCTION("""COMPUTED_VALUE"""),"GL1802051") -> GL1802051 | R2: =IFERROR(__xludf.DUMMYFUNCTION("""COMPUTED_VALUE"""),43136.0) -> 43136 | S2: =IFERROR(__xludf.DUMMYFUNCTION("""COMPUTED_VALUE"""),"-") -> - | T2: =IFERROR(__xludf.DUMMYFUNCTION("""COMPUTED_VALUE"""),43160.0) -> 43160
A3: =IFERROR(__xludf.DUMMYFUNCTION("""COMPUTED_VALUE"""),"181750042-2") -> 181750042-2 | B3: =IFERROR(__xludf.DUMMYFUNCTION("""COMPUTED_VALUE"""),"181750042 - Approved") -> 181750042 - Approved | C3: =IFERROR(__xludf.DUMMYFUNCTION("""COMPUTED_VALUE"""),2.0) -> 2 | D3: =IFERROR(__xludf.DUMMYFUNCTION("""COMPUTED_VALUE"""),"P-15904-00") -> P-15904-00 | E3: =IFERROR(__xludf.DUMMYFUNCTION("""COMPUTED_VALUE"""),"Filter Catridge; Type : TefTEC Series; P/N : TefTEC 0.2 - 5 P7S; Micron : 0.2 Micron; Lenght : 5 Inc; ; ;") -> Filter Catridge; Type : TefTEC Series; P/N : TefTEC 0.2 - 5 P7S; Micron : 0.2 Micron; Lenght : 5 Inc; ; ; | F3: =IFERROR(__xludf.DUMMYFUNCTION("""COMPUTED_VALUE"""),1.0) -> 1 | G3: =IFERROR(__xludf.DUMMYFUNCTION("""COMPUTED_VALUE"""),"Unit") -> Unit | H3: =IFERROR(__xludf.DUMMYFUNCTION("""COMPUTED_VALUE"""),"IDR") -> IDR | I3: =IFERROR(__xludf.DUMMYFUNCTION("""COMPUTED_VALUE"""),2850000.0) -> 2850000 | J3: =IFERROR(__xludf.DUMMYFUNCTION("""COMPUTED_VALUE"""),2850000.0) -> 2850000 | K3: =IFERROR(__xludf.DUMMYFUNCTION("""COMPUTED_VALUE"""),43189.0) -> 43189 | L3: =IFERROR(__xludf.DUMMYFUNCTION("""COMPUTED_VALUE"""),"FIP Engineering") -> FIP Engineering | M3: =IFERROR(__xludf.DUMMYFUNCTION("""COMPUTED_VALUE"""),"Joko Nugroho") -> Joko Nugroho | N3: =IFERROR(__xludf.DUMMYFUNCTION("""COMPUTED_VALUE"""),"FIP Engineering") -> FIP Engineering | O3: =IFERROR(__xludf.DUMMYFUNCTION("""COMPUTED_VALUE"""),"FIP-DOM-000-11304-OS00001-INA-000000") -> FIP-DOM-000-11304-OS00001-INA-000000 | P3: =IFERROR(__xludf.DUMMYFUNCTION("""COMPUTED_VALUE"""),"PO Closed") -> PO Closed | Q3: =IFERROR(__xludf.DUMMYFUNCTION("""COMPUTED_VALUE"""),"GL1802051") -> GL1802051 | R3: =IFERROR(__xludf.DUMMYFUNCTION("""COMPUTED_VALUE"""),43136.0) -> 43136 | S3: =IFERROR(__xludf.DUMMYFUNCTION("""COMPUTED_VALUE"""),"-") -> - | T3: =IFERROR(__xludf.DUMMYFUNCTION("""COMPUTED_VALUE"""),43160.0) -> 43160
A4: =IFERROR(__xludf.DUMMYFUNCTION("""COMPUTED_VALUE"""),"181750039-5") -> 181750039-5 | B4: =IFERROR(__xludf.DUMMYFUNCTION("""COMPUTED_VALUE"""),"181750039 - Approved") -> 181750039 - Approved | C4: =IFERROR(__xludf.DUMMYFUNCTION("""COMPUTED_VALUE"""),5.0) -> 5 | D4: =IFERROR(__xludf.DUMMYFUNCTION("""COMPUTED_VALUE"""),"P-15446-00") -> P-15446-00 | E4: =IFERROR(__xludf.DUMMYFUNCTION("""COMPUTED_VALUE"""),"Flowmeter Merk Wiebrock; 60 LPM 0-60 liter/menit; ; ;") -> Flowmeter Merk Wiebrock; 60 LPM 0-60 liter/menit; ; ; | F4: =IFERROR(__xludf.DUMMYFUNCTION("""COMPUTED_VALUE"""),2.0) -> 2 | G4: =IFERROR(__xludf.DUMMYFUNCTION("""COMPUTED_VALUE"""),"Unit") -> Unit | H4: =IFERROR(__xludf.DUMMYFUNCTION("""COMPUTED_VALUE"""),"IDR") -> IDR | I4: =IFERROR(__xludf.DUMMYFUNCTION("""COMPUTED_VALUE"""),876000.0) -> 876000 | J4: =IFERROR(__xludf.DUMMYFUNCTION("""COMPUTED_VALUE"""),1752000.0) -> 1752000 | K4: =IFERROR(__xludf.DUMMYFUNCTION("""COMPUTED_VALUE"""),43159.0) -> 43159 | L4: =IFERROR(__xludf.DUMMYFUNCTION("""COMPUTED_VALUE"""),"FIP General") -> FIP General | M4: =IFERROR(__xludf.DUMMYFUNCTION("""COMPUTED_VALUE"""),"Joko Nugroho") -> Joko Nugroho | N4: =IFERROR(__xludf.DUMMYFUNCTION("""COMPUTED_VALUE"""),"FIP Engineering") -> FIP Engineering | O4: =IFERROR(__xludf.DUMMYFUNCTION("""COMPUTED_VALUE"""),"FIP-DOM-ENG-51404-0000000-INA-000000") -> FIP-DOM-ENG-51404-0000000-INA-000000 | P4: =IFERROR(__xludf.DUMMYFUNCTION("""COMPUTED_VALUE"""),"PO Closed") -> PO Closed | Q4: =IFERROR(__xludf.DUMMYFUNCTION("""COMPUTED_VALUE"""),"GL1803032") -> GL1803032 | R4: =IFERROR(__xludf.DUMMYFUNCTION("""COMPUTED_VALUE"""),43139.0) -> 43139 | S4: =IFERROR(__xludf.DUMMYFUNCTION("""COMPUTED_VALUE"""),"-") -> - | T4: =IFERROR(__xludf.DUMMYFUNCTION("""COMPUTED_VALUE"""),43174.0) -> 43174
A5: =IFERROR(__xludf.DUMMYFUNCTION("""COMPUTED_VALUE"""),"181750039-5") -> 181750039-5 | B5: =IFERROR(__xludf.DUMMYFUNCTION("""COMPUTED_VALUE"""),"181750039 - Approved") -> 181750039 - Approved | C5: =IFERROR(__xludf.DUMMYFUNCTION("""COMPUTED_VALUE"""),5.0) -> 5 | D5: =IFERROR(__xludf.DUMMYFUNCTION("""COMPUTED_VALUE"""),"P-15448-00") -> P-15448-00 | E5: =IFERROR(__xludf.DUMMYFUNCTION("""COMPUTED_VALUE"""),"Flowmeter Mfg : Dwyer; Type : MMA-5; ; ;") -> Flowmeter Mfg : Dwyer; Type : MMA-5; ; ; | F5: =IFERROR(__xludf.DUMMYFUNCTION("""COMPUTED_VALUE"""),1.0) -> 1 | G5: =IFERROR(__xludf.DUMMYFUNCTION("""COMPUTED_VALUE"""),"Unit") -> Unit | H5: =IFERROR(__xludf.DUMMYFUNCTION("""COMPUTED_VALUE"""),"IDR") -> IDR | I5: =IFERROR(__xludf.DUMMYFUNCTION("""COMPUTED_VALUE"""),782000.0) -> 782000 | J5: =IFERROR(__xludf.DUMMYFUNCTION("""COMPUTED_VALUE"""),782000.0) -> 782000 | K5: =IFERROR(__xludf.DUMMYFUNCTION("""COMPUTED_VALUE"""),43159.0) -> 43159 | L5: =IFERROR(__xludf.DUMMYFUNCTION("""COMPUTED_VALUE"""),"FIP General") -> FIP General | M5: =IFERROR(__xludf.DUMMYFUNCTION("""COMPUTED_VALUE"""),"Joko Nugroho") -> Joko Nugroho | N5: =IFERROR(__xludf.DUMMYFUNCTION("""COMPUTED_VALUE"""),"FIP Engineering") -> FIP Engineering | O5: =IFERROR(__xludf.DUMMYFUNCTION("""COMPUTED_VALUE"""),"FIP-DOM-ENG-51404-0000000-INA-000000") -> FIP-DOM-ENG-51404-0000000-INA-000000 | P5: =IFERROR(__xludf.DUMMYFUNCTION("""COMPUTED_VALUE"""),"PO Closed") -> PO Closed | Q5: =IFERROR(__xludf.DUMMYFUNCTION("""COMPUTED_VALUE"""),"GL1802043") -> GL1802043 | R5: =IFERROR(__xludf.DUMMYFUNCTION("""COMPUTED_VALUE"""),43139.0) -> 43139 | S5: =IFERROR(__xludf.DUMMYFUNCTION("""COMPUTED_VALUE"""),"-") -> - | T5: =IFERROR(__xludf.DUMMYFUNCTION("""COMPUTED_VALUE"""),43208.0) -> 43208
A6: =IFERROR(__xludf.DUMMYFUNCTION("""COMPUTED_VALUE"""),"181750039-5") -> 181750039-5 | B6: =IFERROR(__xludf.DUMMYFUNCTION("""COMPUTED_VALUE"""),"181750039 - Approved") -> 181750039 - Approved | C6: =IFERROR(__xludf.DUMMYFUNCTION("""COMPUTED_VALUE"""),5.0) -> 5 | D6: =IFERROR(__xludf.DUMMYFUNCTION("""COMPUTED_VALUE"""),"P-15447-00") -> P-15447-00 | E6: =IFERROR(__xludf.DUMMYFUNCTION("""COMPUTED_VALUE"""),"Flowmeter Merk Wiebrock; 100 LPM, 0 - 100liter / menit; ; ;") -> Flowmeter Merk Wiebrock; 100 LPM, 0 - 100liter / menit; ; ; | F6: =IFERROR(__xludf.DUMMYFUNCTION("""COMPUTED_VALUE"""),1.0) -> 1 | G6: =IFERROR(__xludf.DUMMYFUNCTION("""COMPUTED_VALUE"""),"Unit") -> Unit | H6: =IFERROR(__xludf.DUMMYFUNCTION("""COMPUTED_VALUE"""),"IDR") -> IDR | I6: =IFERROR(__xludf.DUMMYFUNCTION("""COMPUTED_VALUE"""),792000.0) -> 792000 | J6: =IFERROR(__xludf.DUMMYFUNCTION("""COMPUTED_VALUE"""),792000.0) -> 792000 | K6: =IFERROR(__xludf.DUMMYFUNCTION("""COMPUTED_VALUE"""),43159.0) -> 43159 | L6: =IFERROR(__xludf.DUMMYFUNCTION("""COMPUTED_VALUE"""),"FIP General") -> FIP General | M6: =IFERROR(__xludf.DUMMYFUNCTION("""COMPUTED_VALUE"""),"Joko Nugroho") -> Joko Nugroho | N6: =IFERROR(__xludf.DUMMYFUNCTION("""COMPUTED_VALUE"""),"FIP Engineering") -> FIP Engineering | O6: =IFERROR(__xludf.DUMMYFUNCTION("""COMPUTED_VALUE"""),"FIP-DOM-ENG-51404-0000000-INA-000000") -> FIP-DOM-ENG-51404-0000000-INA-000000 | P6: =IFERROR(__xludf.DUMMYFUNCTION("""COMPUTED_VALUE"""),"PO Closed") -> PO Closed | Q6: =IFERROR(__xludf.DUMMYFUNCTION("""COMPUTED_VALUE"""),"GL1803052") -> GL1803052 | R6: =IFERROR(__xludf.DUMMYFUNCTION("""COMPUTED_VALUE"""),43139.0) -> 43139 | S6: =IFERROR(__xludf.DUMMYFUNCTION("""COMPUTED_VALUE"""),"-") -> - | T6: =IFERROR(__xludf.DUMMYFUNCTION("""COMPUTED_VALUE"""),43208.0) -> 43208
A7: =IFERROR(__xludf.DUMMYFUNCTION("""COMPUTED_VALUE"""),"181750039-5") -> 181750039-5 | B7: =IFERROR(__xludf.DUMMYFUNCTION("""COMPUTED_VALUE"""),"181750039 - Approved") -> 181750039 - Approved | C7: =IFERROR(__xludf.DUMMYFUNCTION("""COMPUTED_VALUE"""),5.0) -> 5 | D7: =IFERROR(__xludf.DUMMYFUNCTION("""COMPUTED_VALUE"""),"P-15449-00") -> P-15449-00 | E7: =IFERROR(__xludf.DUMMYFUNCTION("""COMPUTED_VALUE"""),"Flowmeter Mfg : Dwyer; Type : RMA-1-SSV-ARB; Range : 0.05-0.4 SCFH AIR; ; ;") -> Flowmeter Mfg : Dwyer; Type : RMA-1-SSV-ARB; Range : 0.05-0.4 SCFH AIR; ; ; | F7: =IFERROR(__xludf.DUMMYFUNCTION("""COMPUTED_VALUE"""),1.0) -> 1 | G7: =IFERROR(__xludf.DUMMYFUNCTION("""COMPUTED_VALUE"""),"Unit") -> Unit | H7: =IFERROR(__xludf.DUMMYFUNCTION("""COMPUTED_VALUE"""),"IDR") -> IDR | I7: =IFERROR(__xludf.DUMMYFUNCTION("""COMPUTED_VALUE"""),1232500.0) -> 1232500 | J7: =IFERROR(__xludf.DUMMYFUNCTION("""COMPUTED_VALUE"""),1232500.0) -> 1232500 | K7: =IFERROR(__xludf.DUMMYFUNCTION("""COMPUTED_VALUE"""),43159.0) -> 43159 | L7: =IFERROR(__xludf.DUMMYFUNCTION("""COMPUTED_VALUE"""),"FIP General") -> FIP General | M7: =IFERROR(__xludf.DUMMYFUNCTION("""COMPUTED_VALUE"""),"Joko Nugroho") -> Joko Nugroho | N7: =IFERROR(__xludf.DUMMYFUNCTION("""COMPUTED_VALUE"""),"FIP Engineering") -> FIP Engineering | O7: =IFERROR(__xludf.DUMMYFUNCTION("""COMPUTED_VALUE"""),"FIP-DOM-ENG-51404-0000000-INA-000000") -> FIP-DOM-ENG-51404-0000000-INA-000000 | P7: =IFERROR(__xludf.DUMMYFUNCTION("""COMPUTED_VALUE"""),"PO Closed") -> PO Closed | Q7: =IFERROR(__xludf.DUMMYFUNCTION("""COMPUTED_VALUE"""),"GL1802043") -> GL1802043 | R7: =IFERROR(__xludf.DUMMYFUNCTION("""COMPUTED_VALUE"""),43139.0) -> 43139 | S7: =IFERROR(__xludf.DUMMYFUNCTION("""COMPUTED_VALUE"""),"-") -> - | T7: =IFERROR(__xludf.DUMMYFUNCTION("""COMPUTED_VALUE"""),43208.0) -> 43208
A8: =IFERROR(__xludf.DUMMYFUNCTION("""COMPUTED_VALUE"""),"181750039-2") -> 181750039-2 | B8: =IFERROR(__xludf.DUMMYFUNCTION("""COMPUTED_VALUE"""),"181750039 - Approved") -> 181750039 - Approved | C8: =IFERROR(__xludf.DUMMYFUNCTION("""COMPUTED_VALUE"""),2.0) -> 2 | D8: =IFERROR(__xludf.DUMMYFUNCTION("""COMPUTED_VALUE"""),"O-15902-00") -> O-15902-00 | E8: =IFERROR(__xludf.DUMMYFUNCTION("""COMPUTED_VALUE"""),"Suction Cup capping size 6R; P/N : 011010; ; ;") -> Suction Cup capping size 6R; P/N : 011010; ; ; | F8: =IFERROR(__xludf.DUMMYFUNCTION("""COMPUTED_VALUE"""),12.0) -> 12 | G8: =IFERROR(__xludf.DUMMYFUNCTION("""COMPUTED_VALUE"""),"Pieces") -> Pieces | H8: =IFERROR(__xludf.DUMMYFUNCTION("""COMPUTED_VALUE"""),"IDR") -> IDR | I8: =IFERROR(__xludf.DUMMYFUNCTION("""COMPUTED_VALUE"""),36000.0) -> 36000 | J8: =IFERROR(__xludf.DUMMYFUNCTION("""COMPUTED_VALUE"""),432000.0) -> 432000 | K8: =IFERROR(__xludf.DUMMYFUNCTION("""COMPUTED_VALUE"""),43157.0) -> 43157 | L8: =IFERROR(__xludf.DUMMYFUNCTION("""COMPUTED_VALUE"""),"FIP Engineering") -> FIP Engineering | M8: =IFERROR(__xludf.DUMMYFUNCTION("""COMPUTED_VALUE"""),"Joko Nugroho") -> Joko Nugroho | N8: =IFERROR(__xludf.DUMMYFUNCTION("""COMPUTED_VALUE"""),"FIP Engineering") -> FIP Engineering | O8: =IFERROR(__xludf.DUMMYFUNCTION("""COMPUTED_VALUE"""),"FIP-DOM-000-11304-OS00001-INA-000000") -> FIP-DOM-000-11304-OS00001-INA-000000 | P8: =IFERROR(__xludf.DUMMYFUNCTION("""COMPUTED_VALUE"""),"PO Closed") -> PO Closed | Q8: =IFERROR(__xludf.DUMMYFUNCTION("""COMPUTED_VALUE"""),"GL1802044") -> GL1802044 | R8: =IFERROR(__xludf.DUMMYFUNCTION("""COMPUTED_VALUE"""),43144.0) -> 43144 | S8: =IFERROR(__xludf.DUMMYFUNCTION("""COMPUTED_VALUE"""),"-") -> - | T8: =IFERROR(__xludf.DUMMYFUNCTION("""COMPUTED_VALUE"""),43227.0) -> 43227
A9: =IFERROR(__xludf.DUMMYFUNCTION("""COMPUTED_VALUE"""),"181750047-3") -> 181750047-3 | B9: =IFERROR(__xludf.DUMMYFUNCTION("""COMPUTED_VALUE"""),"181750047 - Approved") -> 181750047 - Approved | C9: =IFERROR(__xludf.DUMMYFUNCTION("""COMPUTED_VALUE"""),3.0) -> 3 | D9: =IFERROR(__xludf.DUMMYFUNCTION("""COMPUTED_VALUE"""),"O-15902-00") -> O-15902-00 | E9: =IFERROR(__xludf.DUMMYFUNCTION("""COMPUTED_VALUE"""),"Suction Cup capping size 6R; P/N : 011010; ; ;") -> Suction Cup capping size 6R; P/N : 011010; ; ; | F9: =IFERROR(__xludf.DUMMYFUNCTION("""COMPUTED_VALUE"""),28.0) -> 28 | G9: =IFERROR(__xludf.DUMMYFUNCTION("""COMPUTED_VALUE"""),"Pieces") -> Pieces | H9: =IFERROR(__xludf.DUMMYFUNCTION("""COMPUTED_VALUE"""),"IDR") -> IDR | I9: =IFERROR(__xludf.DUMMYFUNCTION("""COMPUTED_VALUE"""),36000.0) -> 36000 | J9: =IFERROR(__xludf.DUMMYFUNCTION("""COMPUTED_VALUE"""),1008000.0) -> 1008000 | K9: =IFERROR(__xludf.DUMMYFUNCTION("""COMPUTED_VALUE"""),43171.0) -> 43171 | L9: =IFERROR(__xludf.DUMMYFUNCTION("""COMPUTED_VALUE"""),"FIP Engineering") -> FIP Engineering | M9: =IFERROR(__xludf.DUMMYFUNCTION("""COMPUTED_VALUE"""),"Joko Nugroho") -> Joko Nugroho | N9: =IFERROR(__xludf.DUMMYFUNCTION("""COMPUTED_VALUE"""),"FIP Engineering") -> FIP Engineering | O9: =IFERROR(__xludf.DUMMYFUNCTION("""COMPUTED_VALUE"""),"FIP-DOM-000-11304-OS00001-INA-000000") -> FIP-DOM-000-11304-OS00001-INA-000000 | P9: =IFERROR(__xludf.DUMMYFUNCTION("""COMPUTED_VALUE"""),"PO Closed") -> PO Closed | Q9: =IFERROR(__xludf.DUMMYFUNCTION("""COMPUTED_VALUE"""),"GL1802044") -> GL1802044 | R9: =IFERROR(__xludf.DUMMYFUNCTION("""COMPUTED_VALUE"""),43144.0) -> 43144 | S9: =IFERROR(__xludf.DUMMYFUNCTION("""COMPUTED_VALUE"""),"-") -> - | T9: =IFERROR(__xludf.DUMMYFUNCTION("""COMPUTED_VALUE"""),43227.0) -> 43227
A10: =IFERROR(__xludf.DUMMYFUNCTION("""COMPUTED_VALUE"""),"181750054-1") -> 181750054-1 | B10: =IFERROR(__xludf.DUMMYFUNCTION("""COMPUTED_VALUE"""),"181750054 - Approved") -> 181750054 - Approved | C10: =IFERROR(__xludf.DUMMYFUNCTION("""COMPUTED_VALUE"""),1.0) -> 1 | D10: =IFERROR(__xludf.DUMMYFUNCTION("""COMPUTED_VALUE"""),"O-14594-00") -> O-14594-00 | E10: =IFERROR(__xludf.DUMMYFUNCTION("""COMPUTED_VALUE"""),"Kit, membrane ozone 6510; ; ;") -> Kit, membrane ozone 6510; ; ; | F10: =IFERROR(__xludf.DUMMYFUNCTION("""COMPUTED_VALUE"""),1.0) -> 1 | G10: =IFERROR(__xludf.DUMMYFUNCTION("""COMPUTED_VALUE"""),"Unit") -> Unit | H10: =IFERROR(__xludf.DUMMYFUNCTION("""COMPUTED_VALUE"""),"IDR") -> IDR | I10: =IFERROR(__xludf.DUMMYFUNCTION("""COMPUTED_VALUE"""),1.032365E7) -> 10323650 | J10: =IFERROR(__xludf.DUMMYFUNCTION("""COMPUTED_VALUE"""),1.032365E7) -> 10323650 | K10: =IFERROR(__xludf.DUMMYFUNCTION("""COMPUTED_VALUE"""),43192.0) -> 43192 | L10: =IFERROR(__xludf.DUMMYFUNCTION("""COMPUTED_VALUE"""),"FIP Engineering") -> FIP Engineering | M10: =IFERROR(__xludf.DUMMYFUNCTION("""COMPUTED_VALUE"""),"Joko Nugroho") -> Joko Nugroho | N10: =IFERROR(__xludf.DUMMYFUNCTION("""COMPUTED_VALUE"""),"FIP Engineering") -> FIP Engineering | O10: =IFERROR(__xludf.DUMMYFUNCTION("""COMPUTED_VALUE"""),"FIP-DOM-000-11304-OS00001-INA-000000") -> FIP-DOM-000-11304-OS00001-INA-000000 | P10: =IFERROR(__xludf.DUMMYFUNCTION("""COMPUTED_VALUE"""),"PO Closed") -> PO Closed | Q10: =IFERROR(__xludf.DUMMYFUNCTION("""COMPUTED_VALUE"""),"GL1802045") -> GL1802045 | R10: =IFERROR(__xludf.DUMMYFUNCTION("""COMPUTED_VALUE"""),43145.0) -> 43145 | S10: =IFERROR(__xludf.DUMMYFUNCTION("""COMPUTED_VALUE"""),"-") -> - | T10: =IFERROR(__xludf.DUMMYFUNCTION("""COMPUTED_VALUE"""),43209.0) -> 43209
A11: =IFERROR(__xludf.DUMMYFUNCTION("""COMPUTED_VALUE"""),"181750047-3") -> 181750047-3 | B11: =IFERROR(__xludf.DUMMYFUNCTION("""COMPUTED_VALUE"""),"181750047 - Approved") -> 181750047 - Approved | C11: =IFERROR(__xludf.DUMMYFUNCTION("""COMPUTED_VALUE"""),3.0) -> 3 | D11: =IFERROR(__xludf.DUMMYFUNCTION("""COMPUTED_VALUE"""),"S-62033-00") -> S-62033-00 | E11: =IFERROR(__xludf.DUMMYFUNCTION("""COMPUTED_VALUE"""),"Regulator Hidrogen Yamato; ; ;") -> Regulator Hidrogen Yamato; ; ; | F11: =IFERROR(__xludf.DUMMYFUNCTION("""COMPUTED_VALUE"""),1.0) -> 1 | G11: =IFERROR(__xludf.DUMMYFUNCTION("""COMPUTED_VALUE"""),"Unit") -> Unit | H11: =IFERROR(__xludf.DUMMYFUNCTION("""COMPUTED_VALUE"""),"IDR") -> IDR | I11: =IFERROR(__xludf.DUMMYFUNCTION("""COMPUTED_VALUE"""),1260000.0) -> 1260000 | J11: =IFERROR(__xludf.DUMMYFUNCTION("""COMPUTED_VALUE"""),1260000.0) -> 1260000 | K11: =IFERROR(__xludf.DUMMYFUNCTION("""COMPUTED_VALUE"""),43159.0) -> 43159 | L11: =IFERROR(__xludf.DUMMYFUNCTION("""COMPUTED_VALUE"""),"FIP General") -> FIP General | M11: =IFERROR(__xludf.DUMMYFUNCTION("""COMPUTED_VALUE"""),"Joko Nugroho") -> Joko Nugroho | N11: =IFERROR(__xludf.DUMMYFUNCTION("""COMPUTED_VALUE"""),"FIP Engineering") -> FIP Engineering | O11: =IFERROR(__xludf.DUMMYFUNCTION("""COMPUTED_VALUE"""),"FIP-DOM-ENG-51504-0000000-INA-000000") -> FIP-DOM-ENG-51504-0000000-INA-000000 | P11: =IFERROR(__xludf.DUMMYFUNCTION("""COMPUTED_VALUE"""),"PO Closed") -> PO Closed | Q11: =IFERROR(__xludf.DUMMYFUNCTION("""COMPUTED_VALUE"""),"GL1806028") -> GL1806028 | R11: =IFERROR(__xludf.DUMMYFUNCTION("""COMPUTED_VALUE"""),43145.0) -> 43145 | S11: =IFERROR(__xludf.DUMMYFUNCTION("""COMPUTED_VALUE"""),"-") -> - | T11: =IFERROR(__xludf.DUMMYFUNCTION("""COMPUTED_VALUE"""),43280.0) -> 43280
A12: =IFERROR(__xludf.DUMMYFUNCTION("""COMPUTED_VALUE"""),"181750057-2") -> 181750057-2 | B12: =IFERROR(__xludf.DUMMYFUNCTION("""COMPUTED_VALUE"""),"181750057 - Approved") -> 181750057 - Approved | C12: =IFERROR(__xludf.DUMMYFUNCTION("""COMPUTED_VALUE"""),2.0) -> 2 | D12: =IFERROR(__xludf.DUMMYFUNCTION("""COMPUTED_VALUE"""),"P-51027-00") -> P-51027-00 | E12: =IFERROR(__xludf.DUMMYFUNCTION("""COMPUTED_VALUE"""),"Isolasi Kabel SCOTCH super 33+ size: 19 mmx20x0.177 mm ( vinyl electric tape ) Black 3M") -> Isolasi Kabel SCOTCH super 33+ size: 19 mmx20x0.177 mm ( vinyl electric tape ) Black 3M | F12: =IFERROR(__xludf.DUMMYFUNCTION("""COMPUTED_VALUE"""),3.0) -> 3 | G12: =IFERROR(__xludf.DUMMYFUNCTION("""COMPUTED_VALUE"""),"Pieces") -> Pieces | H12: =IFERROR(__xludf.DUMMYFUNCTION("""COMPUTED_VALUE"""),"IDR") -> IDR | I12: =IFERROR(__xludf.DUMMYFUNCTION("""COMPUTED_VALUE"""),47700.0) -> 47700 | J12: =IFERROR(__xludf.DUMMYFUNCTION("""COMPUTED_VALUE"""),143100.0) -> 143100 | K12: =IFERROR(__xludf.DUMMYFUNCTION("""COMPUTED_VALUE"""),43171.0) -> 43171 | L12: =IFERROR(__xludf.DUMMYFUNCTION("""COMPUTED_VALUE"""),"FIP Engineering") -> FIP Engineering | M12: =IFERROR(__xludf.DUMMYFUNCTION("""COMPUTED_VALUE"""),"Joko Nugroho") -> Joko Nugroho | N12: =IFERROR(__xludf.DUMMYFUNCTION("""COMPUTED_VALUE"""),"FIP Engineering") -> FIP Engineering | O12: =IFERROR(__xludf.DUMMYFUNCTION("""COMPUTED_VALUE"""),"FIP-DOM-000-11304-OS00001-INA-000000") -> FIP-DOM-000-11304-OS00001-INA-000000 | P12: =IFERROR(__xludf.DUMMYFUNCTION("""COMPUTED_VALUE"""),"PO Closed") -> PO Closed | Q12: =IFERROR(__xludf.DUMMYFUNCTION("""COMPUTED_VALUE"""),"GL1803022") -> GL1803022 | R12: =IFERROR(__xludf.DUMMYFUNCTION("""COMPUTED_VALUE"""),43146.0) -> 43146 | S12: =IFERROR(__xludf.DUMMYFUNCTION("""COMPUTED_VALUE"""),"-") -> - | T12: =IFERROR(__xludf.DUMMYFUNCTION("""COMPUTED_VALUE"""),43171.0) -> 43171
A13: =IFERROR(__xludf.DUMMYFUNCTION("""COMPUTED_VALUE"""),"181750057-3") -> 181750057-3 | B13: =IFERROR(__xludf.DUMMYFUNCTION("""COMPUTED_VALUE"""),"181750057 - Approved") -> 181750057 - Approved | C13: =IFERROR(__xludf.DUMMYFUNCTION("""COMPUTED_VALUE"""),3.0) -> 3 | D13: =IFERROR(__xludf.DUMMYFUNCTION("""COMPUTED_VALUE"""),"P-53214-00") -> P-53214-00 | E13: =IFERROR(__xludf.DUMMYFUNCTION("""COMPUTED_VALUE"""),"Epoxy Adhesive DEXTONE; ; ;") -> Epoxy Adhesive DEXTONE; ; ; | F13: =IFERROR(__xludf.DUMMYFUNCTION("""COMPUTED_VALUE"""),3.0) -> 3 | G13: =IFERROR(__xludf.DUMMYFUNCTION("""COMPUTED_VALUE"""),"Pieces") -> Pieces | H13: =IFERROR(__xludf.DUMMYFUNCTION("""COMPUTED_VALUE"""),"IDR") -> IDR | I13: =IFERROR(__xludf.DUMMYFUNCTION("""COMPUTED_VALUE"""),13500.0) -> 13500 | J13: =IFERROR(__xludf.DUMMYFUNCTION("""COMPUTED_VALUE"""),40500.0) -> 40500 | K13: =IFERROR(__xludf.DUMMYFUNCTION("""COMPUTED_VALUE"""),43171.0) -> 43171 | L13: =IFERROR(__xludf.DUMMYFUNCTION("""COMPUTED_VALUE"""),"FIP Engineering") -> FIP Engineering | M13: =IFERROR(__xludf.DUMMYFUNCTION("""COMPUTED_VALUE"""),"Joko Nugroho") -> Joko Nugroho | N13: =IFERROR(__xludf.DUMMYFUNCTION("""COMPUTED_VALUE"""),"FIP Engineering") -> FIP Engineering | O13: =IFERROR(__xludf.DUMMYFUNCTION("""COMPUTED_VALUE"""),"FIP-DOM-000-11304-OS00001-INA-000000") -> FIP-DOM-000-11304-OS00001-INA-000000 | P13: =IFERROR(__xludf.DUMMYFUNCTION("""COMPUTED_VALUE"""),"PO Closed") -> PO Closed | Q13: =IFERROR(__xludf.DUMMYFUNCTION("""COMPUTED_VALUE"""),"GL1803022") -> GL1803022 | R13: =IFERROR(__xludf.DUMMYFUNCTION("""COMPUTED_VALUE"""),43146.0) -> 43146 | S13: =IFERROR(__xludf.DUMMYFUNCTION("""COMPUTED_VALUE"""),"-") -> - | T13: =IFERROR(__xludf.DUMMYFUNCTION("""COMPUTED_VALUE"""),43171.0) -> 43171
A14: =IFERROR(__xludf.DUMMYFUNCTION("""COMPUTED_VALUE"""),"181750057-4") -> 181750057-4 | B14: =IFERROR(__xludf.DUMMYFUNCTION("""COMPUTED_VALUE"""),"181750057 - Approved") -> 181750057 - Approved | C14: =IFERROR(__xludf.DUMMYFUNCTION("""COMPUTED_VALUE"""),4.0) -> 4 | D14: =IFERROR(__xludf.DUMMYFUNCTION("""COMPUTED_VALUE"""),"P-12764-00") -> P-12764-00 | E14: =IFERROR(__xludf.DUMMYFUNCTION("""COMPUTED_VALUE"""),"Silicone gasket for ferrule dia 1/2inch Taiwan") -> Silicone gasket for ferrule dia 1/2inch Taiwan | F14: =IFERROR(__xludf.DUMMYFUNCTION("""COMPUTED_VALUE"""),6.0) -> 6 | G14: =IFERROR(__xludf.DUMMYFUNCTION("""COMPUTED_VALUE"""),"Pieces") -> Pieces | H14: =IFERROR(__xludf.DUMMYFUNCTION("""COMPUTED_VALUE"""),"IDR") -> IDR | I14: =IFERROR(__xludf.DUMMYFUNCTION("""COMPUTED_VALUE"""),8000.0) -> 8000 | J14: =IFERROR(__xludf.DUMMYFUNCTION("""COMPUTED_VALUE"""),48000.0) -> 48000 | K14: =IFERROR(__xludf.DUMMYFUNCTION("""COMPUTED_VALUE"""),43171.0) -> 43171 | L14: =IFERROR(__xludf.DUMMYFUNCTION("""COMPUTED_VALUE"""),"FIP Engineering") -> FIP Engineering | M14: =IFERROR(__xludf.DUMMYFUNCTION("""COMPUTED_VALUE"""),"Joko Nugroho") -> Joko Nugroho | N14: =IFERROR(__xludf.DUMMYFUNCTION("""COMPUTED_VALUE"""),"FIP Engineering") -> FIP Engineering | O14: =IFERROR(__xludf.DUMMYFUNCTION("""COMPUTED_VALUE"""),"FIP-DOM-000-11304-OS00001-INA-000000") -> FIP-DOM-000-11304-OS00001-INA-000000 | P14: =IFERROR(__xludf.DUMMYFUNCTION("""COMPUTED_VALUE"""),"PO Closed") -> PO Closed | Q14: =IFERROR(__xludf.DUMMYFUNCTION("""COMPUTED_VALUE"""),"GL1803022") -> GL1803022 | R14: =IFERROR(__xludf.DUMMYFUNCTION("""COMPUTED_VALUE"""),43146.0) -> 43146 | S14: =IFERROR(__xludf.DUMMYFUNCTION("""COMPUTED_VALUE"""),"-") -> - | T14: =IFERROR(__xludf.DUMMYFUNCTION("""COMPUTED_VALUE"""),43171.0) -> 43171
A15: =IFERROR(__xludf.DUMMYFUNCTION("""COMPUTED_VALUE"""),"181750057-5") -> 181750057-5 | B15: =IFERROR(__xludf.DUMMYFUNCTION("""COMPUTED_VALUE"""),"181750057 - Approved") -> 181750057 - Approved | C15: =IFERROR(__xludf.DUMMYFUNCTION("""COMPUTED_VALUE"""),5.0) -> 5 | D15: =IFERROR(__xludf.DUMMYFUNCTION("""COMPUTED_VALUE"""),"P-15862-00") -> P-15862-00 | E15: =IFERROR(__xludf.DUMMYFUNCTION("""COMPUTED_VALUE"""),"PAPER RECORD YOKOGAWA; FOLDING CHART B9565AW") -> PAPER RECORD YOKOGAWA; FOLDING CHART B9565AW | F15: =IFERROR(__xludf.DUMMYFUNCTION("""COMPUTED_VALUE"""),13.0) -> 13 | G15: =IFERROR(__xludf.DUMMYFUNCTION("""COMPUTED_VALUE"""),"Pieces") -> Pieces | H15: =IFERROR(__xludf.DUMMYFUNCTION("""COMPUTED_VALUE"""),"IDR") -> IDR | I15: =IFERROR(__xludf.DUMMYFUNCTION("""COMPUTED_VALUE"""),220000.0) -> 220000 | J15: =IFERROR(__xludf.DUMMYFUNCTION("""COMPUTED_VALUE"""),2860000.0) -> 2860000 | K15: =IFERROR(__xludf.DUMMYFUNCTION("""COMPUTED_VALUE"""),43171.0) -> 43171 | L15: =IFERROR(__xludf.DUMMYFUNCTION("""COMPUTED_VALUE"""),"FIP Engineering") -> FIP Engineering | M15: =IFERROR(__xludf.DUMMYFUNCTION("""COMPUTED_VALUE"""),"Joko Nugroho") -> Joko Nugroho | N15: =IFERROR(__xludf.DUMMYFUNCTION("""COMPUTED_VALUE"""),"FIP Engineering") -> FIP Engineering | O15: =IFERROR(__xludf.DUMMYFUNCTION("""COMPUTED_VALUE"""),"FIP-DOM-000-11304-OS00001-INA-000000") -> FIP-DOM-000-11304-OS00001-INA-000000 | P15: =IFERROR(__xludf.DUMMYFUNCTION("""COMPUTED_VALUE"""),"PO Closed") -> PO Closed | Q15: =IFERROR(__xludf.DUMMYFUNCTION("""COMPUTED_VALUE"""),"GL1803026") -> GL1803026 | R15: =IFERROR(__xludf.DUMMYFUNCTION("""COMPUTED_VALUE"""),43146.0) -> 43146 | S15: =IFERROR(__xludf.DUMMYFUNCTION("""COMPUTED_VALUE"""),"-") -> - | T15: =IFERROR(__xludf.DUMMYFUNCTION("""COMPUTED_VALUE"""),43171.0) -> 43171
A16: =IFERROR(__xludf.DUMMYFUNCTION("""COMPUTED_VALUE"""),"181750057-6") -> 181750057-6 | B16: =IFERROR(__xludf.DUMMYFUNCTION("""COMPUTED_VALUE"""),"181750057 - Approved") -> 181750057 - Approved | C16: =IFERROR(__xludf.DUMMYFUNCTION("""COMPUTED_VALUE"""),6.0) -> 6 | D16: =IFERROR(__xludf.DUMMYFUNCTION("""COMPUTED_VALUE"""),"P-10945-00") -> P-10945-00 | E16: =IFERROR(__xludf.DUMMYFUNCTION("""COMPUTED_VALUE"""),"Insulation - Seal Tape onda") -> Insulation - Seal Tape onda | F16: =IFERROR(__xludf.DUMMYFUNCTION("""COMPUTED_VALUE"""),9.0) -> 9 | G16: =IFERROR(__xludf.DUMMYFUNCTION("""COMPUTED_VALUE"""),"Pieces") -> Pieces | H16: =IFERROR(__xludf.DUMMYFUNCTION("""COMPUTED_VALUE"""),"IDR") -> IDR | I16: =IFERROR(__xludf.DUMMYFUNCTION("""COMPUTED_VALUE"""),4500.0) -> 4500 | J16: =IFERROR(__xludf.DUMMYFUNCTION("""COMPUTED_VALUE"""),40500.0) -> 40500 | K16: =IFERROR(__xludf.DUMMYFUNCTION("""COMPUTED_VALUE"""),43171.0) -> 43171 | L16: =IFERROR(__xludf.DUMMYFUNCTION("""COMPUTED_VALUE"""),"FIP Engineering") -> FIP Engineering | M16: =IFERROR(__xludf.DUMMYFUNCTION("""COMPUTED_VALUE"""),"Joko Nugroho") -> Joko Nugroho | N16: =IFERROR(__xludf.DUMMYFUNCTION("""COMPUTED_VALUE"""),"FIP Engineering") -> FIP Engineering | O16: =IFERROR(__xludf.DUMMYFUNCTION("""COMPUTED_VALUE"""),"FIP-DOM-000-11304-OS00001-INA-000000") -> FIP-DOM-000-11304-OS00001-INA-000000 | P16: =IFERROR(__xludf.DUMMYFUNCTION("""COMPUTED_VALUE"""),"PO Closed") -> PO Closed | Q16: =IFERROR(__xludf.DUMMYFUNCTION("""COMPUTED_VALUE"""),"GL1803022") -> GL1803022 | R16: =IFERROR(__xludf.DUMMYFUNCTION("""COMPUTED_VALUE"""),43146.0) -> 43146 | S16: =IFERROR(__xludf.DUMMYFUNCTION("""COMPUTED_VALUE"""),"-") -> - | T16: =IFERROR(__xludf.DUMMYFUNCTION("""COMPUTED_VALUE"""),43171.0) -> 43171
A17: =IFERROR(__xludf.DUMMYFUNCTION("""COMPUTED_VALUE"""),"181750057-7") -> 181750057-7 | B17: =IFERROR(__xludf.DUMMYFUNCTION("""COMPUTED_VALUE"""),"181750057 - Approved") -> 181750057 - Approved | C17: =IFERROR(__xludf.DUMMYFUNCTION("""COMPUTED_VALUE"""),7.0) -> 7 | D17: =IFERROR(__xludf.DUMMYFUNCTION("""COMPUTED_VALUE"""),"O-15490-00") -> O-15490-00 | E17: =IFERROR(__xludf.DUMMYFUNCTION("""COMPUTED_VALUE"""),"B63 Brand : Optibelt / Bando Merah; Optibelt; ;") -> B63 Brand : Optibelt / Bando Merah; Optibelt; ; | F17: =IFERROR(__xludf.DUMMYFUNCTION("""COMPUTED_VALUE"""),2.0) -> 2 | G17: =IFERROR(__xludf.DUMMYFUNCTION("""COMPUTED_VALUE"""),"Pieces") -> Pieces | H17: =IFERROR(__xludf.DUMMYFUNCTION("""COMPUTED_VALUE"""),"IDR") -> IDR | I17: =IFERROR(__xludf.DUMMYFUNCTION("""COMPUTED_VALUE"""),141800.0) -> 141800 | J17: =IFERROR(__xludf.DUMMYFUNCTION("""COMPUTED_VALUE"""),283600.0) -> 283600 | K17: =IFERROR(__xludf.DUMMYFUNCTION("""COMPUTED_VALUE"""),43171.0) -> 43171 | L17: =IFERROR(__xludf.DUMMYFUNCTION("""COMPUTED_VALUE"""),"FIP Engineering") -> FIP Engineering | M17: =IFERROR(__xludf.DUMMYFUNCTION("""COMPUTED_VALUE"""),"Joko Nugroho") -> Joko Nugroho | N17: =IFERROR(__xludf.DUMMYFUNCTION("""COMPUTED_VALUE"""),"FIP Engineering") -> FIP Engineering | O17: =IFERROR(__xludf.DUMMYFUNCTION("""COMPUTED_VALUE"""),"FIP-DOM-000-11304-OS00001-INA-000000") -> FIP-DOM-000-11304-OS00001-INA-000000 | P17: =IFERROR(__xludf.DUMMYFUNCTION("""COMPUTED_VALUE"""),"PO Closed") -> PO Closed | Q17: =IFERROR(__xludf.DUMMYFUNCTION("""COMPUTED_VALUE"""),"GL1803023") -> GL1803023 | R17: =IFERROR(__xludf.DUMMYFUNCTION("""COMPUTED_VALUE"""),43146.0) -> 43146 | S17: =IFERROR(__xludf.DUMMYFUNCTION("""COMPUTED_VALUE"""),"-") -> - | T17: =IFERROR(__xludf.DUMMYFUNCTION("""COMPUTED_VALUE"""),43192.0) -> 43192
A18: =IFERROR(__xludf.DUMMYFUNCTION("""COMPUTED_VALUE"""),"181750057-8") -> 181750057-8 | B18: =IFERROR(__xludf.DUMMYFUNCTION("""COMPUTED_VALUE"""),"181750057 - Approved") -> 181750057 - Approved | C18: =IFERROR(__xludf.DUMMYFUNCTION("""COMPUTED_VALUE"""),8.0) -> 8 | D18: =IFERROR(__xludf.DUMMYFUNCTION("""COMPUTED_VALUE"""),"P-12464-00") -> P-12464-00 | E18: =IFERROR(__xludf.DUMMYFUNCTION("""COMPUTED_VALUE"""),"Lem Aibon 1 gal/ kaleng") -> Lem Aibon 1 gal/ kaleng | F18: =IFERROR(__xludf.DUMMYFUNCTION("""COMPUTED_VALUE"""),1.0) -> 1 | G18: =IFERROR(__xludf.DUMMYFUNCTION("""COMPUTED_VALUE"""),"Pieces") -> Pieces | H18: =IFERROR(__xludf.DUMMYFUNCTION("""COMPUTED_VALUE"""),"IDR") -> IDR | I18: =IFERROR(__xludf.DUMMYFUNCTION("""COMPUTED_VALUE"""),11500.0) -> 11500 | J18: =IFERROR(__xludf.DUMMYFUNCTION("""COMPUTED_VALUE"""),11500.0) -> 11500 | K18: =IFERROR(__xludf.DUMMYFUNCTION("""COMPUTED_VALUE"""),43171.0) -> 43171 | L18: =IFERROR(__xludf.DUMMYFUNCTION("""COMPUTED_VALUE"""),"FIP Engineering") -> FIP Engineering | M18: =IFERROR(__xludf.DUMMYFUNCTION("""COMPUTED_VALUE"""),"Joko Nugroho") -> Joko Nugroho | N18: =IFERROR(__xludf.DUMMYFUNCTION("""COMPUTED_VALUE"""),"FIP Engineering") -> FIP Engineering | O18: =IFERROR(__xludf.DUMMYFUNCTION("""COMPUTED_VALUE"""),"FIP-DOM-000-11304-OS00001-INA-000000") -> FIP-DOM-000-11304-OS00001-INA-000000 | P18: =IFERROR(__xludf.DUMMYFUNCTION("""COMPUTED_VALUE"""),"PO Closed") -> PO Closed | Q18: =IFERROR(__xludf.DUMMYFUNCTION("""COMPUTED_VALUE"""),"GL1803022") -> GL1803022 | R18: =IFERROR(__xludf.DUMMYFUNCTION("""COMPUTED_VALUE"""),43146.0) -> 43146 | S18: =IFERROR(__xludf.DUMMYFUNCTION("""COMPUTED_VALUE"""),"-") -> - | T18: =IFERROR(__xludf.DUMMYFUNCTION("""COMPUTED_VALUE"""),43171.0) -> 43171
A19: =IFERROR(__xludf.DUMMYFUNCTION("""COMPUTED_VALUE"""),"181750057-9") -> 181750057-9 | B19: =IFERROR(__xludf.DUMMYFUNCTION("""COMPUTED_VALUE"""),"181750057 - Approved") -> 181750057 - Approved | C19: =IFERROR(__xludf.DUMMYFUNCTION("""COMPUTED_VALUE"""),9.0) -> 9 | D19: =IFERROR(__xludf.DUMMYFUNCTION("""COMPUTED_VALUE"""),"Q-10234-00") -> Q-10234-00 | E19: =IFERROR(__xludf.DUMMYFUNCTION("""COMPUTED_VALUE"""),"Silicone Sealant N10 Grey; ; ;") -> Silicone Sealant N10 Grey; ; ; | F19: =IFERROR(__xludf.DUMMYFUNCTION("""COMPUTED_VALUE"""),8.0) -> 8 | G19: =IFERROR(__xludf.DUMMYFUNCTION("""COMPUTED_VALUE"""),"Pieces") -> Pieces | H19: =IFERROR(__xludf.DUMMYFUNCTION("""COMPUTED_VALUE"""),"IDR") -> IDR | I19: =IFERROR(__xludf.DUMMYFUNCTION("""COMPUTED_VALUE"""),45000.0) -> 45000 | J19: =IFERROR(__xludf.DUMMYFUNCTION("""COMPUTED_VALUE"""),360000.0) -> 360000 | K19: =IFERROR(__xludf.DUMMYFUNCTION("""COMPUTED_VALUE"""),43171.0) -> 43171 | L19: =IFERROR(__xludf.DUMMYFUNCTION("""COMPUTED_VALUE"""),"FIP Engineering") -> FIP Engineering | M19: =IFERROR(__xludf.DUMMYFUNCTION("""COMPUTED_VALUE"""),"Joko Nugroho") -> Joko Nugroho | N19: =IFERROR(__xludf.DUMMYFUNCTION("""COMPUTED_VALUE"""),"FIP Engineering") -> FIP Engineering | O19: =IFERROR(__xludf.DUMMYFUNCTION("""COMPUTED_VALUE"""),"FIP-DOM-000-11304-OS00001-INA-000000") -> FIP-DOM-000-11304-OS00001-INA-000000 | P19: =IFERROR(__xludf.DUMMYFUNCTION("""COMPUTED_VALUE"""),"PO Closed") -> PO Closed | Q19: =IFERROR(__xludf.DUMMYFUNCTION("""COMPUTED_VALUE"""),"GL1803022") -> GL1803022 | R19: =IFERROR(__xludf.DUMMYFUNCTION("""COMPUTED_VALUE"""),43146.0) -> 43146 | S19: =IFERROR(__xludf.DUMMYFUNCTION("""COMPUTED_VALUE"""),"-") -> - | T19: =IFERROR(__xludf.DUMMYFUNCTION("""COMPUTED_VALUE"""),43171.0) -> 43171
A20: =IFERROR(__xludf.DUMMYFUNCTION("""COMPUTED_VALUE"""),"181750058-5") -> 181750058-5 | B20: =IFERROR(__xludf.DUMMYFUNCTION("""COMPUTED_VALUE"""),"181750058 - Approved") -> 181750058 - Approved | C20: =IFERROR(__xludf.DUMMYFUNCTION("""COMPUTED_VALUE"""),5.0) -> 5 | D20: =IFERROR(__xludf.DUMMYFUNCTION("""COMPUTED_VALUE"""),"O-15820-00") -> O-15820-00 | E20: =IFERROR(__xludf.DUMMYFUNCTION("""COMPUTED_VALUE"""),"MCB Schneider C60H 1 phase 1 pole 2 A 100000A") -> MCB Schneider C60H 1 phase 1 pole 2 A 100000A | F20: =IFERROR(__xludf.DUMMYFUNCTION("""COMPUTED_VALUE"""),2.0) -> 2 | G20: =IFERROR(__xludf.DUMMYFUNCTION("""COMPUTED_VALUE"""),"Pieces") -> Pieces | H20: =IFERROR(__xludf.DUMMYFUNCTION("""COMPUTED_VALUE"""),"IDR") -> IDR | I20: =IFERROR(__xludf.DUMMYFUNCTION("""COMPUTED_VALUE"""),118500.0) -> 118500 | J20: =IFERROR(__xludf.DUMMYFUNCTION("""COMPUTED_VALUE"""),237000.0) -> 237000 | K20: =IFERROR(__xludf.DUMMYFUNCTION("""COMPUTED_VALUE"""),43171.0) -> 43171 | L20: =IFERROR(__xludf.DUMMYFUNCTION("""COMPUTED_VALUE"""),"FIP Engineering") -> FIP Engineering | M20: =IFERROR(__xludf.DUMMYFUNCTION("""COMPUTED_VALUE"""),"Joko Nugroho") -> Joko Nugroho | N20: =IFERROR(__xludf.DUMMYFUNCTION("""COMPUTED_VALUE"""),"FIP Engineering") -> FIP Engineering | O20: =IFERROR(__xludf.DUMMYFUNCTION("""COMPUTED_VALUE"""),"FIP-DOM-000-11304-OS00001-INA-000000") -> FIP-DOM-000-11304-OS00001-INA-000000 | P20: =IFERROR(__xludf.DUMMYFUNCTION("""COMPUTED_VALUE"""),"PO Closed") -> PO Closed | Q20: =IFERROR(__xludf.DUMMYFUNCTION("""COMPUTED_VALUE"""),"GL1715059") -> GL1715059 | R20: =IFERROR(__xludf.DUMMYFUNCTION("""COMPUTED_VALUE"""),43149.0) -> 43149 | S20: =IFERROR(__xludf.DUMMYFUNCTION("""COMPUTED_VALUE"""),"-") -> - | T20: =IFERROR(__xludf.DUMMYFUNCTION("""COMPUTED_VALUE"""),43174.0) -> 43174
A21: =IFERROR(__xludf.DUMMYFUNCTION("""COMPUTED_VALUE"""),"181750057-10") -> 181750057-10 | B21: =IFERROR(__xludf.DUMMYFUNCTION("""COMPUTED_VALUE"""),"181750057 - Approved") -> 181750057 - Approved | C21: =IFERROR(__xludf.DUMMYFUNCTION("""COMPUTED_VALUE"""),10.0) -> 10 | D21: =IFERROR(__xludf.DUMMYFUNCTION("""COMPUTED_VALUE"""),"P-14455-00") -> P-14455-00 | E21: =IFERROR(__xludf.DUMMYFUNCTION("""COMPUTED_VALUE"""),"Filter IAF MBV Series (Medium Filter), efficiency : 80-85 %, Size: 24 x 24 x 12 inch; IAF; ;") -> Filter IAF MBV Series (Medium Filter), efficiency : 80-85 %, Size: 24 x 24 x 12 inch; IAF; ; | F21: =IFERROR(__xludf.DUMMYFUNCTION("""COMPUTED_VALUE"""),6.0) -> 6 | G21: =IFERROR(__xludf.DUMMYFUNCTION("""COMPUTED_VALUE"""),"Pieces") -> Pieces | H21: =IFERROR(__xludf.DUMMYFUNCTION("""COMPUTED_VALUE"""),"IDR") -> IDR | I21: =IFERROR(__xludf.DUMMYFUNCTION("""COMPUTED_VALUE"""),1600000.0) -> 1600000 | J21: =IFERROR(__xludf.DUMMYFUNCTION("""COMPUTED_VALUE"""),9600000.0) -> 9600000 | K21: =IFERROR(__xludf.DUMMYFUNCTION("""COMPUTED_VALUE"""),43178.0) -> 43178 | L21: =IFERROR(__xludf.DUMMYFUNCTION("""COMPUTED_VALUE"""),"FIP Engineering") -> FIP Engineering | M21: =IFERROR(__xludf.DUMMYFUNCTION("""COMPUTED_VALUE"""),"Joko Nugroho") -> Joko Nugroho | N21: =IFERROR(__xludf.DUMMYFUNCTION("""COMPUTED_VALUE"""),"FIP Engineering") -> FIP Engineering | O21: =IFERROR(__xludf.DUMMYFUNCTION("""COMPUTED_VALUE"""),"FIP-DOM-000-11304-OS00001-INA-000000") -> FIP-DOM-000-11304-OS00001-INA-000000 | P21: =IFERROR(__xludf.DUMMYFUNCTION("""COMPUTED_VALUE"""),"PO Closed") -> PO Closed | Q21: =IFERROR(__xludf.DUMMYFUNCTION("""COMPUTED_VALUE"""),"GL1803025") -> GL1803025 | R21: =IFERROR(__xludf.DUMMYFUNCTION("""COMPUTED_VALUE"""),43151.0) -> 43151 | S21: =IFERROR(__xludf.DUMMYFUNCTION("""COMPUTED_VALUE"""),"-") -> - | T21: =IFERROR(__xludf.DUMMYFUNCTION("""COMPUTED_VALUE"""),43187.0) -> 43187
A22: =IFERROR(__xludf.DUMMYFUNCTION("""COMPUTED_VALUE"""),"181750057-11") -> 181750057-11 | B22: =IFERROR(__xludf.DUMMYFUNCTION("""COMPUTED_VALUE"""),"181750057 - Approved") -> 181750057 - Approved | C22: =IFERROR(__xludf.DUMMYFUNCTION("""COMPUTED_VALUE"""),11.0) -> 11 | D22: =IFERROR(__xludf.DUMMYFUNCTION("""COMPUTED_VALUE"""),"P-14456-00") -> P-14456-00 | E22: =IFERROR(__xludf.DUMMYFUNCTION("""COMPUTED_VALUE"""),"Filter IAF MBV Series (Medium Filter), efficiency : 80-85 %, Size: 12 x 24 x 12 inch; IAF; ;") -> Filter IAF MBV Series (Medium Filter), efficiency : 80-85 %, Size: 12 x 24 x 12 inch; IAF; ; | F22: =IFERROR(__xludf.DUMMYFUNCTION("""COMPUTED_VALUE"""),7.0) -> 7 | G22: =IFERROR(__xludf.DUMMYFUNCTION("""COMPUTED_VALUE"""),"Pieces") -> Pieces | H22: =IFERROR(__xludf.DUMMYFUNCTION("""COMPUTED_VALUE"""),"IDR") -> IDR | I22: =IFERROR(__xludf.DUMMYFUNCTION("""COMPUTED_VALUE"""),540000.0) -> 540000 | J22: =IFERROR(__xludf.DUMMYFUNCTION("""COMPUTED_VALUE"""),3780000.0) -> 3780000 | K22: =IFERROR(__xludf.DUMMYFUNCTION("""COMPUTED_VALUE"""),43178.0) -> 43178 | L22: =IFERROR(__xludf.DUMMYFUNCTION("""COMPUTED_VALUE"""),"FIP Engineering") -> FIP Engineering | M22: =IFERROR(__xludf.DUMMYFUNCTION("""COMPUTED_VALUE"""),"Joko Nugroho") -> Joko Nugroho | N22: =IFERROR(__xludf.DUMMYFUNCTION("""COMPUTED_VALUE"""),"FIP Engineering") -> FIP Engineering | O22: =IFERROR(__xludf.DUMMYFUNCTION("""COMPUTED_VALUE"""),"FIP-DOM-000-11304-OS00001-INA-000000") -> FIP-DOM-000-11304-OS00001-INA-000000 | P22: =IFERROR(__xludf.DUMMYFUNCTION("""COMPUTED_VALUE"""),"PO Closed") -> PO Closed | Q22: =IFERROR(__xludf.DUMMYFUNCTION("""COMPUTED_VALUE"""),"GL1803025") -> GL1803025 | R22: =IFERROR(__xludf.DUMMYFUNCTION("""COMPUTED_VALUE"""),43151.0) -> 43151 | S22: =IFERROR(__xludf.DUMMYFUNCTION("""COMPUTED_VALUE"""),"-") -> - | T22: =IFERROR(__xludf.DUMMYFUNCTION("""COMPUTED_VALUE"""),43187.0) -> 43187
A23: =IFERROR(__xludf.DUMMYFUNCTION("""COMPUTED_VALUE"""),"181750057-12") -> 181750057-12 | B23: =IFERROR(__xludf.DUMMYFUNCTION("""COMPUTED_VALUE"""),"181750057 - Approved") -> 181750057 - Approved | C23: =IFERROR(__xludf.DUMMYFUNCTION("""COMPUTED_VALUE"""),12.0) -> 12 | D23: =IFERROR(__xludf.DUMMYFUNCTION("""COMPUTED_VALUE"""),"P-14457-00") -> P-14457-00 | E23: =IFERROR(__xludf.DUMMYFUNCTION("""COMPUTED_VALUE"""),"Filter IAF MBV Series (Medium Filter), efficiency : 90-95 %, Size: 24 x 24 x 12 inch; IAF; ;") -> Filter IAF MBV Series (Medium Filter), efficiency : 90-95 %, Size: 24 x 24 x 12 inch; IAF; ; | F23: =IFERROR(__xludf.DUMMYFUNCTION("""COMPUTED_VALUE"""),8.0) -> 8 | G23: =IFERROR(__xludf.DUMMYFUNCTION("""COMPUTED_VALUE"""),"Pieces") -> Pieces | H23: =IFERROR(__xludf.DUMMYFUNCTION("""COMPUTED_VALUE"""),"IDR") -> IDR | I23: =IFERROR(__xludf.DUMMYFUNCTION("""COMPUTED_VALUE"""),1800000.0) -> 1800000 | J23: =IFERROR(__xludf.DUMMYFUNCTION("""COMPUTED_VALUE"""),1.44E7) -> 14400000 | K23: =IFERROR(__xludf.DUMMYFUNCTION("""COMPUTED_VALUE"""),43178.0) -> 43178 | L23: =IFERROR(__xludf.DUMMYFUNCTION("""COMPUTED_VALUE"""),"FIP Engineering") -> FIP Engineering | M23: =IFERROR(__xludf.DUMMYFUNCTION("""COMPUTED_VALUE"""),"Joko Nugroho") -> Joko Nugroho | N23: =IFERROR(__xludf.DUMMYFUNCTION("""COMPUTED_VALUE"""),"FIP Engineering") -> FIP Engineering | O23: =IFERROR(__xludf.DUMMYFUNCTION("""COMPUTED_VALUE"""),"FIP-DOM-000-11304-OS00001-INA-000000") -> FIP-DOM-000-11304-OS00001-INA-000000 | P23: =IFERROR(__xludf.DUMMYFUNCTION("""COMPUTED_VALUE"""),"PO Closed") -> PO Closed | Q23: =IFERROR(__xludf.DUMMYFUNCTION("""COMPUTED_VALUE"""),"GL1803025") -> GL1803025 | R23: =IFERROR(__xludf.DUMMYFUNCTION("""COMPUTED_VALUE"""),43151.0) -> 43151 | S23: =IFERROR(__xludf.DUMMYFUNCTION("""COMPUTED_VALUE"""),"-") -> - | T23: =IFERROR(__xludf.DUMMYFUNCTION("""COMPUTED_VALUE"""),43187.0) -> 43187
A24: =IFERROR(__xludf.DUMMYFUNCTION("""COMPUTED_VALUE"""),"181750057-13") -> 181750057-13 | B24: =IFERROR(__xludf.DUMMYFUNCTION("""COMPUTED_VALUE"""),"181750057 - Approved") -> 181750057 - Approved | C24: =IFERROR(__xludf.DUMMYFUNCTION("""COMPUTED_VALUE"""),13.0) -> 13 | D24: =IFERROR(__xludf.DUMMYFUNCTION("""COMPUTED_VALUE"""),"P-14458-00") -> P-14458-00 | E24: =IFERROR(__xludf.DUMMYFUNCTION("""COMPUTED_VALUE"""),"Filter IAF MBV Series (Medium Filter), efficiency : 90-95 %, Size: 12 x 24 x 12 inch; IAF; ;") -> Filter IAF MBV Series (Medium Filter), efficiency : 90-95 %, Size: 12 x 24 x 12 inch; IAF; ; | F24: =IFERROR(__xludf.DUMMYFUNCTION("""COMPUTED_VALUE"""),3.0) -> 3 | G24: =IFERROR(__xludf.DUMMYFUNCTION("""COMPUTED_VALUE"""),"Pieces") -> Pieces | H24: =IFERROR(__xludf.DUMMYFUNCTION("""COMPUTED_VALUE"""),"IDR") -> IDR | I24: =IFERROR(__xludf.DUMMYFUNCTION("""COMPUTED_VALUE"""),1200000.0) -> 1200000 | J24: =IFERROR(__xludf.DUMMYFUNCTION("""COMPUTED_VALUE"""),3600000.0) -> 3600000 | K24: =IFERROR(__xludf.DUMMYFUNCTION("""COMPUTED_VALUE"""),43178.0) -> 43178 | L24: =IFERROR(__xludf.DUMMYFUNCTION("""COMPUTED_VALUE"""),"FIP Engineering") -> FIP Engineering | M24: =IFERROR(__xludf.DUMMYFUNCTION("""COMPUTED_VALUE"""),"Joko Nugroho") -> Joko Nugroho | N24: =IFERROR(__xludf.DUMMYFUNCTION("""COMPUTED_VALUE"""),"FIP Engineering") -> FIP Engineering | O24: =IFERROR(__xludf.DUMMYFUNCTION("""COMPUTED_VALUE"""),"FIP-DOM-000-11304-OS00001-INA-000000") -> FIP-DOM-000-11304-OS00001-INA-000000 | P24: =IFERROR(__xludf.DUMMYFUNCTION("""COMPUTED_VALUE"""),"PO Closed") -> PO Closed | Q24: =IFERROR(__xludf.DUMMYFUNCTION("""COMPUTED_VALUE"""),"GL1803025") -> GL1803025 | R24: =IFERROR(__xludf.DUMMYFUNCTION("""COMPUTED_VALUE"""),43151.0) -> 43151 | S24: =IFERROR(__xludf.DUMMYFUNCTION("""COMPUTED_VALUE"""),"-") -> - | T24: =IFERROR(__xludf.DUMMYFUNCTION("""COMPUTED_VALUE"""),43187.0) -> 43187
A25: =IFERROR(__xludf.DUMMYFUNCTION("""COMPUTED_VALUE"""),"181750060-2") -> 181750060-2 | B25: =IFERROR(__xludf.DUMMYFUNCTION("""COMPUTED_VALUE"""),"181750060 - Approved") -> 181750060 - Approved | C25: =IFERROR(__xludf.DUMMYFUNCTION("""COMPUTED_VALUE"""),2.0) -> 2 | D25: =IFERROR(__xludf.DUMMYFUNCTION("""COMPUTED_VALUE"""),"O-15918-00") -> O-15918-00 | E25: =IFERROR(__xludf.DUMMYFUNCTION("""COMPUTED_VALUE"""),"Fedegari FVA2/A1 - O-RING 15.47x3.53 ; Code : CC150170; ; ;") -> Fedegari FVA2/A1 - O-RING 15.47x3.53 ; Code : CC150170; ; ; | F25: =IFERROR(__xludf.DUMMYFUNCTION("""COMPUTED_VALUE"""),5.0) -> 5 | G25: =IFERROR(__xludf.DUMMYFUNCTION("""COMPUTED_VALUE"""),"Unit") -> Unit | H25: =IFERROR(__xludf.DUMMYFUNCTION("""COMPUTED_VALUE"""),"EUR") -> EUR | I25: =IFERROR(__xludf.DUMMYFUNCTION("""COMPUTED_VALUE"""),3.66) -> 3.66 | J25: =IFERROR(__xludf.DUMMYFUNCTION("""COMPUTED_VALUE"""),18.3) -> 18.3 | K25: =IFERROR(__xludf.DUMMYFUNCTION("""COMPUTED_VALUE"""),43221.0) -> 43221 | L25: =IFERROR(__xludf.DUMMYFUNCTION("""COMPUTED_VALUE"""),"FIP Engineering") -> FIP Engineering | M25: =IFERROR(__xludf.DUMMYFUNCTION("""COMPUTED_VALUE"""),"Joko Nugroho") -> Joko Nugroho | N25: =IFERROR(__xludf.DUMMYFUNCTION("""COMPUTED_VALUE"""),"FIP Engineering") -> FIP Engineering | O25: =IFERROR(__xludf.DUMMYFUNCTION("""COMPUTED_VALUE"""),"FIP-DOM-000-11304-OS00001-INA-000000") -> FIP-DOM-000-11304-OS00001-INA-000000 | P25: =IFERROR(__xludf.DUMMYFUNCTION("""COMPUTED_VALUE"""),"PO Closed") -> PO Closed | Q25: =IFERROR(__xludf.DUMMYFUNCTION("""COMPUTED_VALUE"""),"GL1803040") -> GL1803040 | R25: =IFERROR(__xludf.DUMMYFUNCTION("""COMPUTED_VALUE"""),43153.0) -> 43153 | S25: =IFERROR(__xludf.DUMMYFUNCTION("""COMPUTED_VALUE"""),"-") -> - | T25: =IFERROR(__xludf.DUMMYFUNCTION("""COMPUTED_VALUE"""),43279.0) -> 43279
A26: =IFERROR(__xludf.DUMMYFUNCTION("""COMPUTED_VALUE"""),"181750060-3") -> 181750060-3 | B26: =IFERROR(__xludf.DUMMYFUNCTION("""COMPUTED_VALUE"""),"181750060 - Approved") -> 181750060 - Approved | C26: =IFERROR(__xludf.DUMMYFUNCTION("""COMPUTED_VALUE"""),3.0) -> 3 | D26: =IFERROR(__xludf.DUMMYFUNCTION("""COMPUTED_VALUE"""),"O-15917-00") -> O-15917-00 | E26: =IFERROR(__xludf.DUMMYFUNCTION("""COMPUTED_VALUE"""),"Fedegari FVA2/A1 - CENTERING RING DN16 CLAMP; Code : PP100907; ; ;") -> Fedegari FVA2/A1 - CENTERING RING DN16 CLAMP; Code : PP100907; ; ; | F26: =IFERROR(__xludf.DUMMYFUNCTION("""COMPUTED_VALUE"""),5.0) -> 5 | G26: =IFERROR(__xludf.DUMMYFUNCTION("""COMPUTED_VALUE"""),"Unit") -> Unit | H26: =IFERROR(__xludf.DUMMYFUNCTION("""COMPUTED_VALUE"""),"EUR") -> EUR | I26: =IFERROR(__xludf.DUMMYFUNCTION("""COMPUTED_VALUE"""),6.58) -> 6.58 | J26: =IFERROR(__xludf.DUMMYFUNCTION("""COMPUTED_VALUE"""),32.9) -> 32.9 | K26: =IFERROR(__xludf.DUMMYFUNCTION("""COMPUTED_VALUE"""),43221.0) -> 43221 | L26: =IFERROR(__xludf.DUMMYFUNCTION("""COMPUTED_VALUE"""),"FIP Engineering") -> FIP Engineering | M26: =IFERROR(__xludf.DUMMYFUNCTION("""COMPUTED_VALUE"""),"Joko Nugroho") -> Joko Nugroho | N26: =IFERROR(__xludf.DUMMYFUNCTION("""COMPUTED_VALUE"""),"FIP Engineering") -> FIP Engineering | O26: =IFERROR(__xludf.DUMMYFUNCTION("""COMPUTED_VALUE"""),"FIP-DOM-000-11304-OS00001-INA-000000") -> FIP-DOM-000-11304-OS00001-INA-000000 | P26: =IFERROR(__xludf.DUMMYFUNCTION("""COMPUTED_VALUE"""),"PO Closed") -> PO Closed | Q26: =IFERROR(__xludf.DUMMYFUNCTION("""COMPUTED_VALUE"""),"GL1803040") -> GL1803040 | R26: =IFERROR(__xludf.DUMMYFUNCTION("""COMPUTED_VALUE"""),43153.0) -> 43153 | S26: =IFERROR(__xludf.DUMMYFUNCTION("""COMPUTED_VALUE"""),"-") -> - | T26: =IFERROR(__xludf.DUMMYFUNCTION("""COMPUTED_VALUE"""),43279.0) -> 43279
A27: =IFERROR(__xludf.DUMMYFUNCTION("""COMPUTED_VALUE"""),"181750060-4") -> 181750060-4 | B27: =IFERROR(__xludf.DUMMYFUNCTION("""COMPUTED_VALUE"""),"181750060 - Approved") -> 181750060 - Approved | C27: =IFERROR(__xludf.DUMMYFUNCTION("""COMPUTED_VALUE"""),4.0) -> 4 | D27: =IFERROR(__xludf.DUMMYFUNCTION("""COMPUTED_VALUE"""),"O-15916-00") -> O-15916-00 | E27: =IFERROR(__xludf.DUMMYFUNCTION("""COMPUTED_VALUE"""),"Fedegari FVA2/A1 - CLAMP DN10 1/2"" (MICROCASTED); Code : GM100017; ; ;") -> Fedegari FVA2/A1 - CLAMP DN10 1/2" (MICROCASTED); Code : GM100017; ; ; | F27: =IFERROR(__xludf.DUMMYFUNCTION("""COMPUTED_VALUE"""),2.0) -> 2 | G27: =IFERROR(__xludf.DUMMYFUNCTION("""COMPUTED_VALUE"""),"Unit") -> Unit | H27: =IFERROR(__xludf.DUMMYFUNCTION("""COMPUTED_VALUE"""),"EUR") -> EUR | I27: =IFERROR(__xludf.DUMMYFUNCTION("""COMPUTED_VALUE"""),37.28) -> 37.28 | J27: =IFERROR(__xludf.DUMMYFUNCTION("""COMPUTED_VALUE"""),74.56) -> 74.56 | K27: =IFERROR(__xludf.DUMMYFUNCTION("""COMPUTED_VALUE"""),43221.0) -> 43221 | L27: =IFERROR(__xludf.DUMMYFUNCTION("""COMPUTED_VALUE"""),"FIP Engineering") -> FIP Engineering | M27: =IFERROR(__xludf.DUMMYFUNCTION("""COMPUTED_VALUE"""),"Joko Nugroho") -> Joko Nugroho | N27: =IFERROR(__xludf.DUMMYFUNCTION("""COMPUTED_VALUE"""),"FIP Engineering") -> FIP Engineering | O27: =IFERROR(__xludf.DUMMYFUNCTION("""COMPUTED_VALUE"""),"FIP-DOM-000-11304-OS00001-INA-000000") -> FIP-DOM-000-11304-OS00001-INA-000000 | P27: =IFERROR(__xludf.DUMMYFUNCTION("""COMPUTED_VALUE"""),"PO Closed") -> PO Closed | Q27: =IFERROR(__xludf.DUMMYFUNCTION("""COMPUTED_VALUE"""),"GL1803040") -> GL1803040 | R27: =IFERROR(__xludf.DUMMYFUNCTION("""COMPUTED_VALUE"""),43153.0) -> 43153 | S27: =IFERROR(__xludf.DUMMYFUNCTION("""COMPUTED_VALUE"""),"-") -> - | T27: =IFERROR(__xludf.DUMMYFUNCTION("""COMPUTED_VALUE"""),43279.0) -> 43279
A28: =IFERROR(__xludf.DUMMYFUNCTION("""COMPUTED_VALUE"""),"181750060-5") -> 181750060-5 | B28: =IFERROR(__xludf.DUMMYFUNCTION("""COMPUTED_VALUE"""),"181750060 - Approved") -> 181750060 - Approved | C28: =IFERROR(__xludf.DUMMYFUNCTION("""COMPUTED_VALUE"""),5.0) -> 5 | D28: =IFERROR(__xludf.DUMMYFUNCTION("""COMPUTED_VALUE"""),"O-15915-00") -> O-15915-00 | E28: =IFERROR(__xludf.DUMMYFUNCTION("""COMPUTED_VALUE"""),"Fedegari FVA2/A1 - DN16 ASTM CAP; Code : PM102747; ; ;") -> Fedegari FVA2/A1 - DN16 ASTM CAP; Code : PM102747; ; ; | F28: =IFERROR(__xludf.DUMMYFUNCTION("""COMPUTED_VALUE"""),1.0) -> 1 | G28: =IFERROR(__xludf.DUMMYFUNCTION("""COMPUTED_VALUE"""),"Unit") -> Unit | H28: =IFERROR(__xludf.DUMMYFUNCTION("""COMPUTED_VALUE"""),"EUR") -> EUR | I28: =IFERROR(__xludf.DUMMYFUNCTION("""COMPUTED_VALUE"""),31.43) -> 31.43 | J28: =IFERROR(__xludf.DUMMYFUNCTION("""COMPUTED_VALUE"""),31.43) -> 31.43 | K28: =IFERROR(__xludf.DUMMYFUNCTION("""COMPUTED_VALUE"""),43221.0) -> 43221 | L28: =IFERROR(__xludf.DUMMYFUNCTION("""COMPUTED_VALUE"""),"FIP Engineering") -> FIP Engineering | M28: =IFERROR(__xludf.DUMMYFUNCTION("""COMPUTED_VALUE"""),"Joko Nugroho") -> Joko Nugroho | N28: =IFERROR(__xludf.DUMMYFUNCTION("""COMPUTED_VALUE"""),"FIP Engineering") -> FIP Engineering | O28: =IFERROR(__xludf.DUMMYFUNCTION("""COMPUTED_VALUE"""),"FIP-DOM-000-11304-OS00001-INA-000000") -> FIP-DOM-000-11304-OS00001-INA-000000 | P28: =IFERROR(__xludf.DUMMYFUNCTION("""COMPUTED_VALUE"""),"PO Closed") -> PO Closed | Q28: =IFERROR(__xludf.DUMMYFUNCTION("""COMPUTED_VALUE"""),"GL1803040") -> GL1803040 | R28: =IFERROR(__xludf.DUMMYFUNCTION("""COMPUTED_VALUE"""),43153.0) -> 43153 | S28: =IFERROR(__xludf.DUMMYFUNCTION("""COMPUTED_VALUE"""),"-") -> - | T28: =IFERROR(__xludf.DUMMYFUNCTION("""COMPUTED_VALUE"""),43279.0) -> 43279
A29: =IFERROR(__xludf.DUMMYFUNCTION("""COMPUTED_VALUE"""),"181750060-6") -> 181750060-6 | B29: =IFERROR(__xludf.DUMMYFUNCTION("""COMPUTED_VALUE"""),"181750060 - Approved") -> 181750060 - Approved | C29: =IFERROR(__xludf.DUMMYFUNCTION("""COMPUTED_VALUE"""),6.0) -> 6 | D29: =IFERROR(__xludf.DUMMYFUNCTION("""COMPUTED_VALUE"""),"O-15914-00") -> O-15914-00 | E29: =IFERROR(__xludf.DUMMYFUNCTION("""COMPUTED_VALUE"""),"Fedegari FVA2/A1 - O-RING 34.52x3.53; Code : CC150171; ; ;") -> Fedegari FVA2/A1 - O-RING 34.52x3.53; Code : CC150171; ; ; | F29: =IFERROR(__xludf.DUMMYFUNCTION("""COMPUTED_VALUE"""),5.0) -> 5 | G29: =IFERROR(__xludf.DUMMYFUNCTION("""COMPUTED_VALUE"""),"Unit") -> Unit | H29: =IFERROR(__xludf.DUMMYFUNCTION("""COMPUTED_VALUE"""),"EUR") -> EUR | I29: =IFERROR(__xludf.DUMMYFUNCTION("""COMPUTED_VALUE"""),2.92) -> 2.92 | J29: =IFERROR(__xludf.DUMMYFUNCTION("""COMPUTED_VALUE"""),14.6) -> 14.6 | K29: =IFERROR(__xludf.DUMMYFUNCTION("""COMPUTED_VALUE"""),43221.0) -> 43221 | L29: =IFERROR(__xludf.DUMMYFUNCTION("""COMPUTED_VALUE"""),"FIP Engineering") -> FIP Engineering | M29: =IFERROR(__xludf.DUMMYFUNCTION("""COMPUTED_VALUE"""),"Joko Nugroho") -> Joko Nugroho | N29: =IFERROR(__xludf.DUMMYFUNCTION("""COMPUTED_VALUE"""),"FIP Engineering") -> FIP Engineering | O29: =IFERROR(__xludf.DUMMYFUNCTION("""COMPUTED_VALUE"""),"FIP-DOM-000-11304-OS00001-INA-000000") -> FIP-DOM-000-11304-OS00001-INA-000000 | P29: =IFERROR(__xludf.DUMMYFUNCTION("""COMPUTED_VALUE"""),"PO Closed") -> PO Closed | Q29: =IFERROR(__xludf.DUMMYFUNCTION("""COMPUTED_VALUE"""),"GL1803040") -> GL1803040 | R29: =IFERROR(__xludf.DUMMYFUNCTION("""COMPUTED_VALUE"""),43153.0) -> 43153 | S29: =IFERROR(__xludf.DUMMYFUNCTION("""COMPUTED_VALUE"""),"-") -> - | T29: =IFERROR(__xludf.DUMMYFUNCTION("""COMPUTED_VALUE"""),43279.0) -> 43279
A30: =IFERROR(__xludf.DUMMYFUNCTION("""COMPUTED_VALUE"""),"181750060-7") -> 181750060-7 | B30: =IFERROR(__xludf.DUMMYFUNCTION("""COMPUTED_VALUE"""),"181750060 - Approved") -> 181750060 - Approved | C30: =IFERROR(__xludf.DUMMYFUNCTION("""COMPUTED_VALUE"""),7.0) -> 7 | D30: =IFERROR(__xludf.DUMMYFUNCTION("""COMPUTED_VALUE"""),"O-15913-00") -> O-15913-00 | E30: =IFERROR(__xludf.DUMMYFUNCTION("""COMPUTED_VALUE"""),"Fedegari FVA2/A1 - CENTERING RING DN35 CLAMP; Code : PP100897; ; ;") -> Fedegari FVA2/A1 - CENTERING RING DN35 CLAMP; Code : PP100897; ; ; | F30: =IFERROR(__xludf.DUMMYFUNCTION("""COMPUTED_VALUE"""),5.0) -> 5 | G30: =IFERROR(__xludf.DUMMYFUNCTION("""COMPUTED_VALUE"""),"Unit") -> Unit | H30: =IFERROR(__xludf.DUMMYFUNCTION("""COMPUTED_VALUE"""),"EUR") -> EUR | I30: =IFERROR(__xludf.DUMMYFUNCTION("""COMPUTED_VALUE"""),9.5) -> 9.5 | J30: =IFERROR(__xludf.DUMMYFUNCTION("""COMPUTED_VALUE"""),47.5) -> 47.5 | K30: =IFERROR(__xludf.DUMMYFUNCTION("""COMPUTED_VALUE"""),43221.0) -> 43221 | L30: =IFERROR(__xludf.DUMMYFUNCTION("""COMPUTED_VALUE"""),"FIP Engineering") -> FIP Engineering | M30: =IFERROR(__xludf.DUMMYFUNCTION("""COMPUTED_VALUE"""),"Joko Nugroho") -> Joko Nugroho | N30: =IFERROR(__xludf.DUMMYFUNCTION("""COMPUTED_VALUE"""),"FIP Engineering") -> FIP Engineering | O30: =IFERROR(__xludf.DUMMYFUNCTION("""COMPUTED_VALUE"""),"FIP-DOM-000-11304-OS00001-INA-000000") -> FIP-DOM-000-11304-OS00001-INA-000000 | P30: =IFERROR(__xludf.DUMMYFUNCTION("""COMPUTED_VALUE"""),"PO Closed") -> PO Closed | Q30: =IFERROR(__xludf.DUMMYFUNCTION("""COMPUTED_VALUE"""),"GL1803040") -> GL1803040 | R30: =IFERROR(__xludf.DUMMYFUNCTION("""COMPUTED_VALUE"""),43153.0) -> 43153 | S30: =IFERROR(__xludf.DUMMYFUNCTION("""COMPUTED_VALUE"""),"-") -> - | T30: =IFERROR(__xludf.DUMMYFUNCTION("""COMPUTED_VALUE"""),43279.0) -> 43279
A31: =IFERROR(__xludf.DUMMYFUNCTION("""COMPUTED_VALUE"""),"181750060-8") -> 181750060-8 | B31: =IFERROR(__xludf.DUMMYFUNCTION("""COMPUTED_VALUE"""),"181750060 - Approved") -> 181750060 - Approved | C31: =IFERROR(__xludf.DUMMYFUNCTION("""COMPUTED_VALUE"""),8.0) -> 8 | D31: =IFERROR(__xludf.DUMMYFUNCTION("""COMPUTED_VALUE"""),"O-15912-00") -> O-15912-00 | E31: =IFERROR(__xludf.DUMMYFUNCTION("""COMPUTED_VALUE"""),"Fedegari FVA2/A1 - CLAMP DN34-DN35 (MICROCASTED); Code : GM100094; ; ;") -> Fedegari FVA2/A1 - CLAMP DN34-DN35 (MICROCASTED); Code : GM100094; ; ; | F31: =IFERROR(__xludf.DUMMYFUNCTION("""COMPUTED_VALUE"""),2.0) -> 2 | G31: =IFERROR(__xludf.DUMMYFUNCTION("""COMPUTED_VALUE"""),"Unit") -> Unit | H31: =IFERROR(__xludf.DUMMYFUNCTION("""COMPUTED_VALUE"""),"EUR") -> EUR | I31: =IFERROR(__xludf.DUMMYFUNCTION("""COMPUTED_VALUE"""),52.63) -> 52.63 | J31: =IFERROR(__xludf.DUMMYFUNCTION("""COMPUTED_VALUE"""),105.26) -> 105.26 | K31: =IFERROR(__xludf.DUMMYFUNCTION("""COMPUTED_VALUE"""),43221.0) -> 43221 | L31: =IFERROR(__xludf.DUMMYFUNCTION("""COMPUTED_VALUE"""),"FIP Engineering") -> FIP Engineering | M31: =IFERROR(__xludf.DUMMYFUNCTION("""COMPUTED_VALUE"""),"Joko Nugroho") -> Joko Nugroho | N31: =IFERROR(__xludf.DUMMYFUNCTION("""COMPUTED_VALUE"""),"FIP Engineering") -> FIP Engineering | O31: =IFERROR(__xludf.DUMMYFUNCTION("""COMPUTED_VALUE"""),"FIP-DOM-000-11304-OS00001-INA-000000") -> FIP-DOM-000-11304-OS00001-INA-000000 | P31: =IFERROR(__xludf.DUMMYFUNCTION("""COMPUTED_VALUE"""),"PO Closed") -> PO Closed | Q31: =IFERROR(__xludf.DUMMYFUNCTION("""COMPUTED_VALUE"""),"GL1803040") -> GL1803040 | R31: =IFERROR(__xludf.DUMMYFUNCTION("""COMPUTED_VALUE"""),43153.0) -> 43153 | S31: =IFERROR(__xludf.DUMMYFUNCTION("""COMPUTED_VALUE"""),"-") -> - | T31: =IFERROR(__xludf.DUMMYFUNCTION("""COMPUTED_VALUE"""),43279.0) -> 43279
A32: =IFERROR(__xludf.DUMMYFUNCTION("""COMPUTED_VALUE"""),"181750060-9") -> 181750060-9 | B32: =IFERROR(__xludf.DUMMYFUNCTION("""COMPUTED_VALUE"""),"181750060 - Approved") -> 181750060 - Approved | C32: =IFERROR(__xludf.DUMMYFUNCTION("""COMPUTED_VALUE"""),9.0) -> 9 | D32: =IFERROR(__xludf.DUMMYFUNCTION("""COMPUTED_VALUE"""),"O-15911-00") -> O-15911-00 | E32: =IFERROR(__xludf.DUMMYFUNCTION("""COMPUTED_VALUE"""),"Fedegari FVA2/A1 - TAPPO DN35 ASTM; Code : PM102749; ; ;") -> Fedegari FVA2/A1 - TAPPO DN35 ASTM; Code : PM102749; ; ; | F32: =IFERROR(__xludf.DUMMYFUNCTION("""COMPUTED_VALUE"""),1.0) -> 1 | G32: =IFERROR(__xludf.DUMMYFUNCTION("""COMPUTED_VALUE"""),"Unit") -> Unit | H32: =IFERROR(__xludf.DUMMYFUNCTION("""COMPUTED_VALUE"""),"EUR") -> EUR | I32: =IFERROR(__xludf.DUMMYFUNCTION("""COMPUTED_VALUE"""),43.13) -> 43.13 | J32: =IFERROR(__xludf.DUMMYFUNCTION("""COMPUTED_VALUE"""),43.13) -> 43.13 | K32: =IFERROR(__xludf.DUMMYFUNCTION("""COMPUTED_VALUE"""),43221.0) -> 43221 | L32: =IFERROR(__xludf.DUMMYFUNCTION("""COMPUTED_VALUE"""),"FIP Engineering") -> FIP Engineering | M32: =IFERROR(__xludf.DUMMYFUNCTION("""COMPUTED_VALUE"""),"Joko Nugroho") -> Joko Nugroho | N32: =IFERROR(__xludf.DUMMYFUNCTION("""COMPUTED_VALUE"""),"FIP Engineering") -> FIP Engineering | O32: =IFERROR(__xludf.DUMMYFUNCTION("""COMPUTED_VALUE"""),"FIP-DOM-000-11304-OS00001-INA-000000") -> FIP-DOM-000-11304-OS00001-INA-000000 | P32: =IFERROR(__xludf.DUMMYFUNCTION("""COMPUTED_VALUE"""),"PO Closed") -> PO Closed | Q32: =IFERROR(__xludf.DUMMYFUNCTION("""COMPUTED_VALUE"""),"GL1803040") -> GL1803040 | R32: =IFERROR(__xludf.DUMMYFUNCTION("""COMPUTED_VALUE"""),43153.0) -> 43153 | S32: =IFERROR(__xludf.DUMMYFUNCTION("""COMPUTED_VALUE"""),"-") -> - | T32: =IFERROR(__xludf.DUMMYFUNCTION("""COMPUTED_VALUE"""),43279.0) -> 43279
A33: =IFERROR(__xludf.DUMMYFUNCTION("""COMPUTED_VALUE"""),"181750059-3") -> 181750059-3 | B33: =IFERROR(__xludf.DUMMYFUNCTION("""COMPUTED_VALUE"""),"181750059 - Approved") -> 181750059 - Approved | C33: =IFERROR(__xludf.DUMMYFUNCTION("""COMPUTED_VALUE"""),3.0) -> 3 | D33: =IFERROR(__xludf.DUMMYFUNCTION("""COMPUTED_VALUE"""),"O-15920-00") -> O-15920-00 | E33: =IFERROR(__xludf.DUMMYFUNCTION("""COMPUTED_VALUE"""),"Digital Event I/O module PUM-E, model PUM ERYY1-0B072; ; ;") -> Digital Event I/O module PUM-E, model PUM ERYY1-0B072; ; ; | F33: =IFERROR(__xludf.DUMMYFUNCTION("""COMPUTED_VALUE"""),1.0) -> 1 | G33: =IFERROR(__xludf.DUMMYFUNCTION("""COMPUTED_VALUE"""),"Unit") -> Unit | H33: =IFERROR(__xludf.DUMMYFUNCTION("""COMPUTED_VALUE"""),"USD") -> USD | I33: =IFERROR(__xludf.DUMMYFUNCTION("""COMPUTED_VALUE"""),751.0) -> 751 | J33: =IFERROR(__xludf.DUMMYFUNCTION("""COMPUTED_VALUE"""),751.0) -> 751 | K33: =IFERROR(__xludf.DUMMYFUNCTION("""COMPUTED_VALUE"""),43192.0) -> 43192 | L33: =IFERROR(__xludf.DUMMYFUNCTION("""COMPUTED_VALUE"""),"FIP Engineering") -> FIP Engineering | M33: =IFERROR(__xludf.DUMMYFUNCTION("""COMPUTED_VALUE"""),"Joko Nugroho") -> Joko Nugroho | N33: =IFERROR(__xludf.DUMMYFUNCTION("""COMPUTED_VALUE"""),"FIP Engineering") -> FIP Engineering | O33: =IFERROR(__xludf.DUMMYFUNCTION("""COMPUTED_VALUE"""),"FIP-DOM-000-11304-OS00001-INA-000000") -> FIP-DOM-000-11304-OS00001-INA-000000 | P33: =IFERROR(__xludf.DUMMYFUNCTION("""COMPUTED_VALUE"""),"PO Closed") -> PO Closed | Q33: =IFERROR(__xludf.DUMMYFUNCTION("""COMPUTED_VALUE"""),"GL1803028") -> GL1803028 | R33: =IFERROR(__xludf.DUMMYFUNCTION("""COMPUTED_VALUE"""),43153.0) -> 43153 | S33: =IFERROR(__xludf.DUMMYFUNCTION("""COMPUTED_VALUE"""),"-") -> - | T33: =IFERROR(__xludf.DUMMYFUNCTION("""COMPUTED_VALUE"""),43231.0) -> 43231
A34: =IFERROR(__xludf.DUMMYFUNCTION("""COMPUTED_VALUE"""),"181750059-4") -> 181750059-4 | B34: =IFERROR(__xludf.DUMMYFUNCTION("""COMPUTED_VALUE"""),"181750059 - Approved") -> 181750059 - Approved | C34: =IFERROR(__xludf.DUMMYFUNCTION("""COMPUTED_VALUE"""),4.0) -> 4 | D34: =IFERROR(__xludf.DUMMYFUNCTION("""COMPUTED_VALUE"""),"O-15919-00") -> O-15919-00 | E34: =IFERROR(__xludf.DUMMYFUNCTION("""COMPUTED_VALUE"""),"Temperature control Module PUM-A, MODEL PUMATCC1-0BY71; ; ;") -> Temperature control Module PUM-A, MODEL PUMATCC1-0BY71; ; ; | F34: =IFERROR(__xludf.DUMMYFUNCTION("""COMPUTED_VALUE"""),2.0) -> 2 | G34: =IFERROR(__xludf.DUMMYFUNCTION("""COMPUTED_VALUE"""),"Unit") -> Unit | H34: =IFERROR(__xludf.DUMMYFUNCTION("""COMPUTED_VALUE"""),"USD") -> USD | I34: =IFERROR(__xludf.DUMMYFUNCTION("""COMPUTED_VALUE"""),751.0) -> 751 | J34: =IFERROR(__xludf.DUMMYFUNCTION("""COMPUTED_VALUE"""),1502.0) -> 1502 | K34: =IFERROR(__xludf.DUMMYFUNCTION("""COMPUTED_VALUE"""),43192.0) -> 43192 | L34: =IFERROR(__xludf.DUMMYFUNCTION("""COMPUTED_VALUE"""),"FIP Engineering") -> FIP Engineering | M34: =IFERROR(__xludf.DUMMYFUNCTION("""COMPUTED_VALUE"""),"Joko Nugroho") -> Joko Nugroho | N34: =IFERROR(__xludf.DUMMYFUNCTION("""COMPUTED_VALUE"""),"FIP Engineering") -> FIP Engineering | O34: =IFERROR(__xludf.DUMMYFUNCTION("""COMPUTED_VALUE"""),"FIP-DOM-000-11304-OS00001-INA-000000") -> FIP-DOM-000-11304-OS00001-INA-000000 | P34: =IFERROR(__xludf.DUMMYFUNCTION("""COMPUTED_VALUE"""),"PO Closed") -> PO Closed | Q34: =IFERROR(__xludf.DUMMYFUNCTION("""COMPUTED_VALUE"""),"GL1803028") -> GL1803028 | R34: =IFERROR(__xludf.DUMMYFUNCTION("""COMPUTED_VALUE"""),43153.0) -> 43153 | S34: =IFERROR(__xludf.DUMMYFUNCTION("""COMPUTED_VALUE"""),"-") -> - | T34: =IFERROR(__xludf.DUMMYFUNCTION("""COMPUTED_VALUE"""),43231.0) -> 43231
A35: =IFERROR(__xludf.DUMMYFUNCTION("""COMPUTED_VALUE"""),"181750058-6") -> 181750058-6 | B35: =IFERROR(__xludf.DUMMYFUNCTION("""COMPUTED_VALUE"""),"181750058 - Approved") -> 181750058 - Approved | C35: =IFERROR(__xludf.DUMMYFUNCTION("""COMPUTED_VALUE"""),6.0) -> 6 | D35: =IFERROR(__xludf.DUMMYFUNCTION("""COMPUTED_VALUE"""),"P-15943-00") -> P-15943-00 | E35: =IFERROR(__xludf.DUMMYFUNCTION("""COMPUTED_VALUE"""),"Blind Ferrule SUS304 1/2""; ; ;") -> Blind Ferrule SUS304 1/2"; ; ; | F35: =IFERROR(__xludf.DUMMYFUNCTION("""COMPUTED_VALUE"""),8.0) -> 8 | G35: =IFERROR(__xludf.DUMMYFUNCTION("""COMPUTED_VALUE"""),"Pieces") -> Pieces | H35: =IFERROR(__xludf.DUMMYFUNCTION("""COMPUTED_VALUE"""),"IDR") -> IDR | I35: =IFERROR(__xludf.DUMMYFUNCTION("""COMPUTED_VALUE"""),150000.0) -> 150000 | J35: =IFERROR(__xludf.DUMMYFUNCTION("""COMPUTED_VALUE"""),1200000.0) -> 1200000 | K35: =IFERROR(__xludf.DUMMYFUNCTION("""COMPUTED_VALUE"""),43171.0) -> 43171 | L35: =IFERROR(__xludf.DUMMYFUNCTION("""COMPUTED_VALUE"""),"FIP General") -> FIP General | M35: =IFERROR(__xludf.DUMMYFUNCTION("""COMPUTED_VALUE"""),"Joko Nugroho") -> Joko Nugroho | N35: =IFERROR(__xludf.DUMMYFUNCTION("""COMPUTED_VALUE"""),"FIP Engineering") -> FIP Engineering | O35: =IFERROR(__xludf.DUMMYFUNCTION("""COMPUTED_VALUE"""),"FIP-DOM-ENG-51404-0000000-INA-000000") -> FIP-DOM-ENG-51404-0000000-INA-000000 | P35: =IFERROR(__xludf.DUMMYFUNCTION("""COMPUTED_VALUE"""),"PO Closed") -> PO Closed | Q35: =IFERROR(__xludf.DUMMYFUNCTION("""COMPUTED_VALUE"""),"GL1803027") -> GL1803027 | R35: =IFERROR(__xludf.DUMMYFUNCTION("""COMPUTED_VALUE"""),43153.0) -> 43153 | S35: =IFERROR(__xludf.DUMMYFUNCTION("""COMPUTED_VALUE"""),"-") -> - | T35: =IFERROR(__xludf.DUMMYFUNCTION("""COMPUTED_VALUE"""),43174.0) -> 43174
A36: =IFERROR(__xludf.DUMMYFUNCTION("""COMPUTED_VALUE"""),"181750058-6") -> 181750058-6 | B36: =IFERROR(__xludf.DUMMYFUNCTION("""COMPUTED_VALUE"""),"181750058 - Approved") -> 181750058 - Approved | C36: =IFERROR(__xludf.DUMMYFUNCTION("""COMPUTED_VALUE"""),6.0) -> 6 | D36: =IFERROR(__xludf.DUMMYFUNCTION("""COMPUTED_VALUE"""),"P-15944-00") -> P-15944-00 | E36: =IFERROR(__xludf.DUMMYFUNCTION("""COMPUTED_VALUE"""),"Sealing belt (nillon) 1.5 cm x 77cm; ; ;") -> Sealing belt (nillon) 1.5 cm x 77cm; ; ; | F36: =IFERROR(__xludf.DUMMYFUNCTION("""COMPUTED_VALUE"""),3.0) -> 3 | G36: =IFERROR(__xludf.DUMMYFUNCTION("""COMPUTED_VALUE"""),"Pieces") -> Pieces | H36: =IFERROR(__xludf.DUMMYFUNCTION("""COMPUTED_VALUE"""),"IDR") -> IDR | I36: =IFERROR(__xludf.DUMMYFUNCTION("""COMPUTED_VALUE"""),30000.0) -> 30000 | J36: =IFERROR(__xludf.DUMMYFUNCTION("""COMPUTED_VALUE"""),90000.0) -> 90000 | K36: =IFERROR(__xludf.DUMMYFUNCTION("""COMPUTED_VALUE"""),43171.0) -> 43171 | L36: =IFERROR(__xludf.DUMMYFUNCTION("""COMPUTED_VALUE"""),"FIP General") -> FIP General | M36: =IFERROR(__xludf.DUMMYFUNCTION("""COMPUTED_VALUE"""),"Joko Nugroho") -> Joko Nugroho | N36: =IFERROR(__xludf.DUMMYFUNCTION("""COMPUTED_VALUE"""),"FIP Engineering") -> FIP Engineering | O36: =IFERROR(__xludf.DUMMYFUNCTION("""COMPUTED_VALUE"""),"FIP-DOM-ENG-51404-0000000-INA-000000") -> FIP-DOM-ENG-51404-0000000-INA-000000 | P36: =IFERROR(__xludf.DUMMYFUNCTION("""COMPUTED_VALUE"""),"PO Closed") -> PO Closed | Q36: =IFERROR(__xludf.DUMMYFUNCTION("""COMPUTED_VALUE"""),"GL1803023") -> GL1803023 | R36: =IFERROR(__xludf.DUMMYFUNCTION("""COMPUTED_VALUE"""),43153.0) -> 43153 | S36: =IFERROR(__xludf.DUMMYFUNCTION("""COMPUTED_VALUE"""),"-") -> - | T36: =IFERROR(__xludf.DUMMYFUNCTION("""COMPUTED_VALUE"""),43192.0) -> 43192
A37: =IFERROR(__xludf.DUMMYFUNCTION("""COMPUTED_VALUE"""),"181750058-6") -> 181750058-6 | B37: =IFERROR(__xludf.DUMMYFUNCTION("""COMPUTED_VALUE"""),"181750058 - Approved") -> 181750058 - Approved | C37: =IFERROR(__xludf.DUMMYFUNCTION("""COMPUTED_VALUE"""),6.0) -> 6 | D37: =IFERROR(__xludf.DUMMYFUNCTION("""COMPUTED_VALUE"""),"P-15942-00") -> P-15942-00 | E37: =IFERROR(__xludf.DUMMYFUNCTION("""COMPUTED_VALUE"""),"Blind Ferrule SUS304 1.0""; ; ;") -> Blind Ferrule SUS304 1.0"; ; ; | F37: =IFERROR(__xludf.DUMMYFUNCTION("""COMPUTED_VALUE"""),4.0) -> 4 | G37: =IFERROR(__xludf.DUMMYFUNCTION("""COMPUTED_VALUE"""),"Pieces") -> Pieces | H37: =IFERROR(__xludf.DUMMYFUNCTION("""COMPUTED_VALUE"""),"IDR") -> IDR | I37: =IFERROR(__xludf.DUMMYFUNCTION("""COMPUTED_VALUE"""),225000.0) -> 225000 | J37: =IFERROR(__xludf.DUMMYFUNCTION("""COMPUTED_VALUE"""),900000.0) -> 900000 | K37: =IFERROR(__xludf.DUMMYFUNCTION("""COMPUTED_VALUE"""),43171.0) -> 43171 | L37: =IFERROR(__xludf.DUMMYFUNCTION("""COMPUTED_VALUE"""),"FIP General") -> FIP General | M37: =IFERROR(__xludf.DUMMYFUNCTION("""COMPUTED_VALUE"""),"Joko Nugroho") -> Joko Nugroho | N37: =IFERROR(__xludf.DUMMYFUNCTION("""COMPUTED_VALUE"""),"FIP Engineering") -> FIP Engineering | O37: =IFERROR(__xludf.DUMMYFUNCTION("""COMPUTED_VALUE"""),"FIP-DOM-ENG-51404-0000000-INA-000000") -> FIP-DOM-ENG-51404-0000000-INA-000000 | P37: =IFERROR(__xludf.DUMMYFUNCTION("""COMPUTED_VALUE"""),"PO Closed") -> PO Closed | Q37: =IFERROR(__xludf.DUMMYFUNCTION("""COMPUTED_VALUE"""),"GL1803027") -> GL1803027 | R37: =IFERROR(__xludf.DUMMYFUNCTION("""COMPUTED_VALUE"""),43153.0) -> 43153 | S37: =IFERROR(__xludf.DUMMYFUNCTION("""COMPUTED_VALUE"""),"-") -> - | T37: =IFERROR(__xludf.DUMMYFUNCTION("""COMPUTED_VALUE"""),43174.0) -> 43174
A38: =IFERROR(__xludf.DUMMYFUNCTION("""COMPUTED_VALUE"""),"181750058-6") -> 181750058-6 | B38: =IFERROR(__xludf.DUMMYFUNCTION("""COMPUTED_VALUE"""),"181750058 - Approved") -> 181750058 - Approved | C38: =IFERROR(__xludf.DUMMYFUNCTION("""COMPUTED_VALUE"""),6.0) -> 6 | D38: =IFERROR(__xludf.DUMMYFUNCTION("""COMPUTED_VALUE"""),"P-15945-00") -> P-15945-00 | E38: =IFERROR(__xludf.DUMMYFUNCTION("""COMPUTED_VALUE"""),"WEDGE BELT OPTIBELT SPA 2082; ; ;") -> WEDGE BELT OPTIBELT SPA 2082; ; ; | F38: =IFERROR(__xludf.DUMMYFUNCTION("""COMPUTED_VALUE"""),2.0) -> 2 | G38: =IFERROR(__xludf.DUMMYFUNCTION("""COMPUTED_VALUE"""),"Unit") -> Unit | H38: =IFERROR(__xludf.DUMMYFUNCTION("""COMPUTED_VALUE"""),"IDR") -> IDR | I38: =IFERROR(__xludf.DUMMYFUNCTION("""COMPUTED_VALUE"""),106000.0) -> 106000 | J38: =IFERROR(__xludf.DUMMYFUNCTION("""COMPUTED_VALUE"""),212000.0) -> 212000 | K38: =IFERROR(__xludf.DUMMYFUNCTION("""COMPUTED_VALUE"""),43171.0) -> 43171 | L38: =IFERROR(__xludf.DUMMYFUNCTION("""COMPUTED_VALUE"""),"FIP Engineering") -> FIP Engineering | M38: =IFERROR(__xludf.DUMMYFUNCTION("""COMPUTED_VALUE"""),"Joko Nugroho") -> Joko Nugroho | N38: =IFERROR(__xludf.DUMMYFUNCTION("""COMPUTED_VALUE"""),"FIP Engineering") -> FIP Engineering | O38: =IFERROR(__xludf.DUMMYFUNCTION("""COMPUTED_VALUE"""),"FIP-DOM-000-11304-OS00001-INA-000000") -> FIP-DOM-000-11304-OS00001-INA-000000 | P38: =IFERROR(__xludf.DUMMYFUNCTION("""COMPUTED_VALUE"""),"PO Closed") -> PO Closed | Q38: =IFERROR(__xludf.DUMMYFUNCTION("""COMPUTED_VALUE"""),"GL1803024") -> GL1803024 | R38: =IFERROR(__xludf.DUMMYFUNCTION("""COMPUTED_VALUE"""),43153.0) -> 43153 | S38: =IFERROR(__xludf.DUMMYFUNCTION("""COMPUTED_VALUE"""),"-") -> - | T38: =IFERROR(__xludf.DUMMYFUNCTION("""COMPUTED_VALUE"""),43171.0) -> 43171
A39: =IFERROR(__xludf.DUMMYFUNCTION("""COMPUTED_VALUE"""),"181750062-1") -> 181750062-1 | B39: =IFERROR(__xludf.DUMMYFUNCTION("""COMPUTED_VALUE"""),"181750062 - Approved") -> 181750062 - Approved | C39: =IFERROR(__xludf.DUMMYFUNCTION("""COMPUTED_VALUE"""),1.0) -> 1 | D39: =IFERROR(__xludf.DUMMYFUNCTION("""COMPUTED_VALUE"""),"S-20016-00") -> S-20016-00 | E39: =IFERROR(__xludf.DUMMYFUNCTION("""COMPUTED_VALUE"""),"Sarung tangan bahan kain; ; ;") -> Sarung tangan bahan kain; ; ; | F39: =IFERROR(__xludf.DUMMYFUNCTION("""COMPUTED_VALUE"""),2.0) -> 2 | G39: =IFERROR(__xludf.DUMMYFUNCTION("""COMPUTED_VALUE"""),"Pack") -> Pack | H39: =IFERROR(__xludf.DUMMYFUNCTION("""COMPUTED_VALUE"""),"IDR") -> IDR | I39: =IFERROR(__xludf.DUMMYFUNCTION("""COMPUTED_VALUE"""),42000.0) -> 42000 | J39: =IFERROR(__xludf.DUMMYFUNCTION("""COMPUTED_VALUE"""),84000.0) -> 84000 | K39: =IFERROR(__xludf.DUMMYFUNCTION("""COMPUTED_VALUE"""),43171.0) -> 43171 | L39: =IFERROR(__xludf.DUMMYFUNCTION("""COMPUTED_VALUE"""),"FIP General") -> FIP General | M39: =IFERROR(__xludf.DUMMYFUNCTION("""COMPUTED_VALUE"""),"Joko Nugroho") -> Joko Nugroho | N39: =IFERROR(__xludf.DUMMYFUNCTION("""COMPUTED_VALUE"""),"FIP Engineering") -> FIP Engineering | O39: =IFERROR(__xludf.DUMMYFUNCTION("""COMPUTED_VALUE"""),"FIP-DOM-ENG-51202-0000000-INA-000000") -> FIP-DOM-ENG-51202-0000000-INA-000000 | P39: =IFERROR(__xludf.DUMMYFUNCTION("""COMPUTED_VALUE"""),"PO Closed") -> PO Closed | Q39: =IFERROR(__xludf.DUMMYFUNCTION("""COMPUTED_VALUE"""),"GL1803044") -> GL1803044 | R39: =IFERROR(__xludf.DUMMYFUNCTION("""COMPUTED_VALUE"""),43154.0) -> 43154 | S39: =IFERROR(__xludf.DUMMYFUNCTION("""COMPUTED_VALUE"""),"-") -> - | T39: =IFERROR(__xludf.DUMMYFUNCTION("""COMPUTED_VALUE"""),43178.0) -> 43178
A40: =IFERROR(__xludf.DUMMYFUNCTION("""COMPUTED_VALUE"""),"181750059-3") -> 181750059-3 | B40: =IFERROR(__xludf.DUMMYFUNCTION("""COMPUTED_VALUE"""),"181750059 - Approved") -> 181750059 - Approved | C40: =IFERROR(__xludf.DUMMYFUNCTION("""COMPUTED_VALUE"""),3.0) -> 3 | D40: =IFERROR(__xludf.DUMMYFUNCTION("""COMPUTED_VALUE"""),"S-60002-00") -> S-60002-00 | E40: =IFERROR(__xludf.DUMMYFUNCTION("""COMPUTED_VALUE"""),"FREIGHT CHARGES") -> FREIGHT CHARGES | F40: =IFERROR(__xludf.DUMMYFUNCTION("""COMPUTED_VALUE"""),1.0) -> 1 | G40: =IFERROR(__xludf.DUMMYFUNCTION("""COMPUTED_VALUE"""),"Lot") -> Lot | H40: =IFERROR(__xludf.DUMMYFUNCTION("""COMPUTED_VALUE"""),"USD") -> USD | I40: =IFERROR(__xludf.DUMMYFUNCTION("""COMPUTED_VALUE"""),200.0) -> 200 | J40: =IFERROR(__xludf.DUMMYFUNCTION("""COMPUTED_VALUE"""),200.0) -> 200 | K40: =IFERROR(__xludf.DUMMYFUNCTION("""COMPUTED_VALUE"""),43192.0) -> 43192 | L40: =IFERROR(__xludf.DUMMYFUNCTION("""COMPUTED_VALUE"""),"FIP General") -> FIP General | M40: =IFERROR(__xludf.DUMMYFUNCTION("""COMPUTED_VALUE"""),"Joko Nugroho") -> Joko Nugroho | N40: =IFERROR(__xludf.DUMMYFUNCTION("""COMPUTED_VALUE"""),"FIP Engineering") -> FIP Engineering | O40: =IFERROR(__xludf.DUMMYFUNCTION("""COMPUTED_VALUE"""),"FIP-DOM-ENG-51508-0000000-INA-000000") -> FIP-DOM-ENG-51508-0000000-INA-000000 | P40: =IFERROR(__xludf.DUMMYFUNCTION("""COMPUTED_VALUE"""),"PO Closed") -> PO Closed | Q40: =IFERROR(__xludf.DUMMYFUNCTION("""COMPUTED_VALUE"""),"GL1803028") -> GL1803028 | R40: =IFERROR(__xludf.DUMMYFUNCTION("""COMPUTED_VALUE"""),43154.0) -> 43154 | S40: =IFERROR(__xludf.DUMMYFUNCTION("""COMPUTED_VALUE"""),"-") -> - | T40: =IFERROR(__xludf.DUMMYFUNCTION("""COMPUTED_VALUE"""),43231.0) -> 43231
A41: =IFERROR(__xludf.DUMMYFUNCTION("""COMPUTED_VALUE"""),"181750063-1") -> 181750063-1 | B41: =IFERROR(__xludf.DUMMYFUNCTION("""COMPUTED_VALUE"""),"181750063 - Approved") -> 181750063 - Approved | C41: =IFERROR(__xludf.DUMMYFUNCTION("""COMPUTED_VALUE"""),1.0) -> 1 | D41: =IFERROR(__xludf.DUMMYFUNCTION("""COMPUTED_VALUE"""),"S-60002-00") -> S-60002-00 | E41: =IFERROR(__xludf.DUMMYFUNCTION("""COMPUTED_VALUE"""),"Remote Service assistance; 4 hours connection package + SW Engineer preparation") -> Remote Service assistance; 4 hours connection package + SW Engineer preparation | F41: =IFERROR(__xludf.DUMMYFUNCTION("""COMPUTED_VALUE"""),1.0) -> 1 | G41: =IFERROR(__xludf.DUMMYFUNCTION("""COMPUTED_VALUE"""),"Lot") -> Lot | H41: =IFERROR(__xludf.DUMMYFUNCTION("""COMPUTED_VALUE"""),"EUR") -> EUR | I41: =IFERROR(__xludf.DUMMYFUNCTION("""COMPUTED_VALUE"""),1400.0) -> 1400 | J41: =IFERROR(__xludf.DUMMYFUNCTION("""COMPUTED_VALUE"""),1400.0) -> 1400 | K41: =IFERROR(__xludf.DUMMYFUNCTION("""COMPUTED_VALUE"""),43168.0) -> 43168 | L41: =IFERROR(__xludf.DUMMYFUNCTION("""COMPUTED_VALUE"""),"FIP General") -> FIP General | M41: =IFERROR(__xludf.DUMMYFUNCTION("""COMPUTED_VALUE"""),"Iman Dwinanto") -> Iman Dwinanto | N41: =IFERROR(__xludf.DUMMYFUNCTION("""COMPUTED_VALUE"""),"FIP Engineering") -> FIP Engineering | O41: =IFERROR(__xludf.DUMMYFUNCTION("""COMPUTED_VALUE"""),"FIP-DOM-ENG-51508-0000000-INA-000000") -> FIP-DOM-ENG-51508-0000000-INA-000000 | P41: =IFERROR(__xludf.DUMMYFUNCTION("""COMPUTED_VALUE"""),"PO Closed") -> PO Closed | Q41: =IFERROR(__xludf.DUMMYFUNCTION("""COMPUTED_VALUE"""),"GL1802054") -> GL1802054 | R41: =IFERROR(__xludf.DUMMYFUNCTION("""COMPUTED_VALUE"""),43156.0) -> 43156 | S41: =IFERROR(__xludf.DUMMYFUNCTION("""COMPUTED_VALUE"""),"-") -> - | T41: =IFERROR(__xludf.DUMMYFUNCTION("""COMPUTED_VALUE"""),43189.0) -> 43189
A42: =IFERROR(__xludf.DUMMYFUNCTION("""COMPUTED_VALUE"""),"181750064-1") -> 181750064-1 | B42: =IFERROR(__xludf.DUMMYFUNCTION("""COMPUTED_VALUE"""),"181750064 - Approved") -> 181750064 - Approved | C42: =IFERROR(__xludf.DUMMYFUNCTION("""COMPUTED_VALUE"""),1.0) -> 1 | D42: =IFERROR(__xludf.DUMMYFUNCTION("""COMPUTED_VALUE"""),"S-60002-00") -> S-60002-00 | E42: =IFERROR(__xludf.DUMMYFUNCTION("""COMPUTED_VALUE"""),"Parts untuk perbaikan isolator Skan; Pneum Gasket for SKAN P/N : 1015746") -> Parts untuk perbaikan isolator Skan; Pneum Gasket for SKAN P/N : 1015746 | F42: =IFERROR(__xludf.DUMMYFUNCTION("""COMPUTED_VALUE"""),1.0) -> 1 | G42: =IFERROR(__xludf.DUMMYFUNCTION("""COMPUTED_VALUE"""),"Lot") -> Lot | H42: =IFERROR(__xludf.DUMMYFUNCTION("""COMPUTED_VALUE"""),"IDR") -> IDR | I42: =IFERROR(__xludf.DUMMYFUNCTION("""COMPUTED_VALUE"""),2.612E7) -> 26120000 | J42: =IFERROR(__xludf.DUMMYFUNCTION("""COMPUTED_VALUE"""),2.612E7) -> 26120000 | K42: =IFERROR(__xludf.DUMMYFUNCTION("""COMPUTED_VALUE"""),43234.0) -> 43234 | L42: =IFERROR(__xludf.DUMMYFUNCTION("""COMPUTED_VALUE"""),"FIP General") -> FIP General | M42: =IFERROR(__xludf.DUMMYFUNCTION("""COMPUTED_VALUE"""),"Iman Dwinanto") -> Iman Dwinanto | N42: =IFERROR(__xludf.DUMMYFUNCTION("""COMPUTED_VALUE"""),"FIP Engineering") -> FIP Engineering | O42: =IFERROR(__xludf.DUMMYFUNCTION("""COMPUTED_VALUE"""),"FIP-DOM-ENG-51508-0000000-INA-000000") -> FIP-DOM-ENG-51508-0000000-INA-000000 | P42: =IFERROR(__xludf.DUMMYFUNCTION("""COMPUTED_VALUE"""),"PO Closed") -> PO Closed | Q42: =IFERROR(__xludf.DUMMYFUNCTION("""COMPUTED_VALUE"""),"GL1803029") -> GL1803029 | R42: =IFERROR(__xludf.DUMMYFUNCTION("""COMPUTED_VALUE"""),43158.0) -> 43158 | S42: =IFERROR(__xludf.DUMMYFUNCTION("""COMPUTED_VALUE"""),"-") -> - | T42: =IFERROR(__xludf.DUMMYFUNCTION("""COMPUTED_VALUE"""),43210.0) -> 43210
A43: =IFERROR(__xludf.DUMMYFUNCTION("""COMPUTED_VALUE"""),"181750060-12") -> 181750060-12 | B43: =IFERROR(__xludf.DUMMYFUNCTION("""COMPUTED_VALUE"""),"181750060 - Approved") -> 181750060 - Approved | C43: =IFERROR(__xludf.DUMMYFUNCTION("""COMPUTED_VALUE"""),12.0) -> 12 | D43: =IFERROR(__xludf.DUMMYFUNCTION("""COMPUTED_VALUE"""),"P-15429-00") -> P-15429-00 | E43: =IFERROR(__xludf.DUMMYFUNCTION("""COMPUTED_VALUE"""),"Fedegari FVA2/A1 S/N : NB2964AT - Cover Seal FVM-A/2 FOB2 (Code: PP600265); ; ;") -> Fedegari FVA2/A1 S/N : NB2964AT - Cover Seal FVM-A/2 FOB2 (Code: PP600265); ; ; | F43: =IFERROR(__xludf.DUMMYFUNCTION("""COMPUTED_VALUE"""),2.0) -> 2 | G43: =IFERROR(__xludf.DUMMYFUNCTION("""COMPUTED_VALUE"""),"Unit") -> Unit | H43: =IFERROR(__xludf.DUMMYFUNCTION("""COMPUTED_VALUE"""),"EUR") -> EUR | I43: =IFERROR(__xludf.DUMMYFUNCTION("""COMPUTED_VALUE"""),182.02) -> 182.02 | J43: =IFERROR(__xludf.DUMMYFUNCTION("""COMPUTED_VALUE"""),364.04) -> 364.04 | K43: =IFERROR(__xludf.DUMMYFUNCTION("""COMPUTED_VALUE"""),43221.0) -> 43221 | L43: =IFERROR(__xludf.DUMMYFUNCTION("""COMPUTED_VALUE"""),"FIP Engineering") -> FIP Engineering | M43: =IFERROR(__xludf.DUMMYFUNCTION("""COMPUTED_VALUE"""),"Joko Nugroho") -> Joko Nugroho | N43: =IFERROR(__xludf.DUMMYFUNCTION("""COMPUTED_VALUE"""),"FIP Engineering") -> FIP Engineering | O43: =IFERROR(__xludf.DUMMYFUNCTION("""COMPUTED_VALUE"""),"FIP-DOM-000-11304-OS00001-INA-000000") -> FIP-DOM-000-11304-OS00001-INA-000000 | P43: =IFERROR(__xludf.DUMMYFUNCTION("""COMPUTED_VALUE"""),"PO Closed") -> PO Closed | Q43: =IFERROR(__xludf.DUMMYFUNCTION("""COMPUTED_VALUE"""),"GL1803040") -> GL1803040 | R43: =IFERROR(__xludf.DUMMYFUNCTION("""COMPUTED_VALUE"""),43158.0) -> 43158 | S43: =IFERROR(__xludf.DUMMYFUNCTION("""COMPUTED_VALUE"""),"-") -> - | T43: =IFERROR(__xludf.DUMMYFUNCTION("""COMPUTED_VALUE"""),43279.0) -> 43279
A44: =IFERROR(__xludf.DUMMYFUNCTION("""COMPUTED_VALUE"""),"181750062-3") -> 181750062-3 | B44: =IFERROR(__xludf.DUMMYFUNCTION("""COMPUTED_VALUE"""),"181750062 - Approved") -> 181750062 - Approved | C44: =IFERROR(__xludf.DUMMYFUNCTION("""COMPUTED_VALUE"""),3.0) -> 3 | D44: =IFERROR(__xludf.DUMMYFUNCTION("""COMPUTED_VALUE"""),"O-51000-00") -> O-51000-00 | E44: =IFERROR(__xludf.DUMMYFUNCTION("""COMPUTED_VALUE"""),"Colamark - Print Head for Part TTO Domino p/n EPP001359 SP; ; ;") -> Colamark - Print Head for Part TTO Domino p/n EPP001359 SP; ; ; | F44: =IFERROR(__xludf.DUMMYFUNCTION("""COMPUTED_VALUE"""),1.0) -> 1 | G44: =IFERROR(__xludf.DUMMYFUNCTION("""COMPUTED_VALUE"""),"Pieces") -> Pieces | H44: =IFERROR(__xludf.DUMMYFUNCTION("""COMPUTED_VALUE"""),"IDR") -> IDR | I44: =IFERROR(__xludf.DUMMYFUNCTION("""COMPUTED_VALUE"""),1.0824E7) -> 10824000 | J44: =IFERROR(__xludf.DUMMYFUNCTION("""COMPUTED_VALUE"""),1.0824E7) -> 10824000 | K44: =IFERROR(__xludf.DUMMYFUNCTION("""COMPUTED_VALUE"""),43168.0) -> 43168 | L44: =IFERROR(__xludf.DUMMYFUNCTION("""COMPUTED_VALUE"""),"FIP General") -> FIP General | M44: =IFERROR(__xludf.DUMMYFUNCTION("""COMPUTED_VALUE"""),"Joko Nugroho") -> Joko Nugroho | N44: =IFERROR(__xludf.DUMMYFUNCTION("""COMPUTED_VALUE"""),"FIP Engineering") -> FIP Engineering | O44: =IFERROR(__xludf.DUMMYFUNCTION("""COMPUTED_VALUE"""),"FIP-DOM-ENG-51504-0000000-INA-000000") -> FIP-DOM-ENG-51504-0000000-INA-000000 | P44: =IFERROR(__xludf.DUMMYFUNCTION("""COMPUTED_VALUE"""),"PO Closed") -> PO Closed | Q44: =IFERROR(__xludf.DUMMYFUNCTION("""COMPUTED_VALUE"""),"GL1803053") -> GL1803053 | R44: =IFERROR(__xludf.DUMMYFUNCTION("""COMPUTED_VALUE"""),43159.0) -> 43159 | S44: =IFERROR(__xludf.DUMMYFUNCTION("""COMPUTED_VALUE"""),"-") -> - | T44: =IFERROR(__xludf.DUMMYFUNCTION("""COMPUTED_VALUE"""),43195.0) -> 43195
A45: =IFERROR(__xludf.DUMMYFUNCTION("""COMPUTED_VALUE"""),"181750073-1") -> 181750073-1 | B45: =IFERROR(__xludf.DUMMYFUNCTION("""COMPUTED_VALUE"""),"181750073 - Approved") -> 181750073 - Approved | C45: =IFERROR(__xludf.DUMMYFUNCTION("""COMPUTED_VALUE"""),1.0) -> 1 | D45: =IFERROR(__xludf.DUMMYFUNCTION("""COMPUTED_VALUE"""),"O-14621-00") -> O-14621-00 | E45: =IFERROR(__xludf.DUMMYFUNCTION("""COMPUTED_VALUE"""),"Coil U2 11W 24VDC; Univer; c/n 5233;") -> Coil U2 11W 24VDC; Univer; c/n 5233; | F45: =IFERROR(__xludf.DUMMYFUNCTION("""COMPUTED_VALUE"""),2.0) -> 2 | G45: =IFERROR(__xludf.DUMMYFUNCTION("""COMPUTED_VALUE"""),"Unit") -> Unit | H45: =IFERROR(__xludf.DUMMYFUNCTION("""COMPUTED_VALUE"""),"EUR") -> EUR | I45: =IFERROR(__xludf.DUMMYFUNCTION("""COMPUTED_VALUE"""),26.0) -> 26 | J45: =IFERROR(__xludf.DUMMYFUNCTION("""COMPUTED_VALUE"""),52.0) -> 52 | K45: =IFERROR(__xludf.DUMMYFUNCTION("""COMPUTED_VALUE"""),43234.0) -> 43234 | L45: =IFERROR(__xludf.DUMMYFUNCTION("""COMPUTED_VALUE"""),"FIP Engineering") -> FIP Engineering | M45: =IFERROR(__xludf.DUMMYFUNCTION("""COMPUTED_VALUE"""),"Joko Nugroho") -> Joko Nugroho | N45: =IFERROR(__xludf.DUMMYFUNCTION("""COMPUTED_VALUE"""),"FIP Engineering") -> FIP Engineering | O45: =IFERROR(__xludf.DUMMYFUNCTION("""COMPUTED_VALUE"""),"FIP-DOM-000-11304-OS00001-INA-000000") -> FIP-DOM-000-11304-OS00001-INA-000000 | P45: =IFERROR(__xludf.DUMMYFUNCTION("""COMPUTED_VALUE"""),"PO Closed") -> PO Closed | Q45: =IFERROR(__xludf.DUMMYFUNCTION("""COMPUTED_VALUE"""),"GL1804055") -> GL1804055 | R45: =IFERROR(__xludf.DUMMYFUNCTION("""COMPUTED_VALUE"""),43161.0) -> 43161 | S45: =IFERROR(__xludf.DUMMYFUNCTION("""COMPUTED_VALUE"""),"-") -> - | T45: =IFERROR(__xludf.DUMMYFUNCTION("""COMPUTED_VALUE"""),43347.0) -> 43347
A46: =IFERROR(__xludf.DUMMYFUNCTION("""COMPUTED_VALUE"""),"181750073-3") -> 181750073-3 | B46: =IFERROR(__xludf.DUMMYFUNCTION("""COMPUTED_VALUE"""),"181750073 - Approved") -> 181750073 - Approved | C46: =IFERROR(__xludf.DUMMYFUNCTION("""COMPUTED_VALUE"""),3.0) -> 3 | D46: =IFERROR(__xludf.DUMMYFUNCTION("""COMPUTED_VALUE"""),"S-60002-00") -> S-60002-00 | E46: =IFERROR(__xludf.DUMMYFUNCTION("""COMPUTED_VALUE"""),"Instrument Calibration Certificate") -> Instrument Calibration Certificate | F46: =IFERROR(__xludf.DUMMYFUNCTION("""COMPUTED_VALUE"""),6.0) -> 6 | G46: =IFERROR(__xludf.DUMMYFUNCTION("""COMPUTED_VALUE"""),"Lot") -> Lot | H46: =IFERROR(__xludf.DUMMYFUNCTION("""COMPUTED_VALUE"""),"EUR") -> EUR | I46: =IFERROR(__xludf.DUMMYFUNCTION("""COMPUTED_VALUE"""),26.0) -> 26 | J46: =IFERROR(__xludf.DUMMYFUNCTION("""COMPUTED_VALUE"""),156.0) -> 156 | K46: =IFERROR(__xludf.DUMMYFUNCTION("""COMPUTED_VALUE"""),43234.0) -> 43234 | L46: =IFERROR(__xludf.DUMMYFUNCTION("""COMPUTED_VALUE"""),"FIP General") -> FIP General | M46: =IFERROR(__xludf.DUMMYFUNCTION("""COMPUTED_VALUE"""),"Joko Nugroho") -> Joko Nugroho | N46: =IFERROR(__xludf.DUMMYFUNCTION("""COMPUTED_VALUE"""),"FIP Engineering") -> FIP Engineering | O46: =IFERROR(__xludf.DUMMYFUNCTION("""COMPUTED_VALUE"""),"FIP-DOM-ENG-51508-0000000-INA-000000") -> FIP-DOM-ENG-51508-0000000-INA-000000 | P46: =IFERROR(__xludf.DUMMYFUNCTION("""COMPUTED_VALUE"""),"PO Closed") -> PO Closed | Q46: =IFERROR(__xludf.DUMMYFUNCTION("""COMPUTED_VALUE"""),"GL1804055") -> GL1804055 | R46: =IFERROR(__xludf.DUMMYFUNCTION("""COMPUTED_VALUE"""),43161.0) -> 43161 | S46: =IFERROR(__xludf.DUMMYFUNCTION("""COMPUTED_VALUE"""),"-") -> - | T46: =IFERROR(__xludf.DUMMYFUNCTION("""COMPUTED_VALUE"""),43347.0) -> 43347
A47: =IFERROR(__xludf.DUMMYFUNCTION("""COMPUTED_VALUE"""),"181750073-4") -> 181750073-4 | B47: =IFERROR(__xludf.DUMMYFUNCTION("""COMPUTED_VALUE"""),"181750073 - Approved") -> 181750073 - Approved | C47: =IFERROR(__xludf.DUMMYFUNCTION("""COMPUTED_VALUE"""),4.0) -> 4 | D47: =IFERROR(__xludf.DUMMYFUNCTION("""COMPUTED_VALUE"""),"O-14618-00") -> O-14618-00 | E47: =IFERROR(__xludf.DUMMYFUNCTION("""COMPUTED_VALUE"""),"Pneumatic pincher silicone cover sleeve; ; c/n 15927;") -> Pneumatic pincher silicone cover sleeve; ; c/n 15927; | F47: =IFERROR(__xludf.DUMMYFUNCTION("""COMPUTED_VALUE"""),10.0) -> 10 | G47: =IFERROR(__xludf.DUMMYFUNCTION("""COMPUTED_VALUE"""),"Unit") -> Unit | H47: =IFERROR(__xludf.DUMMYFUNCTION("""COMPUTED_VALUE"""),"EUR") -> EUR | I47: =IFERROR(__xludf.DUMMYFUNCTION("""COMPUTED_VALUE"""),66.0) -> 66 | J47: =IFERROR(__xludf.DUMMYFUNCTION("""COMPUTED_VALUE"""),660.0) -> 660 | K47: =IFERROR(__xludf.DUMMYFUNCTION("""COMPUTED_VALUE"""),43234.0) -> 43234 | L47: =IFERROR(__xludf.DUMMYFUNCTION("""COMPUTED_VALUE"""),"FIP Engineering") -> FIP Engineering | M47: =IFERROR(__xludf.DUMMYFUNCTION("""COMPUTED_VALUE"""),"Joko Nugroho") -> Joko Nugroho | N47: =IFERROR(__xludf.DUMMYFUNCTION("""COMPUTED_VALUE"""),"FIP Engineering") -> FIP Engineering | O47: =IFERROR(__xludf.DUMMYFUNCTION("""COMPUTED_VALUE"""),"FIP-DOM-000-11304-OS00001-INA-000000") -> FIP-DOM-000-11304-OS00001-INA-000000 | P47: =IFERROR(__xludf.DUMMYFUNCTION("""COMPUTED_VALUE"""),"PO Closed") -> PO Closed | Q47: =IFERROR(__xludf.DUMMYFUNCTION("""COMPUTED_VALUE"""),"GL1804055") -> GL1804055 | R47: =IFERROR(__xludf.DUMMYFUNCTION("""COMPUTED_VALUE"""),43161.0) -> 43161 | S47: =IFERROR(__xludf.DUMMYFUNCTION("""COMPUTED_VALUE"""),"-") -> - | T47: =IFERROR(__xludf.DUMMYFUNCTION("""COMPUTED_VALUE"""),43347.0) -> 43347
A48: =IFERROR(__xludf.DUMMYFUNCTION("""COMPUTED_VALUE"""),"181750073-5") -> 181750073-5 | B48: =IFERROR(__xludf.DUMMYFUNCTION("""COMPUTED_VALUE"""),"181750073 - Approved") -> 181750073 - Approved | C48: =IFERROR(__xludf.DUMMYFUNCTION("""COMPUTED_VALUE"""),5.0) -> 5 | D48: =IFERROR(__xludf.DUMMYFUNCTION("""COMPUTED_VALUE"""),"O-14617-00") -> O-14617-00 | E48: =IFERROR(__xludf.DUMMYFUNCTION("""COMPUTED_VALUE"""),"Solenoid valve 2/2 ways NC 4,5mm; ; c/n 28582;") -> Solenoid valve 2/2 ways NC 4,5mm; ; c/n 28582; | F48: =IFERROR(__xludf.DUMMYFUNCTION("""COMPUTED_VALUE"""),4.0) -> 4 | G48: =IFERROR(__xludf.DUMMYFUNCTION("""COMPUTED_VALUE"""),"Unit") -> Unit | H48: =IFERROR(__xludf.DUMMYFUNCTION("""COMPUTED_VALUE"""),"EUR") -> EUR | I48: =IFERROR(__xludf.DUMMYFUNCTION("""COMPUTED_VALUE"""),88.0) -> 88 | J48: =IFERROR(__xludf.DUMMYFUNCTION("""COMPUTED_VALUE"""),352.0) -> 352 | K48: =IFERROR(__xludf.DUMMYFUNCTION("""COMPUTED_VALUE"""),43234.0) -> 43234 | L48: =IFERROR(__xludf.DUMMYFUNCTION("""COMPUTED_VALUE"""),"FIP Engineering") -> FIP Engineering | M48: =IFERROR(__xludf.DUMMYFUNCTION("""COMPUTED_VALUE"""),"Joko Nugroho") -> Joko Nugroho | N48: =IFERROR(__xludf.DUMMYFUNCTION("""COMPUTED_VALUE"""),"FIP Engineering") -> FIP Engineering | O48: =IFERROR(__xludf.DUMMYFUNCTION("""COMPUTED_VALUE"""),"FIP-DOM-000-11304-OS00001-INA-000000") -> FIP-DOM-000-11304-OS00001-INA-000000 | P48: =IFERROR(__xludf.DUMMYFUNCTION("""COMPUTED_VALUE"""),"PO Closed") -> PO Closed | Q48: =IFERROR(__xludf.DUMMYFUNCTION("""COMPUTED_VALUE"""),"GL1804055") -> GL1804055 | R48: =IFERROR(__xludf.DUMMYFUNCTION("""COMPUTED_VALUE"""),43161.0) -> 43161 | S48: =IFERROR(__xludf.DUMMYFUNCTION("""COMPUTED_VALUE"""),"-") -> - | T48: =IFERROR(__xludf.DUMMYFUNCTION("""COMPUTED_VALUE"""),43347.0) -> 43347
A49: =IFERROR(__xludf.DUMMYFUNCTION("""COMPUTED_VALUE"""),"181750073-6") -> 181750073-6 | B49: =IFERROR(__xludf.DUMMYFUNCTION("""COMPUTED_VALUE"""),"181750073 - Approved") -> 181750073 - Approved | C49: =IFERROR(__xludf.DUMMYFUNCTION("""COMPUTED_VALUE"""),6.0) -> 6 | D49: =IFERROR(__xludf.DUMMYFUNCTION("""COMPUTED_VALUE"""),"O-15905-00") -> O-15905-00 | E49: =IFERROR(__xludf.DUMMYFUNCTION("""COMPUTED_VALUE"""),"Temperature probe model PT100; single element, 3 wires diameter 3mm, length 250mm, Total silicone ca; ; ;") -> Temperature probe model PT100; single element, 3 wires diameter 3mm, length 250mm, Total silicone ca; ; ; | F49: =IFERROR(__xludf.DUMMYFUNCTION("""COMPUTED_VALUE"""),1.0) -> 1 | G49: =IFERROR(__xludf.DUMMYFUNCTION("""COMPUTED_VALUE"""),"Unit") -> Unit | H49: =IFERROR(__xludf.DUMMYFUNCTION("""COMPUTED_VALUE"""),"EUR") -> EUR | I49: =IFERROR(__xludf.DUMMYFUNCTION("""COMPUTED_VALUE"""),296.0) -> 296 | J49: =IFERROR(__xludf.DUMMYFUNCTION("""COMPUTED_VALUE"""),296.0) -> 296 | K49: =IFERROR(__xludf.DUMMYFUNCTION("""COMPUTED_VALUE"""),43234.0) -> 43234 | L49: =IFERROR(__xludf.DUMMYFUNCTION("""COMPUTED_VALUE"""),"FIP Engineering") -> FIP Engineering | M49: =IFERROR(__xludf.DUMMYFUNCTION("""COMPUTED_VALUE"""),"Joko Nugroho") -> Joko Nugroho | N49: =IFERROR(__xludf.DUMMYFUNCTION("""COMPUTED_VALUE"""),"FIP Engineering") -> FIP Engineering | O49: =IFERROR(__xludf.DUMMYFUNCTION("""COMPUTED_VALUE"""),"FIP-DOM-000-11304-OS00001-INA-000000") -> FIP-DOM-000-11304-OS00001-INA-000000 | P49: =IFERROR(__xludf.DUMMYFUNCTION("""COMPUTED_VALUE"""),"PO Closed") -> PO Closed | Q49: =IFERROR(__xludf.DUMMYFUNCTION("""COMPUTED_VALUE"""),"GL1804055") -> GL1804055 | R49: =IFERROR(__xludf.DUMMYFUNCTION("""COMPUTED_VALUE"""),43161.0) -> 43161 | S49: =IFERROR(__xludf.DUMMYFUNCTION("""COMPUTED_VALUE"""),"-") -> - | T49: =IFERROR(__xludf.DUMMYFUNCTION("""COMPUTED_VALUE"""),43347.0) -> 43347
A50: =IFERROR(__xludf.DUMMYFUNCTION("""COMPUTED_VALUE"""),"181750073-7") -> 181750073-7 | B50: =IFERROR(__xludf.DUMMYFUNCTION("""COMPUTED_VALUE"""),"181750073 - Approved") -> 181750073 - Approved | C50: =IFERROR(__xludf.DUMMYFUNCTION("""COMPUTED_VALUE"""),7.0) -> 7 | D50: =IFERROR(__xludf.DUMMYFUNCTION("""COMPUTED_VALUE"""),"S-60002-00") -> S-60002-00 | E50: =IFERROR(__xludf.DUMMYFUNCTION("""COMPUTED_VALUE"""),"Packaging") -> Packaging | F50: =IFERROR(__xludf.DUMMYFUNCTION("""COMPUTED_VALUE"""),1.0) -> 1 | G50: =IFERROR(__xludf.DUMMYFUNCTION("""COMPUTED_VALUE"""),"Lot") -> Lot | H50: =IFERROR(__xludf.DUMMYFUNCTION("""COMPUTED_VALUE"""),"EUR") -> EUR | I50: =IFERROR(__xludf.DUMMYFUNCTION("""COMPUTED_VALUE"""),85.0) -> 85 | J50: =IFERROR(__xludf.DUMMYFUNCTION("""COMPUTED_VALUE"""),85.0) -> 85 | K50: =IFERROR(__xludf.DUMMYFUNCTION("""COMPUTED_VALUE"""),43234.0) -> 43234 | L50: =IFERROR(__xludf.DUMMYFUNCTION("""COMPUTED_VALUE"""),"FIP General") -> FIP General | M50: =IFERROR(__xludf.DUMMYFUNCTION("""COMPUTED_VALUE"""),"Joko Nugroho") -> Joko Nugroho | N50: =IFERROR(__xludf.DUMMYFUNCTION("""COMPUTED_VALUE"""),"FIP Engineering") -> FIP Engineering | O50: =IFERROR(__xludf.DUMMYFUNCTION("""COMPUTED_VALUE"""),"FIP-DOM-ENG-51508-0000000-INA-000000") -> FIP-DOM-ENG-51508-0000000-INA-000000 | P50: =IFERROR(__xludf.DUMMYFUNCTION("""COMPUTED_VALUE"""),"PO Closed") -> PO Closed | Q50: =IFERROR(__xludf.DUMMYFUNCTION("""COMPUTED_VALUE"""),"GL1804055") -> GL1804055 | R50: =IFERROR(__xludf.DUMMYFUNCTION("""COMPUTED_VALUE"""),43161.0) -> 43161 | S50: =IFERROR(__xludf.DUMMYFUNCTION("""COMPUTED_VALUE"""),"-") -> - | T50: =IFERROR(__xludf.DUMMYFUNCTION("""COMPUTED_VALUE"""),43347.0) -> 43347
A51: =IFERROR(__xludf.DUMMYFUNCTION("""COMPUTED_VALUE"""),"181750075-4") -> 181750075-4 | B51: =IFERROR(__xludf.DUMMYFUNCTION("""COMPUTED_VALUE"""),"181750075 - Approved") -> 181750075 - Approved | C51: =IFERROR(__xludf.DUMMYFUNCTION("""COMPUTED_VALUE"""),4.0) -> 4 | D51: =IFERROR(__xludf.DUMMYFUNCTION("""COMPUTED_VALUE"""),"S-60002-00") -> S-60002-00 | E51: =IFERROR(__xludf.DUMMYFUNCTION("""COMPUTED_VALUE"""),"Ferrule Set; Gasket, Clamp Set; Mat SUS 304 dia 1""") -> Ferrule Set; Gasket, Clamp Set; Mat SUS 304 dia 1" | F51: =IFERROR(__xludf.DUMMYFUNCTION("""COMPUTED_VALUE"""),1.0) -> 1 | G51: =IFERROR(__xludf.DUMMYFUNCTION("""COMPUTED_VALUE"""),"Lot") -> Lot | H51: =IFERROR(__xludf.DUMMYFUNCTION("""COMPUTED_VALUE"""),"IDR") -> IDR | I51: =IFERROR(__xludf.DUMMYFUNCTION("""COMPUTED_VALUE"""),377000.0) -> 377000 | J51: =IFERROR(__xludf.DUMMYFUNCTION("""COMPUTED_VALUE"""),377000.0) -> 377000 | K51: =IFERROR(__xludf.DUMMYFUNCTION("""COMPUTED_VALUE"""),43182.0) -> 43182 | L51: =IFERROR(__xludf.DUMMYFUNCTION("""COMPUTED_VALUE"""),"FIP General") -> FIP General | M51: =IFERROR(__xludf.DUMMYFUNCTION("""COMPUTED_VALUE"""),"Joko Nugroho") -> Joko Nugroho | N51: =IFERROR(__xludf.DUMMYFUNCTION("""COMPUTED_VALUE"""),"FIP Engineering") -> FIP Engineering | O51: =IFERROR(__xludf.DUMMYFUNCTION("""COMPUTED_VALUE"""),"FIP-DOM-ENG-51508-0000000-INA-000000") -> FIP-DOM-ENG-51508-0000000-INA-000000 | P51: =IFERROR(__xludf.DUMMYFUNCTION("""COMPUTED_VALUE"""),"PO Closed") -> PO Closed | Q51: =IFERROR(__xludf.DUMMYFUNCTION("""COMPUTED_VALUE"""),"GL1804002") -> GL1804002 | R51: =IFERROR(__xludf.DUMMYFUNCTION("""COMPUTED_VALUE"""),43163.0) -> 43163 | S51: =IFERROR(__xludf.DUMMYFUNCTION("""COMPUTED_VALUE"""),"-") -> - | T51: =IFERROR(__xludf.DUMMYFUNCTION("""COMPUTED_VALUE"""),43216.0) -> 43216
A52: =IFERROR(__xludf.DUMMYFUNCTION("""COMPUTED_VALUE"""),"181750075-5") -> 181750075-5 | B52: =IFERROR(__xludf.DUMMYFUNCTION("""COMPUTED_VALUE"""),"181750075 - Approved") -> 181750075 - Approved | C52: =IFERROR(__xludf.DUMMYFUNCTION("""COMPUTED_VALUE"""),5.0) -> 5 | D52: =IFERROR(__xludf.DUMMYFUNCTION("""COMPUTED_VALUE"""),"S-60002-00") -> S-60002-00 | E52: =IFERROR(__xludf.DUMMYFUNCTION("""COMPUTED_VALUE"""),"Elbow SCH 1"" 304 SUS") -> Elbow SCH 1" 304 SUS | F52: =IFERROR(__xludf.DUMMYFUNCTION("""COMPUTED_VALUE"""),1.0) -> 1 | G52: =IFERROR(__xludf.DUMMYFUNCTION("""COMPUTED_VALUE"""),"Lot") -> Lot | H52: =IFERROR(__xludf.DUMMYFUNCTION("""COMPUTED_VALUE"""),"IDR") -> IDR | I52: =IFERROR(__xludf.DUMMYFUNCTION("""COMPUTED_VALUE"""),65000.0) -> 65000 | J52: =IFERROR(__xludf.DUMMYFUNCTION("""COMPUTED_VALUE"""),65000.0) -> 65000 | K52: =IFERROR(__xludf.DUMMYFUNCTION("""COMPUTED_VALUE"""),43182.0) -> 43182 | L52: =IFERROR(__xludf.DUMMYFUNCTION("""COMPUTED_VALUE"""),"FIP General") -> FIP General | M52: =IFERROR(__xludf.DUMMYFUNCTION("""COMPUTED_VALUE"""),"Joko Nugroho") -> Joko Nugroho | N52: =IFERROR(__xludf.DUMMYFUNCTION("""COMPUTED_VALUE"""),"FIP Engineering") -> FIP Engineering | O52: =IFERROR(__xludf.DUMMYFUNCTION("""COMPUTED_VALUE"""),"FIP-DOM-ENG-51508-0000000-INA-000000") -> FIP-DOM-ENG-51508-0000000-INA-000000 | P52: =IFERROR(__xludf.DUMMYFUNCTION("""COMPUTED_VALUE"""),"PO Closed") -> PO Closed | Q52: =IFERROR(__xludf.DUMMYFUNCTION("""COMPUTED_VALUE"""),"GL1804002") -> GL1804002 | R52: =IFERROR(__xludf.DUMMYFUNCTION("""COMPUTED_VALUE"""),43163.0) -> 43163 | S52: =IFERROR(__xludf.DUMMYFUNCTION("""COMPUTED_VALUE"""),"-") -> - | T52: =IFERROR(__xludf.DUMMYFUNCTION("""COMPUTED_VALUE"""),43216.0) -> 43216
A53: =IFERROR(__xludf.DUMMYFUNCTION("""COMPUTED_VALUE"""),"181750074-1") -> 181750074-1 | B53: =IFERROR(__xludf.DUMMYFUNCTION("""COMPUTED_VALUE"""),"181750074 - Approved") -> 181750074 - Approved | C53: =IFERROR(__xludf.DUMMYFUNCTION("""COMPUTED_VALUE"""),1.0) -> 1 | D53: =IFERROR(__xludf.DUMMYFUNCTION("""COMPUTED_VALUE"""),"S-60002-00") -> S-60002-00 | E53: =IFERROR(__xludf.DUMMYFUNCTION("""COMPUTED_VALUE"""),"Material Workshop; Hollow SUS 304 30x30x2.0 mm") -> Material Workshop; Hollow SUS 304 30x30x2.0 mm | F53: =IFERROR(__xludf.DUMMYFUNCTION("""COMPUTED_VALUE"""),4.0) -> 4 | G53: =IFERROR(__xludf.DUMMYFUNCTION("""COMPUTED_VALUE"""),"Lot") -> Lot | H53: =IFERROR(__xludf.DUMMYFUNCTION("""COMPUTED_VALUE"""),"IDR") -> IDR | I53: =IFERROR(__xludf.DUMMYFUNCTION("""COMPUTED_VALUE"""),925000.0) -> 925000 | J53: =IFERROR(__xludf.DUMMYFUNCTION("""COMPUTED_VALUE"""),3700000.0) -> 3700000 | K53: =IFERROR(__xludf.DUMMYFUNCTION("""COMPUTED_VALUE"""),43182.0) -> 43182 | L53: =IFERROR(__xludf.DUMMYFUNCTION("""COMPUTED_VALUE"""),"FIP General") -> FIP General | M53: =IFERROR(__xludf.DUMMYFUNCTION("""COMPUTED_VALUE"""),"Joko Nugroho") -> Joko Nugroho | N53: =IFERROR(__xludf.DUMMYFUNCTION("""COMPUTED_VALUE"""),"FIP Engineering") -> FIP Engineering | O53: =IFERROR(__xludf.DUMMYFUNCTION("""COMPUTED_VALUE"""),"FIP-DOM-ENG-51508-0000000-INA-000000") -> FIP-DOM-ENG-51508-0000000-INA-000000 | P53: =IFERROR(__xludf.DUMMYFUNCTION("""COMPUTED_VALUE"""),"PO Closed") -> PO Closed | Q53: =IFERROR(__xludf.DUMMYFUNCTION("""COMPUTED_VALUE"""),"GL1804002") -> GL1804002 | R53: =IFERROR(__xludf.DUMMYFUNCTION("""COMPUTED_VALUE"""),43163.0) -> 43163 | S53: =IFERROR(__xludf.DUMMYFUNCTION("""COMPUTED_VALUE"""),"-") -> - | T53: =IFERROR(__xludf.DUMMYFUNCTION("""COMPUTED_VALUE"""),43216.0) -> 43216
A54: =IFERROR(__xludf.DUMMYFUNCTION("""COMPUTED_VALUE"""),"181750074-2") -> 181750074-2 | B54: =IFERROR(__xludf.DUMMYFUNCTION("""COMPUTED_VALUE"""),"181750074 - Approved") -> 181750074 - Approved | C54: =IFERROR(__xludf.DUMMYFUNCTION("""COMPUTED_VALUE"""),2.0) -> 2 | D54: =IFERROR(__xludf.DUMMYFUNCTION("""COMPUTED_VALUE"""),"S-60002-00") -> S-60002-00 | E54: =IFERROR(__xludf.DUMMYFUNCTION("""COMPUTED_VALUE"""),"Material Workshop; Leveling Feet Rubber (Foot Adjuster) M12 SUS 304") -> Material Workshop; Leveling Feet Rubber (Foot Adjuster) M12 SUS 304 | F54: =IFERROR(__xludf.DUMMYFUNCTION("""COMPUTED_VALUE"""),8.0) -> 8 | G54: =IFERROR(__xludf.DUMMYFUNCTION("""COMPUTED_VALUE"""),"Lot") -> Lot | H54: =IFERROR(__xludf.DUMMYFUNCTION("""COMPUTED_VALUE"""),"IDR") -> IDR | I54: =IFERROR(__xludf.DUMMYFUNCTION("""COMPUTED_VALUE"""),175000.0) -> 175000 | J54: =IFERROR(__xludf.DUMMYFUNCTION("""COMPUTED_VALUE"""),1400000.0) -> 1400000 | K54: =IFERROR(__xludf.DUMMYFUNCTION("""COMPUTED_VALUE"""),43182.0) -> 43182 | L54: =IFERROR(__xludf.DUMMYFUNCTION("""COMPUTED_VALUE"""),"FIP General") -> FIP General | M54: =IFERROR(__xludf.DUMMYFUNCTION("""COMPUTED_VALUE"""),"Joko Nugroho") -> Joko Nugroho | N54: =IFERROR(__xludf.DUMMYFUNCTION("""COMPUTED_VALUE"""),"FIP Engineering") -> FIP Engineering | O54: =IFERROR(__xludf.DUMMYFUNCTION("""COMPUTED_VALUE"""),"FIP-DOM-ENG-51508-0000000-INA-000000") -> FIP-DOM-ENG-51508-0000000-INA-000000 | P54: =IFERROR(__xludf.DUMMYFUNCTION("""COMPUTED_VALUE"""),"PO Closed") -> PO Closed | Q54: =IFERROR(__xludf.DUMMYFUNCTION("""COMPUTED_VALUE"""),"GL1804002") -> GL1804002 | R54: =IFERROR(__xludf.DUMMYFUNCTION("""COMPUTED_VALUE"""),43163.0) -> 43163 | S54: =IFERROR(__xludf.DUMMYFUNCTION("""COMPUTED_VALUE"""),"-") -> - | T54: =IFERROR(__xludf.DUMMYFUNCTION("""COMPUTED_VALUE"""),43216.0) -> 43216
A55: =IFERROR(__xludf.DUMMYFUNCTION("""COMPUTED_VALUE"""),"181750074-3") -> 181750074-3 | B55: =IFERROR(__xludf.DUMMYFUNCTION("""COMPUTED_VALUE"""),"181750074 - Approved") -> 181750074 - Approved | C55: =IFERROR(__xludf.DUMMYFUNCTION("""COMPUTED_VALUE"""),3.0) -> 3 | D55: =IFERROR(__xludf.DUMMYFUNCTION("""COMPUTED_VALUE"""),"S-60002-00") -> S-60002-00 | E55: =IFERROR(__xludf.DUMMYFUNCTION("""COMPUTED_VALUE"""),"Material Workshop; Ring Dop Pipa 1"" SUS 304") -> Material Workshop; Ring Dop Pipa 1" SUS 304 | F55: =IFERROR(__xludf.DUMMYFUNCTION("""COMPUTED_VALUE"""),4.0) -> 4 | G55: =IFERROR(__xludf.DUMMYFUNCTION("""COMPUTED_VALUE"""),"Lot") -> Lot | H55: =IFERROR(__xludf.DUMMYFUNCTION("""COMPUTED_VALUE"""),"IDR") -> IDR | I55: =IFERROR(__xludf.DUMMYFUNCTION("""COMPUTED_VALUE"""),25000.0) -> 25000 | J55: =IFERROR(__xludf.DUMMYFUNCTION("""COMPUTED_VALUE"""),100000.0) -> 100000 | K55: =IFERROR(__xludf.DUMMYFUNCTION("""COMPUTED_VALUE"""),43182.0) -> 43182 | L55: =IFERROR(__xludf.DUMMYFUNCTION("""COMPUTED_VALUE"""),"FIP General") -> FIP General | M55: =IFERROR(__xludf.DUMMYFUNCTION("""COMPUTED_VALUE"""),"Joko Nugroho") -> Joko Nugroho | N55: =IFERROR(__xludf.DUMMYFUNCTION("""COMPUTED_VALUE"""),"FIP Engineering") -> FIP Engineering | O55: =IFERROR(__xludf.DUMMYFUNCTION("""COMPUTED_VALUE"""),"FIP-DOM-ENG-51508-0000000-INA-000000") -> FIP-DOM-ENG-51508-0000000-INA-000000 | P55: =IFERROR(__xludf.DUMMYFUNCTION("""COMPUTED_VALUE"""),"PO Closed") -> PO Closed | Q55: =IFERROR(__xludf.DUMMYFUNCTION("""COMPUTED_VALUE"""),"GL1804002") -> GL1804002 | R55: =IFERROR(__xludf.DUMMYFUNCTION("""COMPUTED_VALUE"""),43163.0) -> 43163 | S55: =IFERROR(__xludf.DUMMYFUNCTION("""COMPUTED_VALUE"""),"-") -> - | T55: =IFERROR(__xludf.DUMMYFUNCTION("""COMPUTED_VALUE"""),43216.0) -> 43216
A56: =IFERROR(__xludf.DUMMYFUNCTION("""COMPUTED_VALUE"""),"181750074-4") -> 181750074-4 | B56: =IFERROR(__xludf.DUMMYFUNCTION("""COMPUTED_VALUE"""),"181750074 - Approved") -> 181750074 - Approved | C56: =IFERROR(__xludf.DUMMYFUNCTION("""COMPUTED_VALUE"""),4.0) -> 4 | D56: =IFERROR(__xludf.DUMMYFUNCTION("""COMPUTED_VALUE"""),"S-60002-00") -> S-60002-00 | E56: =IFERROR(__xludf.DUMMYFUNCTION("""COMPUTED_VALUE"""),"Material Workshop; Ferrule SUS 304 1""") -> Material Workshop; Ferrule SUS 304 1" | F56: =IFERROR(__xludf.DUMMYFUNCTION("""COMPUTED_VALUE"""),2.0) -> 2 | G56: =IFERROR(__xludf.DUMMYFUNCTION("""COMPUTED_VALUE"""),"Lot") -> Lot | H56: =IFERROR(__xludf.DUMMYFUNCTION("""COMPUTED_VALUE"""),"IDR") -> IDR | I56: =IFERROR(__xludf.DUMMYFUNCTION("""COMPUTED_VALUE"""),375000.0) -> 375000 | J56: =IFERROR(__xludf.DUMMYFUNCTION("""COMPUTED_VALUE"""),750000.0) -> 750000 | K56: =IFERROR(__xludf.DUMMYFUNCTION("""COMPUTED_VALUE"""),43182.0) -> 43182 | L56: =IFERROR(__xludf.DUMMYFUNCTION("""COMPUTED_VALUE"""),"FIP General") -> FIP General | M56: =IFERROR(__xludf.DUMMYFUNCTION("""COMPUTED_VALUE"""),"Joko Nugroho") -> Joko Nugroho | N56: =IFERROR(__xludf.DUMMYFUNCTION("""COMPUTED_VALUE"""),"FIP Engineering") -> FIP Engineering | O56: =IFERROR(__xludf.DUMMYFUNCTION("""COMPUTED_VALUE"""),"FIP-DOM-ENG-51508-0000000-INA-000000") -> FIP-DOM-ENG-51508-0000000-INA-000000 | P56: =IFERROR(__xludf.DUMMYFUNCTION("""COMPUTED_VALUE"""),"PO Closed") -> PO Closed | Q56: =IFERROR(__xludf.DUMMYFUNCTION("""COMPUTED_VALUE"""),"GL1804002") -> GL1804002 | R56: =IFERROR(__xludf.DUMMYFUNCTION("""COMPUTED_VALUE"""),43163.0) -> 43163 | S56: =IFERROR(__xludf.DUMMYFUNCTION("""COMPUTED_VALUE"""),"-") -> - | T56: =IFERROR(__xludf.DUMMYFUNCTION("""COMPUTED_VALUE"""),43216.0) -> 43216
A57: =IFERROR(__xludf.DUMMYFUNCTION("""COMPUTED_VALUE"""),"181750074-5") -> 181750074-5 | B57: =IFERROR(__xludf.DUMMYFUNCTION("""COMPUTED_VALUE"""),"181750074 - Approved") -> 181750074 - Approved | C57: =IFERROR(__xludf.DUMMYFUNCTION("""COMPUTED_VALUE"""),5.0) -> 5 | D57: =IFERROR(__xludf.DUMMYFUNCTION("""COMPUTED_VALUE"""),"S-60002-00") -> S-60002-00 | E57: =IFERROR(__xludf.DUMMYFUNCTION("""COMPUTED_VALUE"""),"Material Workshop; Elbow SCH SUS 304 1""") -> Material Workshop; Elbow SCH SUS 304 1" | F57: =IFERROR(__xludf.DUMMYFUNCTION("""COMPUTED_VALUE"""),4.0) -> 4 | G57: =IFERROR(__xludf.DUMMYFUNCTION("""COMPUTED_VALUE"""),"Lot") -> Lot | H57: =IFERROR(__xludf.DUMMYFUNCTION("""COMPUTED_VALUE"""),"IDR") -> IDR | I57: =IFERROR(__xludf.DUMMYFUNCTION("""COMPUTED_VALUE"""),75000.0) -> 75000 | J57: =IFERROR(__xludf.DUMMYFUNCTION("""COMPUTED_VALUE"""),300000.0) -> 300000 | K57: =IFERROR(__xludf.DUMMYFUNCTION("""COMPUTED_VALUE"""),43182.0) -> 43182 | L57: =IFERROR(__xludf.DUMMYFUNCTION("""COMPUTED_VALUE"""),"FIP General") -> FIP General | M57: =IFERROR(__xludf.DUMMYFUNCTION("""COMPUTED_VALUE"""),"Joko Nugroho") -> Joko Nugroho | N57: =IFERROR(__xludf.DUMMYFUNCTION("""COMPUTED_VALUE"""),"FIP Engineering") -> FIP Engineering | O57: =IFERROR(__xludf.DUMMYFUNCTION("""COMPUTED_VALUE"""),"FIP-DOM-ENG-51508-0000000-INA-000000") -> FIP-DOM-ENG-51508-0000000-INA-000000 | P57: =IFERROR(__xludf.DUMMYFUNCTION("""COMPUTED_VALUE"""),"PO Closed") -> PO Closed | Q57: =IFERROR(__xludf.DUMMYFUNCTION("""COMPUTED_VALUE"""),"GL1804002") -> GL1804002 | R57: =IFERROR(__xludf.DUMMYFUNCTION("""COMPUTED_VALUE"""),43163.0) -> 43163 | S57: =IFERROR(__xludf.DUMMYFUNCTION("""COMPUTED_VALUE"""),"-") -> - | T57: =IFERROR(__xludf.DUMMYFUNCTION("""COMPUTED_VALUE"""),43216.0) -> 43216
A58: =IFERROR(__xludf.DUMMYFUNCTION("""COMPUTED_VALUE"""),"181750074-6") -> 181750074-6 | B58: =IFERROR(__xludf.DUMMYFUNCTION("""COMPUTED_VALUE"""),"181750074 - Approved") -> 181750074 - Approved | C58: =IFERROR(__xludf.DUMMYFUNCTION("""COMPUTED_VALUE"""),6.0) -> 6 | D58: =IFERROR(__xludf.DUMMYFUNCTION("""COMPUTED_VALUE"""),"S-60002-00") -> S-60002-00 | E58: =IFERROR(__xludf.DUMMYFUNCTION("""COMPUTED_VALUE"""),"Material for Pemasangan RH controller di API room; Junction box ; 120x120x100mm") -> Material for Pemasangan RH controller di API room; Junction box ; 120x120x100mm | F58: =IFERROR(__xludf.DUMMYFUNCTION("""COMPUTED_VALUE"""),3.0) -> 3 | G58: =IFERROR(__xludf.DUMMYFUNCTION("""COMPUTED_VALUE"""),"Lot") -> Lot | H58: =IFERROR(__xludf.DUMMYFUNCTION("""COMPUTED_VALUE"""),"IDR") -> IDR | I58: =IFERROR(__xludf.DUMMYFUNCTION("""COMPUTED_VALUE"""),450000.0) -> 450000 | J58: =IFERROR(__xludf.DUMMYFUNCTION("""COMPUTED_VALUE"""),1350000.0) -> 1350000 | K58: =IFERROR(__xludf.DUMMYFUNCTION("""COMPUTED_VALUE"""),43182.0) -> 43182 | L58: =IFERROR(__xludf.DUMMYFUNCTION("""COMPUTED_VALUE"""),"FIP General") -> FIP General | M58: =IFERROR(__xludf.DUMMYFUNCTION("""COMPUTED_VALUE"""),"Joko Nugroho") -> Joko Nugroho | N58: =IFERROR(__xludf.DUMMYFUNCTION("""COMPUTED_VALUE"""),"FIP Engineering") -> FIP Engineering | O58: =IFERROR(__xludf.DUMMYFUNCTION("""COMPUTED_VALUE"""),"FIP-DOM-ENG-51508-0000000-INA-000000") -> FIP-DOM-ENG-51508-0000000-INA-000000 | P58: =IFERROR(__xludf.DUMMYFUNCTION("""COMPUTED_VALUE"""),"PO Closed") -> PO Closed | Q58: =IFERROR(__xludf.DUMMYFUNCTION("""COMPUTED_VALUE"""),"GL1804001") -> GL1804001 | R58: =IFERROR(__xludf.DUMMYFUNCTION("""COMPUTED_VALUE"""),43163.0) -> 43163 | S58: =IFERROR(__xludf.DUMMYFUNCTION("""COMPUTED_VALUE"""),"-") -> - | T58: =IFERROR(__xludf.DUMMYFUNCTION("""COMPUTED_VALUE"""),43195.0) -> 43195
A59: =IFERROR(__xludf.DUMMYFUNCTION("""COMPUTED_VALUE"""),"181750077-1") -> 181750077-1 | B59: =IFERROR(__xludf.DUMMYFUNCTION("""COMPUTED_VALUE"""),"181750077 - Approved") -> 181750077 - Approved | C59: =IFERROR(__xludf.DUMMYFUNCTION("""COMPUTED_VALUE"""),1.0) -> 1 | D59: =IFERROR(__xludf.DUMMYFUNCTION("""COMPUTED_VALUE"""),"S-11614-00") -> S-11614-00 | E59: =IFERROR(__xludf.DUMMYFUNCTION("""COMPUTED_VALUE"""),"Jerigen Putih 5 L") -> Jerigen Putih 5 L | F59: =IFERROR(__xludf.DUMMYFUNCTION("""COMPUTED_VALUE"""),3.0) -> 3 | G59: =IFERROR(__xludf.DUMMYFUNCTION("""COMPUTED_VALUE"""),"Pieces") -> Pieces | H59: =IFERROR(__xludf.DUMMYFUNCTION("""COMPUTED_VALUE"""),"IDR") -> IDR | I59: =IFERROR(__xludf.DUMMYFUNCTION("""COMPUTED_VALUE"""),15000.0) -> 15000 | J59: =IFERROR(__xludf.DUMMYFUNCTION("""COMPUTED_VALUE"""),45000.0) -> 45000 | K59: =IFERROR(__xludf.DUMMYFUNCTION("""COMPUTED_VALUE"""),43189.0) -> 43189 | L59: =IFERROR(__xludf.DUMMYFUNCTION("""COMPUTED_VALUE"""),"FIP General") -> FIP General | M59: =IFERROR(__xludf.DUMMYFUNCTION("""COMPUTED_VALUE"""),"Joko Nugroho") -> Joko Nugroho | N59: =IFERROR(__xludf.DUMMYFUNCTION("""COMPUTED_VALUE"""),"FIP Engineering") -> FIP Engineering | O59: =IFERROR(__xludf.DUMMYFUNCTION("""COMPUTED_VALUE"""),"FIP-DOM-ENG-51302-0000000-INA-000000") -> FIP-DOM-ENG-51302-0000000-INA-000000 | P59: =IFERROR(__xludf.DUMMYFUNCTION("""COMPUTED_VALUE"""),"PO Closed") -> PO Closed | Q59: =IFERROR(__xludf.DUMMYFUNCTION("""COMPUTED_VALUE"""),"GL1803008") -> GL1803008 | R59: =IFERROR(__xludf.DUMMYFUNCTION("""COMPUTED_VALUE"""),43164.0) -> 43164 | S59: =IFERROR(__xludf.DUMMYFUNCTION("""COMPUTED_VALUE"""),"-") -> - | T59: =IFERROR(__xludf.DUMMYFUNCTION("""COMPUTED_VALUE"""),43196.0) -> 43196
A60: =IFERROR(__xludf.DUMMYFUNCTION("""COMPUTED_VALUE"""),"181750077-2") -> 181750077-2 | B60: =IFERROR(__xludf.DUMMYFUNCTION("""COMPUTED_VALUE"""),"181750077 - Approved") -> 181750077 - Approved | C60: =IFERROR(__xludf.DUMMYFUNCTION("""COMPUTED_VALUE"""),2.0) -> 2 | D60: =IFERROR(__xludf.DUMMYFUNCTION("""COMPUTED_VALUE"""),"S-60002-00") -> S-60002-00 | E60: =IFERROR(__xludf.DUMMYFUNCTION("""COMPUTED_VALUE"""),"Karton A3") -> Karton A3 | F60: =IFERROR(__xludf.DUMMYFUNCTION("""COMPUTED_VALUE"""),2.0) -> 2 | G60: =IFERROR(__xludf.DUMMYFUNCTION("""COMPUTED_VALUE"""),"Lot") -> Lot | H60: =IFERROR(__xludf.DUMMYFUNCTION("""COMPUTED_VALUE"""),"IDR") -> IDR | I60: =IFERROR(__xludf.DUMMYFUNCTION("""COMPUTED_VALUE"""),2500.0) -> 2500 | J60: =IFERROR(__xludf.DUMMYFUNCTION("""COMPUTED_VALUE"""),5000.0) -> 5000 | K60: =IFERROR(__xludf.DUMMYFUNCTION("""COMPUTED_VALUE"""),43189.0) -> 43189 | L60: =IFERROR(__xludf.DUMMYFUNCTION("""COMPUTED_VALUE"""),"FIP General") -> FIP General | M60: =IFERROR(__xludf.DUMMYFUNCTION("""COMPUTED_VALUE"""),"Joko Nugroho") -> Joko Nugroho | N60: =IFERROR(__xludf.DUMMYFUNCTION("""COMPUTED_VALUE"""),"FIP Engineering") -> FIP Engineering | O60: =IFERROR(__xludf.DUMMYFUNCTION("""COMPUTED_VALUE"""),"FIP-DOM-ENG-51508-0000000-INA-000000") -> FIP-DOM-ENG-51508-0000000-INA-000000 | P60: =IFERROR(__xludf.DUMMYFUNCTION("""COMPUTED_VALUE"""),"PO Closed") -> PO Closed | Q60: =IFERROR(__xludf.DUMMYFUNCTION("""COMPUTED_VALUE"""),"GL1804003") -> GL1804003 | R60: =IFERROR(__xludf.DUMMYFUNCTION("""COMPUTED_VALUE"""),43164.0) -> 43164 | S60: =IFERROR(__xludf.DUMMYFUNCTION("""COMPUTED_VALUE"""),"-") -> - | T60: =IFERROR(__xludf.DUMMYFUNCTION("""COMPUTED_VALUE"""),43195.0) -> 43195
A61: =IFERROR(__xludf.DUMMYFUNCTION("""COMPUTED_VALUE"""),"181750077-5") -> 181750077-5 | B61: =IFERROR(__xludf.DUMMYFUNCTION("""COMPUTED_VALUE"""),"181750077 - Approved") -> 181750077 - Approved | C61: =IFERROR(__xludf.DUMMYFUNCTION("""COMPUTED_VALUE"""),5.0) -> 5 | D61: =IFERROR(__xludf.DUMMYFUNCTION("""COMPUTED_VALUE"""),"S-60002-00") -> S-60002-00 | E61: =IFERROR(__xludf.DUMMYFUNCTION("""COMPUTED_VALUE"""),"Neeple BPC 4 MS") -> Neeple BPC 4 MS | F61: =IFERROR(__xludf.DUMMYFUNCTION("""COMPUTED_VALUE"""),2.0) -> 2 | G61: =IFERROR(__xludf.DUMMYFUNCTION("""COMPUTED_VALUE"""),"Lot") -> Lot | H61: =IFERROR(__xludf.DUMMYFUNCTION("""COMPUTED_VALUE"""),"IDR") -> IDR | I61: =IFERROR(__xludf.DUMMYFUNCTION("""COMPUTED_VALUE"""),15000.0) -> 15000 | J61: =IFERROR(__xludf.DUMMYFUNCTION("""COMPUTED_VALUE"""),30000.0) -> 30000 | K61: =IFERROR(__xludf.DUMMYFUNCTION("""COMPUTED_VALUE"""),43189.0) -> 43189 | L61: =IFERROR(__xludf.DUMMYFUNCTION("""COMPUTED_VALUE"""),"FIP General") -> FIP General | M61: =IFERROR(__xludf.DUMMYFUNCTION("""COMPUTED_VALUE"""),"Joko Nugroho") -> Joko Nugroho | N61: =IFERROR(__xludf.DUMMYFUNCTION("""COMPUTED_VALUE"""),"FIP Engineering") -> FIP Engineering | O61: =IFERROR(__xludf.DUMMYFUNCTION("""COMPUTED_VALUE"""),"FIP-DOM-ENG-51508-0000000-INA-000000") -> FIP-DOM-ENG-51508-0000000-INA-000000 | P61: =IFERROR(__xludf.DUMMYFUNCTION("""COMPUTED_VALUE"""),"PO Closed") -> PO Closed | Q61: =IFERROR(__xludf.DUMMYFUNCTION("""COMPUTED_VALUE"""),"GL1804003") -> GL1804003 | R61: =IFERROR(__xludf.DUMMYFUNCTION("""COMPUTED_VALUE"""),43164.0) -> 43164 | S61: =IFERROR(__xludf.DUMMYFUNCTION("""COMPUTED_VALUE"""),"-") -> - | T61: =IFERROR(__xludf.DUMMYFUNCTION("""COMPUTED_VALUE"""),43195.0) -> 43195
A62: =IFERROR(__xludf.DUMMYFUNCTION("""COMPUTED_VALUE"""),"181750077-6") -> 181750077-6 | B62: =IFERROR(__xludf.DUMMYFUNCTION("""COMPUTED_VALUE"""),"181750077 - Approved") -> 181750077 - Approved | C62: =IFERROR(__xludf.DUMMYFUNCTION("""COMPUTED_VALUE"""),6.0) -> 6 | D62: =IFERROR(__xludf.DUMMYFUNCTION("""COMPUTED_VALUE"""),"S-60002-00") -> S-60002-00 | E62: =IFERROR(__xludf.DUMMYFUNCTION("""COMPUTED_VALUE"""),"Neeple Selang") -> Neeple Selang | F62: =IFERROR(__xludf.DUMMYFUNCTION("""COMPUTED_VALUE"""),1.0) -> 1 | G62: =IFERROR(__xludf.DUMMYFUNCTION("""COMPUTED_VALUE"""),"Lot") -> Lot | H62: =IFERROR(__xludf.DUMMYFUNCTION("""COMPUTED_VALUE"""),"IDR") -> IDR | I62: =IFERROR(__xludf.DUMMYFUNCTION("""COMPUTED_VALUE"""),12000.0) -> 12000 | J62: =IFERROR(__xludf.DUMMYFUNCTION("""COMPUTED_VALUE"""),12000.0) -> 12000 | K62: =IFERROR(__xludf.DUMMYFUNCTION("""COMPUTED_VALUE"""),43189.0) -> 43189 | L62: =IFERROR(__xludf.DUMMYFUNCTION("""COMPUTED_VALUE"""),"FIP General") -> FIP General | M62: =IFERROR(__xludf.DUMMYFUNCTION("""COMPUTED_VALUE"""),"Joko Nugroho") -> Joko Nugroho | N62: =IFERROR(__xludf.DUMMYFUNCTION("""COMPUTED_VALUE"""),"FIP Engineering") -> FIP Engineering | O62: =IFERROR(__xludf.DUMMYFUNCTION("""COMPUTED_VALUE"""),"FIP-DOM-ENG-51508-0000000-INA-000000") -> FIP-DOM-ENG-51508-0000000-INA-000000 | P62: =IFERROR(__xludf.DUMMYFUNCTION("""COMPUTED_VALUE"""),"PO Closed") -> PO Closed | Q62: =IFERROR(__xludf.DUMMYFUNCTION("""COMPUTED_VALUE"""),"GL1804003") -> GL1804003 | R62: =IFERROR(__xludf.DUMMYFUNCTION("""COMPUTED_VALUE"""),43164.0) -> 43164 | S62: =IFERROR(__xludf.DUMMYFUNCTION("""COMPUTED_VALUE"""),"-") -> - | T62: =IFERROR(__xludf.DUMMYFUNCTION("""COMPUTED_VALUE"""),43195.0) -> 43195
A63: =IFERROR(__xludf.DUMMYFUNCTION("""COMPUTED_VALUE"""),"181750077-7") -> 181750077-7 | B63: =IFERROR(__xludf.DUMMYFUNCTION("""COMPUTED_VALUE"""),"181750077 - Approved") -> 181750077 - Approved | C63: =IFERROR(__xludf.DUMMYFUNCTION("""COMPUTED_VALUE"""),7.0) -> 7 | D63: =IFERROR(__xludf.DUMMYFUNCTION("""COMPUTED_VALUE"""),"S-60002-00") -> S-60002-00 | E63: =IFERROR(__xludf.DUMMYFUNCTION("""COMPUTED_VALUE"""),"Klem Slang") -> Klem Slang | F63: =IFERROR(__xludf.DUMMYFUNCTION("""COMPUTED_VALUE"""),1.0) -> 1 | G63: =IFERROR(__xludf.DUMMYFUNCTION("""COMPUTED_VALUE"""),"Lot") -> Lot | H63: =IFERROR(__xludf.DUMMYFUNCTION("""COMPUTED_VALUE"""),"IDR") -> IDR | I63: =IFERROR(__xludf.DUMMYFUNCTION("""COMPUTED_VALUE"""),3000.0) -> 3000 | J63: =IFERROR(__xludf.DUMMYFUNCTION("""COMPUTED_VALUE"""),3000.0) -> 3000 | K63: =IFERROR(__xludf.DUMMYFUNCTION("""COMPUTED_VALUE"""),43189.0) -> 43189 | L63: =IFERROR(__xludf.DUMMYFUNCTION("""COMPUTED_VALUE"""),"FIP General") -> FIP General | M63: =IFERROR(__xludf.DUMMYFUNCTION("""COMPUTED_VALUE"""),"Joko Nugroho") -> Joko Nugroho | N63: =IFERROR(__xludf.DUMMYFUNCTION("""COMPUTED_VALUE"""),"FIP Engineering") -> FIP Engineering | O63: =IFERROR(__xludf.DUMMYFUNCTION("""COMPUTED_VALUE"""),"FIP-DOM-ENG-51508-0000000-INA-000000") -> FIP-DOM-ENG-51508-0000000-INA-000000 | P63: =IFERROR(__xludf.DUMMYFUNCTION("""COMPUTED_VALUE"""),"PO Closed") -> PO Closed | Q63: =IFERROR(__xludf.DUMMYFUNCTION("""COMPUTED_VALUE"""),"GL1804003") -> GL1804003 | R63: =IFERROR(__xludf.DUMMYFUNCTION("""COMPUTED_VALUE"""),43164.0) -> 43164 | S63: =IFERROR(__xludf.DUMMYFUNCTION("""COMPUTED_VALUE"""),"-") -> - | T63: =IFERROR(__xludf.DUMMYFUNCTION("""COMPUTED_VALUE"""),43195.0) -> 43195
A64: =IFERROR(__xludf.DUMMYFUNCTION("""COMPUTED_VALUE"""),"181750077-8") -> 181750077-8 | B64: =IFERROR(__xludf.DUMMYFUNCTION("""COMPUTED_VALUE"""),"181750077 - Approved") -> 181750077 - Approved | C64: =IFERROR(__xludf.DUMMYFUNCTION("""COMPUTED_VALUE"""),8.0) -> 8 | D64: =IFERROR(__xludf.DUMMYFUNCTION("""COMPUTED_VALUE"""),"S-60002-00") -> S-60002-00 | E64: =IFERROR(__xludf.DUMMYFUNCTION("""COMPUTED_VALUE"""),"BL 2.5 x 15") -> BL 2.5 x 15 | F64: =IFERROR(__xludf.DUMMYFUNCTION("""COMPUTED_VALUE"""),10.0) -> 10 | G64: =IFERROR(__xludf.DUMMYFUNCTION("""COMPUTED_VALUE"""),"Lot") -> Lot | H64: =IFERROR(__xludf.DUMMYFUNCTION("""COMPUTED_VALUE"""),"IDR") -> IDR | I64: =IFERROR(__xludf.DUMMYFUNCTION("""COMPUTED_VALUE"""),2500.0) -> 2500 | J64: =IFERROR(__xludf.DUMMYFUNCTION("""COMPUTED_VALUE"""),25000.0) -> 25000 | K64: =IFERROR(__xludf.DUMMYFUNCTION("""COMPUTED_VALUE"""),43189.0) -> 43189 | L64: =IFERROR(__xludf.DUMMYFUNCTION("""COMPUTED_VALUE"""),"FIP General") -> FIP General | M64: =IFERROR(__xludf.DUMMYFUNCTION("""COMPUTED_VALUE"""),"Joko Nugroho") -> Joko Nugroho | N64: =IFERROR(__xludf.DUMMYFUNCTION("""COMPUTED_VALUE"""),"FIP Engineering") -> FIP Engineering | O64: =IFERROR(__xludf.DUMMYFUNCTION("""COMPUTED_VALUE"""),"FIP-DOM-ENG-51508-0000000-INA-000000") -> FIP-DOM-ENG-51508-0000000-INA-000000 | P64: =IFERROR(__xludf.DUMMYFUNCTION("""COMPUTED_VALUE"""),"PO Closed") -> PO Closed | Q64: =IFERROR(__xludf.DUMMYFUNCTION("""COMPUTED_VALUE"""),"GL1804003") -> GL1804003 | R64: =IFERROR(__xludf.DUMMYFUNCTION("""COMPUTED_VALUE"""),43164.0) -> 43164 | S64: =IFERROR(__xludf.DUMMYFUNCTION("""COMPUTED_VALUE"""),"-") -> - | T64: =IFERROR(__xludf.DUMMYFUNCTION("""COMPUTED_VALUE"""),43195.0) -> 43195
A65: =IFERROR(__xludf.DUMMYFUNCTION("""COMPUTED_VALUE"""),"181750077-9") -> 181750077-9 | B65: =IFERROR(__xludf.DUMMYFUNCTION("""COMPUTED_VALUE"""),"181750077 - Approved") -> 181750077 - Approved | C65: =IFERROR(__xludf.DUMMYFUNCTION("""COMPUTED_VALUE"""),9.0) -> 9 | D65: =IFERROR(__xludf.DUMMYFUNCTION("""COMPUTED_VALUE"""),"S-60002-00") -> S-60002-00 | E65: =IFERROR(__xludf.DUMMYFUNCTION("""COMPUTED_VALUE"""),"Testpen; ; ;") -> Testpen; ; ; | F65: =IFERROR(__xludf.DUMMYFUNCTION("""COMPUTED_VALUE"""),2.0) -> 2 | G65: =IFERROR(__xludf.DUMMYFUNCTION("""COMPUTED_VALUE"""),"Lot") -> Lot | H65: =IFERROR(__xludf.DUMMYFUNCTION("""COMPUTED_VALUE"""),"IDR") -> IDR | I65: =IFERROR(__xludf.DUMMYFUNCTION("""COMPUTED_VALUE"""),8500.0) -> 8500 | J65: =IFERROR(__xludf.DUMMYFUNCTION("""COMPUTED_VALUE"""),17000.0) -> 17000 | K65: =IFERROR(__xludf.DUMMYFUNCTION("""COMPUTED_VALUE"""),43189.0) -> 43189 | L65: =IFERROR(__xludf.DUMMYFUNCTION("""COMPUTED_VALUE"""),"FIP General") -> FIP General | M65: =IFERROR(__xludf.DUMMYFUNCTION("""COMPUTED_VALUE"""),"Joko Nugroho") -> Joko Nugroho | N65: =IFERROR(__xludf.DUMMYFUNCTION("""COMPUTED_VALUE"""),"FIP Engineering") -> FIP Engineering | O65: =IFERROR(__xludf.DUMMYFUNCTION("""COMPUTED_VALUE"""),"FIP-DOM-ENG-51508-0000000-INA-000000") -> FIP-DOM-ENG-51508-0000000-INA-000000 | P65: =IFERROR(__xludf.DUMMYFUNCTION("""COMPUTED_VALUE"""),"PO Closed") -> PO Closed | Q65: =IFERROR(__xludf.DUMMYFUNCTION("""COMPUTED_VALUE"""),"GL1804003") -> GL1804003 | R65: =IFERROR(__xludf.DUMMYFUNCTION("""COMPUTED_VALUE"""),43164.0) -> 43164 | S65: =IFERROR(__xludf.DUMMYFUNCTION("""COMPUTED_VALUE"""),"-") -> - | T65: =IFERROR(__xludf.DUMMYFUNCTION("""COMPUTED_VALUE"""),43195.0) -> 43195
A66: =IFERROR(__xludf.DUMMYFUNCTION("""COMPUTED_VALUE"""),"181750081-1") -> 181750081-1 | B66: =IFERROR(__xludf.DUMMYFUNCTION("""COMPUTED_VALUE"""),"181750081 - Approved") -> 181750081 - Approved | C66: =IFERROR(__xludf.DUMMYFUNCTION("""COMPUTED_VALUE"""),1.0) -> 1 | D66: =IFERROR(__xludf.DUMMYFUNCTION("""COMPUTED_VALUE"""),"S-60002-00") -> S-60002-00 | E66: =IFERROR(__xludf.DUMMYFUNCTION("""COMPUTED_VALUE"""),"Pekerjaan Persiapan; Preliminaries, Mob & Demob dll") -> Pekerjaan Persiapan; Preliminaries, Mob & Demob dll | F66: =IFERROR(__xludf.DUMMYFUNCTION("""COMPUTED_VALUE"""),1.0) -> 1 | G66: =IFERROR(__xludf.DUMMYFUNCTION("""COMPUTED_VALUE"""),"Lot") -> Lot | H66: =IFERROR(__xludf.DUMMYFUNCTION("""COMPUTED_VALUE"""),"IDR") -> IDR | I66: =IFERROR(__xludf.DUMMYFUNCTION("""COMPUTED_VALUE"""),1000000.0) -> 1000000 | J66: =IFERROR(__xludf.DUMMYFUNCTION("""COMPUTED_VALUE"""),1000000.0) -> 1000000 | K66: =IFERROR(__xludf.DUMMYFUNCTION("""COMPUTED_VALUE"""),43192.0) -> 43192 | L66: =IFERROR(__xludf.DUMMYFUNCTION("""COMPUTED_VALUE"""),"FIP General") -> FIP General | M66: =IFERROR(__xludf.DUMMYFUNCTION("""COMPUTED_VALUE"""),"Joko Nugroho") -> Joko Nugroho | N66: =IFERROR(__xludf.DUMMYFUNCTION("""COMPUTED_VALUE"""),"FIP Engineering") -> FIP Engineering | O66: =IFERROR(__xludf.DUMMYFUNCTION("""COMPUTED_VALUE"""),"FIP-DOM-ENG-51508-0000000-INA-000000") -> FIP-DOM-ENG-51508-0000000-INA-000000 | P66: =IFERROR(__xludf.DUMMYFUNCTION("""COMPUTED_VALUE"""),"PO Closed") -> PO Closed | Q66: =IFERROR(__xludf.DUMMYFUNCTION("""COMPUTED_VALUE"""),"GL1804005") -> GL1804005 | R66: =IFERROR(__xludf.DUMMYFUNCTION("""COMPUTED_VALUE"""),43166.0) -> 43166 | S66: =IFERROR(__xludf.DUMMYFUNCTION("""COMPUTED_VALUE"""),"-") -> - | T66: =IFERROR(__xludf.DUMMYFUNCTION("""COMPUTED_VALUE"""),43227.0) -> 43227
A67: =IFERROR(__xludf.DUMMYFUNCTION("""COMPUTED_VALUE"""),"181750081-2") -> 181750081-2 | B67: =IFERROR(__xludf.DUMMYFUNCTION("""COMPUTED_VALUE"""),"181750081 - Approved") -> 181750081 - Approved | C67: =IFERROR(__xludf.DUMMYFUNCTION("""COMPUTED_VALUE"""),2.0) -> 2 | D67: =IFERROR(__xludf.DUMMYFUNCTION("""COMPUTED_VALUE"""),"S-60002-00") -> S-60002-00 | E67: =IFERROR(__xludf.DUMMYFUNCTION("""COMPUTED_VALUE"""),"Pekerjaan Lantai; Injeksi Epoxy;") -> Pekerjaan Lantai; Injeksi Epoxy; | F67: =IFERROR(__xludf.DUMMYFUNCTION("""COMPUTED_VALUE"""),65.0) -> 65 | G67: =IFERROR(__xludf.DUMMYFUNCTION("""COMPUTED_VALUE"""),"Lot") -> Lot | H67: =IFERROR(__xludf.DUMMYFUNCTION("""COMPUTED_VALUE"""),"IDR") -> IDR | I67: =IFERROR(__xludf.DUMMYFUNCTION("""COMPUTED_VALUE"""),125000.0) -> 125000 | J67: =IFERROR(__xludf.DUMMYFUNCTION("""COMPUTED_VALUE"""),8125000.0) -> 8125000 | K67: =IFERROR(__xludf.DUMMYFUNCTION("""COMPUTED_VALUE"""),43192.0) -> 43192 | L67: =IFERROR(__xludf.DUMMYFUNCTION("""COMPUTED_VALUE"""),"FIP General") -> FIP General | M67: =IFERROR(__xludf.DUMMYFUNCTION("""COMPUTED_VALUE"""),"Joko Nugroho") -> Joko Nugroho | N67: =IFERROR(__xludf.DUMMYFUNCTION("""COMPUTED_VALUE"""),"FIP Engineering") -> FIP Engineering | O67: =IFERROR(__xludf.DUMMYFUNCTION("""COMPUTED_VALUE"""),"FIP-DOM-ENG-51508-0000000-INA-000000") -> FIP-DOM-ENG-51508-0000000-INA-000000 | P67: =IFERROR(__xludf.DUMMYFUNCTION("""COMPUTED_VALUE"""),"PO Closed") -> PO Closed | Q67: =IFERROR(__xludf.DUMMYFUNCTION("""COMPUTED_VALUE"""),"GL1804005") -> GL1804005 | R67: =IFERROR(__xludf.DUMMYFUNCTION("""COMPUTED_VALUE"""),43166.0) -> 43166 | S67: =IFERROR(__xludf.DUMMYFUNCTION("""COMPUTED_VALUE"""),"-") -> - | T67: =IFERROR(__xludf.DUMMYFUNCTION("""COMPUTED_VALUE"""),43227.0) -> 43227
A68: =IFERROR(__xludf.DUMMYFUNCTION("""COMPUTED_VALUE"""),"181750080-1") -> 181750080-1 | B68: =IFERROR(__xludf.DUMMYFUNCTION("""COMPUTED_VALUE"""),"181750080 - Approved") -> 181750080 - Approved | C68: =IFERROR(__xludf.DUMMYFUNCTION("""COMPUTED_VALUE"""),1.0) -> 1 | D68: =IFERROR(__xludf.DUMMYFUNCTION("""COMPUTED_VALUE"""),"S-60002-00") -> S-60002-00 | E68: =IFERROR(__xludf.DUMMYFUNCTION("""COMPUTED_VALUE"""),"Mesin Cutting 14"" Type : GCO200 Bosch") -> Mesin Cutting 14" Type : GCO200 Bosch | F68: =IFERROR(__xludf.DUMMYFUNCTION("""COMPUTED_VALUE"""),1.0) -> 1 | G68: =IFERROR(__xludf.DUMMYFUNCTION("""COMPUTED_VALUE"""),"Lot") -> Lot | H68: =IFERROR(__xludf.DUMMYFUNCTION("""COMPUTED_VALUE"""),"IDR") -> IDR | I68: =IFERROR(__xludf.DUMMYFUNCTION("""COMPUTED_VALUE"""),2150000.0) -> 2150000 | J68: =IFERROR(__xludf.DUMMYFUNCTION("""COMPUTED_VALUE"""),2150000.0) -> 2150000 | K68: =IFERROR(__xludf.DUMMYFUNCTION("""COMPUTED_VALUE"""),43180.0) -> 43180 | L68: =IFERROR(__xludf.DUMMYFUNCTION("""COMPUTED_VALUE"""),"FIP General") -> FIP General | M68: =IFERROR(__xludf.DUMMYFUNCTION("""COMPUTED_VALUE"""),"Joko Nugroho") -> Joko Nugroho | N68: =IFERROR(__xludf.DUMMYFUNCTION("""COMPUTED_VALUE"""),"FIP Engineering") -> FIP Engineering | O68: =IFERROR(__xludf.DUMMYFUNCTION("""COMPUTED_VALUE"""),"FIP-DOM-ENG-51508-0000000-INA-000000") -> FIP-DOM-ENG-51508-0000000-INA-000000 | P68: =IFERROR(__xludf.DUMMYFUNCTION("""COMPUTED_VALUE"""),"PO Closed") -> PO Closed | Q68: =IFERROR(__xludf.DUMMYFUNCTION("""COMPUTED_VALUE"""),"GL1804001") -> GL1804001 | R68: =IFERROR(__xludf.DUMMYFUNCTION("""COMPUTED_VALUE"""),43166.0) -> 43166 | S68: =IFERROR(__xludf.DUMMYFUNCTION("""COMPUTED_VALUE"""),"-") -> - | T68: =IFERROR(__xludf.DUMMYFUNCTION("""COMPUTED_VALUE"""),43195.0) -> 43195
A69: =IFERROR(__xludf.DUMMYFUNCTION("""COMPUTED_VALUE"""),"181750080-2") -> 181750080-2 | B69: =IFERROR(__xludf.DUMMYFUNCTION("""COMPUTED_VALUE"""),"181750080 - Approved") -> 181750080 - Approved | C69: =IFERROR(__xludf.DUMMYFUNCTION("""COMPUTED_VALUE"""),2.0) -> 2 | D69: =IFERROR(__xludf.DUMMYFUNCTION("""COMPUTED_VALUE"""),"S-60002-00") -> S-60002-00 | E69: =IFERROR(__xludf.DUMMYFUNCTION("""COMPUTED_VALUE"""),"Mata Cutting 14"" Makita") -> Mata Cutting 14" Makita | F69: =IFERROR(__xludf.DUMMYFUNCTION("""COMPUTED_VALUE"""),2.0) -> 2 | G69: =IFERROR(__xludf.DUMMYFUNCTION("""COMPUTED_VALUE"""),"Lot") -> Lot | H69: =IFERROR(__xludf.DUMMYFUNCTION("""COMPUTED_VALUE"""),"IDR") -> IDR | I69: =IFERROR(__xludf.DUMMYFUNCTION("""COMPUTED_VALUE"""),63000.0) -> 63000 | J69: =IFERROR(__xludf.DUMMYFUNCTION("""COMPUTED_VALUE"""),126000.0) -> 126000 | K69: =IFERROR(__xludf.DUMMYFUNCTION("""COMPUTED_VALUE"""),43180.0) -> 43180 | L69: =IFERROR(__xludf.DUMMYFUNCTION("""COMPUTED_VALUE"""),"FIP General") -> FIP General | M69: =IFERROR(__xludf.DUMMYFUNCTION("""COMPUTED_VALUE"""),"Joko Nugroho") -> Joko Nugroho | N69: =IFERROR(__xludf.DUMMYFUNCTION("""COMPUTED_VALUE"""),"FIP Engineering") -> FIP Engineering | O69: =IFERROR(__xludf.DUMMYFUNCTION("""COMPUTED_VALUE"""),"FIP-DOM-ENG-51508-0000000-INA-000000") -> FIP-DOM-ENG-51508-0000000-INA-000000 | P69: =IFERROR(__xludf.DUMMYFUNCTION("""COMPUTED_VALUE"""),"PO Closed") -> PO Closed | Q69: =IFERROR(__xludf.DUMMYFUNCTION("""COMPUTED_VALUE"""),"GL1804001") -> GL1804001 | R69: =IFERROR(__xludf.DUMMYFUNCTION("""COMPUTED_VALUE"""),43166.0) -> 43166 | S69: =IFERROR(__xludf.DUMMYFUNCTION("""COMPUTED_VALUE"""),"-") -> - | T69: =IFERROR(__xludf.DUMMYFUNCTION("""COMPUTED_VALUE"""),43195.0) -> 43195
A70: =IFERROR(__xludf.DUMMYFUNCTION("""COMPUTED_VALUE"""),"181750080-3") -> 181750080-3 | B70: =IFERROR(__xludf.DUMMYFUNCTION("""COMPUTED_VALUE"""),"181750080 - Approved") -> 181750080 - Approved | C70: =IFERROR(__xludf.DUMMYFUNCTION("""COMPUTED_VALUE"""),3.0) -> 3 | D70: =IFERROR(__xludf.DUMMYFUNCTION("""COMPUTED_VALUE"""),"S-60002-00") -> S-60002-00 | E70: =IFERROR(__xludf.DUMMYFUNCTION("""COMPUTED_VALUE"""),"Penggaris Siku 10x30 cm") -> Penggaris Siku 10x30 cm | F70: =IFERROR(__xludf.DUMMYFUNCTION("""COMPUTED_VALUE"""),1.0) -> 1 | G70: =IFERROR(__xludf.DUMMYFUNCTION("""COMPUTED_VALUE"""),"Lot") -> Lot | H70: =IFERROR(__xludf.DUMMYFUNCTION("""COMPUTED_VALUE"""),"IDR") -> IDR | I70: =IFERROR(__xludf.DUMMYFUNCTION("""COMPUTED_VALUE"""),25000.0) -> 25000 | J70: =IFERROR(__xludf.DUMMYFUNCTION("""COMPUTED_VALUE"""),25000.0) -> 25000 | K70: =IFERROR(__xludf.DUMMYFUNCTION("""COMPUTED_VALUE"""),43180.0) -> 43180 | L70: =IFERROR(__xludf.DUMMYFUNCTION("""COMPUTED_VALUE"""),"FIP General") -> FIP General | M70: =IFERROR(__xludf.DUMMYFUNCTION("""COMPUTED_VALUE"""),"Joko Nugroho") -> Joko Nugroho | N70: =IFERROR(__xludf.DUMMYFUNCTION("""COMPUTED_VALUE"""),"FIP Engineering") -> FIP Engineering | O70: =IFERROR(__xludf.DUMMYFUNCTION("""COMPUTED_VALUE"""),"FIP-DOM-ENG-51508-0000000-INA-000000") -> FIP-DOM-ENG-51508-0000000-INA-000000 | P70: =IFERROR(__xludf.DUMMYFUNCTION("""COMPUTED_VALUE"""),"PO Closed") -> PO Closed | Q70: =IFERROR(__xludf.DUMMYFUNCTION("""COMPUTED_VALUE"""),"GL1804001") -> GL1804001 | R70: =IFERROR(__xludf.DUMMYFUNCTION("""COMPUTED_VALUE"""),43166.0) -> 43166 | S70: =IFERROR(__xludf.DUMMYFUNCTION("""COMPUTED_VALUE"""),"-") -> - | T70: =IFERROR(__xludf.DUMMYFUNCTION("""COMPUTED_VALUE"""),43195.0) -> 43195
A71: =IFERROR(__xludf.DUMMYFUNCTION("""COMPUTED_VALUE"""),"181750080-4") -> 181750080-4 | B71: =IFERROR(__xludf.DUMMYFUNCTION("""COMPUTED_VALUE"""),"181750080 - Approved") -> 181750080 - Approved | C71: =IFERROR(__xludf.DUMMYFUNCTION("""COMPUTED_VALUE"""),4.0) -> 4 | D71: =IFERROR(__xludf.DUMMYFUNCTION("""COMPUTED_VALUE"""),"S-60002-00") -> S-60002-00 | E71: =IFERROR(__xludf.DUMMYFUNCTION("""COMPUTED_VALUE"""),"Pin Punch Set Lipro") -> Pin Punch Set Lipro | F71: =IFERROR(__xludf.DUMMYFUNCTION("""COMPUTED_VALUE"""),1.0) -> 1 | G71: =IFERROR(__xludf.DUMMYFUNCTION("""COMPUTED_VALUE"""),"Lot") -> Lot | H71: =IFERROR(__xludf.DUMMYFUNCTION("""COMPUTED_VALUE"""),"IDR") -> IDR | I71: =IFERROR(__xludf.DUMMYFUNCTION("""COMPUTED_VALUE"""),325000.0) -> 325000 | J71: =IFERROR(__xludf.DUMMYFUNCTION("""COMPUTED_VALUE"""),325000.0) -> 325000 | K71: =IFERROR(__xludf.DUMMYFUNCTION("""COMPUTED_VALUE"""),43180.0) -> 43180 | L71: =IFERROR(__xludf.DUMMYFUNCTION("""COMPUTED_VALUE"""),"FIP General") -> FIP General | M71: =IFERROR(__xludf.DUMMYFUNCTION("""COMPUTED_VALUE"""),"Joko Nugroho") -> Joko Nugroho | N71: =IFERROR(__xludf.DUMMYFUNCTION("""COMPUTED_VALUE"""),"FIP Engineering") -> FIP Engineering | O71: =IFERROR(__xludf.DUMMYFUNCTION("""COMPUTED_VALUE"""),"FIP-DOM-ENG-51508-0000000-INA-000000") -> FIP-DOM-ENG-51508-0000000-INA-000000 | P71: =IFERROR(__xludf.DUMMYFUNCTION("""COMPUTED_VALUE"""),"PO Closed") -> PO Closed | Q71: =IFERROR(__xludf.DUMMYFUNCTION("""COMPUTED_VALUE"""),"GL1804019") -> GL1804019 | R71: =IFERROR(__xludf.DUMMYFUNCTION("""COMPUTED_VALUE"""),43166.0) -> 43166 | S71: =IFERROR(__xludf.DUMMYFUNCTION("""COMPUTED_VALUE"""),"-") -> - | T71: =IFERROR(__xludf.DUMMYFUNCTION("""COMPUTED_VALUE"""),43216.0) -> 43216
